Workbook

Sheet 1. Cover
B2: Travidz — Market Research v10 (TAM / SAM / SOM · Global)
B3: Investor-ready · Prepared 2026 · 5-year horizon · Reconciled to Travidz_Financial_Model_Global_v6.xlsx
B5: PROJECT BRIEF
B6: Product | C6: Travidz — creator-led travel discovery and booking app (UK-first)
B7: ICP | C7: UK leisure travellers 18-44; creator partners with 5k+ engaged followers
B8: Revenue model | C8: 11% gross commission; Stripe 2.9% + £0.20/txn shared off the top; tapered 50/50/50/40/30 creator share by tier
B9: Round | C9: Seed £2.0M → Series A £8.0M (M22) → Series B £20.0M (M44)
B10: Use of funds (seed) | C10: UK engineering & ops team, paid UA, founding-500 incentives, 18-24mo runway
B11: Geography | C11: UK Y1-Y2 · EU-5 Y3 · Global Viral upside Y3-Y5 (10 regions, 1.22Bn travellers)
B13: GLOBAL INPUTS — FX & MACRO
B14: USD → GBP | C14: 0.79 | D14: Bank of England avg 2024-25 [S21]
B15: EUR → GBP | C15: 0.85 | D15: Bank of England avg 2024-25 [S21]
B16: UK CPI assumption | C16: 0.025 | D16: ONS CPI trend 2024-25 [S22]
B17: Discount rate (DCF cross-check) | C17: 0.15 | D17: Standard VC discount for pre-revenue SaaS/marketplace
B19: COMMISSION STRUCTURE (locked to financial model)
B20: Gross commission % charged to operators | C20: 0.11 | D20: Travidz commercial: 11% blended take (post-MoR repricing)
B21: Creator share — Founding tier (first 500) | C21: 0.5 | D21: 50% of 8% to creator
B22: Creator share — Power tier (>£25k rolling GBV) | C22: 0.5 | D22: 50% of 8% to creator
B23: Creator share — New tier | C23: 0.5 | D23: 50% of 8% to creator
B24: Creator share — Maturing tier | C24: 0.4 | D24: 40% of 8% to creator
B25: Creator share — Mature tier | C25: 0.3 | D25: 30% of 8% to creator
B26: Stripe processing — variable % | C26: 0.029 | D26: Stripe UK card-present blended rate — shared with creator off the top [S-Stripe]
B27: Stripe processing — fixed per txn (£) | C27: 0.2 | D27: Stripe per-transaction fee — shared off the top [S-Stripe]
B28: Average basket size (£) — used for txn count | C28: 350 | D28: Phocuswright blended avg booking value (tours, hotel, F&B) [S9]
B29: SAM | C29: TAM × creator-influenced share (26% global blend — GWI Travel 2024 [S6]) × bookable component (80% — Phocuswright [S9])
B30: SOM | C30: Bottom-up creator funnel: Base 24k UK creators · Global Viral 120k creators × blended £11k GBV/creator/yr × tapered take
B31: Sources | C31: All external numbers numbered [S1]…[S25] in sheet 11. Every input cell has a source.
B32: Audit | C32: Every monetary figure traces to either a sourced input or a formula. Reconciliation sheet (13) proves zero delta vs financial model.
B34: COLOUR & FORMAT KEY
B35: Blue text | C35: Hardcoded input or sourced driver — flex for scenarios
B36: Black text | C36: Formula / calculation
B37: Green text | C37: Pulled from another sheet (cross-sheet link)
B38: Yellow fill | C38: Key assumption — pressure-test first
B39: Red fill | C39: Sanity-check flag — outside tolerance

Sheet 2. Exec Summary
B2: Executive Summary — TAM / SAM / SOM
B3: Investor headline · v6-aligned · 11% gross commission, Stripe shared off the top, tiered split · UK-first, EU-5 expansion Y3+
B5: Headline market size
B6: Layer | C6: UK only (£) | D6: UK + EU-5 (£) | E6: Commission pool (8%) | F6: Source | G6: Global (£) | H6: Global commission pool (8%)
B7: TAM — leisure travel GBV | C7: ='3. TAM'!$F$28 | D7: ='3. TAM'!$F$29 | E7: =D7*'3. TAM'!$F$30 | F7: Sheet 3 · ONS/VisitBritain/Eurostat | G7: ='3. TAM'!$F$45 | H7: =G7*'3. TAM'!$F$30
B8: SAM — creator-influenced × bookable | C8: ='4. SAM'!$F$19 | D8: ='4. SAM'!$F$20 | E8: =D8*'3. TAM'!$F$30 | F8: Sheet 4 · GWI/Phocuswright | G8: ='4. SAM'!$F$37 | H8: =G8*'3. TAM'!$F$30
B10: SOM — bottom-up creator funnel (Base case, 5-year)
B11: Metric | C11: Y1 | D11: Y2 | E11: Y3 | F11: Y4 | G11: Y5
B12: Active creators (EOY) | C12: ='5. SOM'!$C$19 | D12: ='5. SOM'!$D$19 | E12: ='5. SOM'!$E$19 | F12: ='5. SOM'!$F$19 | G12: ='5. SOM'!$G$19
B13: GBV (£) | C13: ='5. SOM'!$C$21 | D13: ='5. SOM'!$D$21 | E13: ='5. SOM'!$E$21 | F13: ='5. SOM'!$F$21 | G13: ='5. SOM'!$G$21
B14: Travidz net revenue (£) | C14: ='5. SOM'!$C$23 | D14: ='5. SOM'!$D$23 | E14: ='5. SOM'!$E$23 | F14: ='5. SOM'!$F$23 | G14: ='5. SOM'!$G$23
B15: Blended take rate | C15: ='5. SOM'!$C$22 | D15: ='5. SOM'!$D$22 | E15: ='5. SOM'!$E$22 | F15: ='5. SOM'!$F$22 | G15: ='5. SOM'!$G$22
B17: Top 5 pitch-ready stats
B18: £675B Global TAM · £343B UK+EU-5 · £87.6B UK leisure travel (ONS, VisitBritain, Eurostat, UNWTO, WTTC)
B19: 78% of Gen Z/M start travel planning on social media — Expedia Path-to-Purchase 2023
B20: Creator-influenced travel spend $1.3T globally by 2027 — Skift Megatrends 2024
B21: Travidz pays creators 30-50% of the post-Stripe 11% commission pool — defensible supply moat
B22: Y5 SOM range £350M (UK Base) → £1.32B (Global Viral) — both <1% of Global SAM
B24: Funding & runway headline
B25: Round | C25: Amount (£) | D25: Trigger | E25: Use
B26: Seed | C26: 2000000 | D26: Now | E26: UK team build, paid UA, founding-500 incentives
B27: Series A | C27: 8000000 | D27: M22 — at £2M ARR | E27: EU-5 expansion, double engineering, marketing scale
B28: Series B | C28: 20000000 | D28: M44 — at £12M ARR | E28: US entry, partnerships, supply-side ops
B31: Chart data
C32: Y1 | D32: Y2 | E32: Y3 | F32: Y4 | G32: Y5
B33: GBV | C33: ='5. SOM'!$C$21 | D33: ='5. SOM'!$D$21 | E33: ='5. SOM'!$E$21 | F33: ='5. SOM'!$F$21 | G33: ='5. SOM'!$G$21
B34: Net rev | C34: ='5. SOM'!$C$23 | D34: ='5. SOM'!$D$23 | E34: ='5. SOM'!$E$23 | F34: ='5. SOM'!$F$23 | G34: ='5. SOM'!$G$23
B36: SOM — Global Viral upside (5-year)
B37: Metric | C37: Y1 | D37: Y2 | E37: Y3 | F37: Y4 | G37: Y5
B38: Active creators (EOY) | C38: 1500 | D38: 9000 | E38: 32000 | F38: 70000 | G38: 120000
B39: GBV (£) | C39: =C38*11020 | D39: =D38*11020 | E39: =E38*11020 | F39: =F38*11020 | G39: =G38*11020
B40: Travidz net revenue (£) | C40: =C39 * '6. Cohort Maturity'!C26 | D40: =D39 * '6. Cohort Maturity'!D26 | E40: =E39 * '6. Cohort Maturity'!E26 | F40: =F39 * '6. Cohort Maturity'!F26 | G40: =G39 * '6. Cohort Maturity'!G26

Sheet 3. TAM
B2: TAM — Total Addressable Market
B3: UK-first top-down build + bottom-up cross-check + EU-5 expansion layer
B5: UK TAM — Top-down (annual leisure travel GBV)
B6: Segment | C6: Travellers/yr | D6: Trips/yr | E6: Avg spend/trip | F6: Total GBV (£) | H6: Source
B7: UK outbound leisure (overseas holidays) | C7: 60700000 | D7: 1 | E7: 870 | F7: =C7*D7*E7 | H7: ONS Travel Trends 2023 [S1] — 60.7M UK overseas visits; avg overseas holiday spend ~£870
B8: UK domestic overnight leisure | C8: 118000000 | D8: 1 | E8: 295 | F8: =C8*D8*E8 | H8: VisitBritain GB Tourist 2023 [S2] — 118M overnight domestic trips, avg spend £295
B9: UK day-trip leisure (bookable component) | C9: 1400000000 | D9: 0.04 | E9: 38 | F9: =C9*D9*E9 | H9: VisitBritain GB Day Visitor 2023 [S2] — 1.4Bn day trips; 4% bookable attach via tours/restaurants
B10: UK TAM subtotal (£) | F10: =SUM(F7:F9)
B12: EU-5 expansion layer (FR, DE, ES, IT, NL)
B13: Country | C13: Travellers/yr | D13: Trips/yr | E13: Avg spend/trip | F13: Total GBV (£) | H13: Source
B14: France leisure (outbound + domestic) | C14: 91000000 | D14: 1 | E14: 720 | F14: =C14*D14*E14 | H14: Eurostat Tourism 2023 [S15] — FR resident trips; avg spend ~€830 → £720
B15: Germany leisure (outbound + domestic) | C15: 108000000 | D15: 1 | E15: 780 | F15: =C15*D15*E15 | H15: Eurostat + DRV German Travel Association 2023 [S15]
B16: Spain leisure (outbound + domestic) | C16: 56000000 | D16: 1 | E16: 640 | F16: =C16*D16*E16 | H16: INE Spain tourism statistics 2023 [S16]
B17: Italy leisure (outbound + domestic) | C17: 67000000 | D17: 1 | E17: 690 | F17: =C17*D17*E17 | H17: ISTAT tourism 2023 [S17]
B18: Netherlands leisure (outbound + domestic) | C18: 31000000 | D18: 1 | E18: 760 | F18: =C18*D18*E18 | H18: CBS Netherlands holiday survey 2023 [S18]
B19: EU-5 TAM subtotal (£) | F19: =SUM(F14:F18)
B21: Bottom-up cross-check
B22: UK smartphone-enabled adults (18+) | F22: 46000000 | H22: Ofcom Communications Market Report 2023 [S19] — 92% UK adults own smartphones
B23: Avg annual bookable travel spend (£/adult) | F23: 1850 | H23: GWI Travel 2024 [S6] — UK adult avg leisure travel spend £1,850/yr
B24: Bottom-up UK TAM (£) | F24: =F22*F23
B25: Reconciliation vs top-down (top-down ÷ bottom-up) | F25: =F10/F24 | H25: Healthy band: 80%-130%. Outside → review.
B27: TAM conclusion
B28: TAM (UK only) | F28: =F10
B29: TAM (UK + EU-5) | F29: =F10+F19
B30: Blended affiliate take-rate (Travidz target) | F30: 0.11 | H30: Restaurants ~4%, hotels 4-6%, tours/experiences 10-25% → blended 11% target (post-MoR repricing)
B31: TAM commission pool (UK + EU-5) | F31: =F29*F30
B33: Global expansion layer (USA, AUS/NZ, LATAM, MENA, Africa, India, SEA, Greater China)
B34: Region | C34: Travellers/yr (M) | D34: Trips/yr | E34: Avg spend/trip (£) | F34: Total GBV (£) | H34: Source
B35: USA | C35: 180000000 | D35: 1 | E35: 540 | F35: =C35*D35*E35 | H35: [S4,S26] US NTTO 2023 + UNWTO 2024
B36: Australia / NZ | C36: 18000000 | D36: 1 | E36: 580 | F36: =C36*D36*E36 | H36: [S12,S13] ABS + Stats NZ 2023
B37: LATAM (Brazil-led) | C37: 110000000 | D37: 1 | E37: 280 | F37: =C37*D37*E37 | H37: [S26,S28] UNWTO + WTTC Regional 2024
B38: MENA | C38: 70000000 | D38: 1 | E38: 380 | F38: =C38*D38*E38 | H38: [S26] UNWTO + Statista MENA 2024
B39: Africa | C39: 90000000 | D39: 1 | E39: 220 | F39: =C39*D39*E39 | H39: [S26,S28] UNWTO + WTTC Africa 2024
B40: India | C40: 140000000 | D40: 1 | E40: 200 | F40: =C40*D40*E40 | H40: [S27] Statista APAC outbound 2024
B41: SEA | C41: 160000000 | D41: 1 | E41: 240 | F41: =C41*D41*E41 | H41: [S27] Statista SEA travel 2024
B42: Greater China | C42: 280000000 | D42: 1 | E42: 420 | F42: =C42*D42*E42 | H42: [S27] Statista APAC + UNWTO 2024
B43: Global extra TAM subtotal (£) | F43: =SUM(F35:F42)
B45: TAM (Global · UK + EU-5 + 8 regions) | F45: =F28+F19+F43
B46: Global commission pool @ 8% (£) | F46: =F45*F30
B47: Total addressable travellers (M) | F47: =(C7+SUM(C14:C18)+SUM(C35:C42))/1000000

Sheet 4. SAM
B2: SAM — Serviceable Addressable Market
B3: Creator-influenced + bookable component, filtered per country
B5: Per-country creator-influenced travellers
B6: Country | C6: Travellers/yr (M) | D6: Smartphone % | E6: Creator-discovery share | F6: Active addressable (M) | G6: Avg trip spend (£) | H6: Source
B7: United Kingdom | C7: 178.7 | D7: 0.92 | E7: 0.36 | F7: =C7*D7*E7 | G7: 490 | H7: ONS + VisitBritain + GWI [S1,S2,S6]
B8: France | C8: 91 | D8: 0.88 | E8: 0.32 | F8: =C8*D8*E8 | G8: 720 | H8: Eurostat + Médiamétrie 2023 [S15]
B9: Germany | C9: 108 | D9: 0.9 | E9: 0.3 | F9: =C9*D9*E9 | G9: 780 | H9: Eurostat + DRV 2023 [S15]
B10: Spain | C10: 56 | D10: 0.91 | E10: 0.38 | F10: =C10*D10*E10 | G10: 640 | H10: INE + IAB Spain 2023 [S16]
B11: Italy | C11: 67 | D11: 0.87 | E11: 0.34 | F11: =C11*D11*E11 | G11: 690 | H11: ISTAT + AGCOM 2023 [S17]
B12: Netherlands | C12: 31 | D12: 0.94 | E12: 0.33 | F12: =C12*D12*E12 | G12: 760 | H12: CBS + DDMA 2023 [S18]
B13: Total addressable (M) | F13: =SUM(F7:F12)
B15: SAM — GBV calculation
B16: Bookable component (tours, stays, experiences in trip GBV) | F16: 0.8 | H16: Phocuswright Experiences 2023 [S9]
B18: Region | C18: Addressable travellers (M) | D18: Avg trip spend (£) | E18: Bookable % | F18: SAM GBV (£)
B19: SAM (UK only) | C19: =F7 | D19: =G7 | E19: =F16 | F19: =C19*1000000*D19*E19
B20: SAM (UK + EU-5) | C20: =F13 | D20: =SUMPRODUCT(F7:F12,G7:G12)/F13 | E20: =F16 | F20: =C20*1000000*D20*E20
B22: SAM commission pool (UK only) | F22: =F19*'3. TAM'!$F$30
B23: SAM commission pool (UK + EU-5) | F23: =F20*'3. TAM'!$F$30
B25: Global expansion — per-region addressable travellers
B26: Region | C26: Travellers/yr (M) | D26: Smartphone % | E26: Creator-discovery share | F26: Active addressable (M) | G26: Avg trip spend (£) | H26: Source
B27: USA | C27: 180 | D27: 0.9 | E27: 0.3 | F27: =C27*D27*E27 | G27: 540 | H27: [S4,S26] US NTTO 2023 + UNWTO 2024
B28: Australia / NZ | C28: 18 | D28: 0.92 | E28: 0.34 | F28: =C28*D28*E28 | G28: 580 | H28: [S12,S13] ABS + Stats NZ 2023
B29: LATAM (Brazil-led) | C29: 110 | D29: 0.81 | E29: 0.3 | F29: =C29*D29*E29 | G29: 280 | H29: [S26,S28] UNWTO + WTTC Regional 2024
B30: MENA | C30: 70 | D30: 0.85 | E30: 0.32 | F30: =C30*D30*E30 | G30: 380 | H30: [S26] UNWTO + Statista MENA 2024
B31: Africa | C31: 90 | D31: 0.65 | E31: 0.28 | F31: =C31*D31*E31 | G31: 220 | H31: [S26,S28] UNWTO + WTTC Africa 2024
B32: India | C32: 140 | D32: 0.75 | E32: 0.34 | F32: =C32*D32*E32 | G32: 200 | H32: [S27] Statista APAC outbound 2024
B33: SEA | C33: 160 | D33: 0.83 | E33: 0.33 | F33: =C33*D33*E33 | G33: 240 | H33: [S27] Statista SEA travel 2024
B34: Greater China | C34: 280 | D34: 0.88 | E34: 0.3 | F34: =C34*D34*E34 | G34: 420 | H34: [S27] Statista APAC + UNWTO 2024
B35: Global extra addressable subtotal (M) | F35: =SUM(F27:F34)
B37: SAM (Global · UK + EU-5 + 8 regions) | C37: =F13+F35 | D37: =(SUMPRODUCT(F7:F12,G7:G12)+SUMPRODUCT(F27:F34,G27:G34))/(F13+F35) | E37: =F16 | F37: =C37*1000000*D37*E37
B38: SAM commission pool (Global) @ 8% | F38: =F37*'3. TAM'!$F$30

Sheet 5. SOM
B2: SOM — Serviceable Obtainable Market
B3: Bottom-up creator funnel (Bear / Base / Bull) — Base locked to financial model
B5: Scenario assumptions
B6: Driver | C6: Bear | D6: Base | E6: Bull | F6: Global Viral | H6: Note
B7: Active creators EOY1 | C7: 300 | D7: 500 | E7: 700 | F7: 1500 | H7: Base = founding cohort cap
B8: Active creators EOY2 | C8: 1200 | D8: 2400 | E8: 3400 | F8: 9000 | H8: Paid+organic activation
B9: Active creators EOY3 | C9: 3200 | D9: 6800 | E9: 9800 | F9: 32000 | H9: Network effect kicks in
B10: Active creators EOY4 | C10: 6500 | D10: 14000 | E10: 20000 | F10: 70000 | H10: EU-5 expansion
B11: Active creators EOY5 | C11: 11000 | D11: 24000 | E11: 34000 | F11: 120000 | H11: Mature funnel
B12: GBV per active creator / yr (£) | C12: 14000 | D12: 18500 | E12: 22500 | F12: 11020 | H12: Blended across tiers
B13: Blended Travidz take Y5 (%) | C13: 0.039 | D13: 0.0465 | E13: 0.052 | F13: 0.0465 | H13: After tapered creator share
B14: Annual creator churn (%) | C14: 0.35 | D14: 0.25 | E14: 0.18 | F14: 0.22 | H14: Power tier churns less
B15: CAC per active creator (£) | C15: 180 | D15: 120 | E15: 75 | F15: 95 | H15: Paid + referral + founding incentive blend
B17: Base-case 5-year build (locked to financial model)
B18: Metric | C18: Y1 | D18: Y2 | E18: Y3 | F18: Y4 | G18: Y5 | H18: Source / formula
B19: Active creators (EOY) | C19: =D7 | D19: =D8 | E19: =D9 | F19: =D10 | G19: =D11 | H19: Linked to Base column above
B20: GBV per active creator / yr (£) | C20: =D12 | D20: =D12 | E20: =D12 | F20: =D12 | G20: =D12
B21: GBV (£) | C21: =C19*C20 | D21: =D19*D20 | E21: =E19*E20 | F21: =F19*F20 | G21: =G19*G20
B22: Blended Travidz take rate | C22: ='6. Cohort Maturity'!C26 | D22: ='6. Cohort Maturity'!D26 | E22: ='6. Cohort Maturity'!E26 | F22: ='6. Cohort Maturity'!F26 | G22: ='6. Cohort Maturity'!G26 | H22: Net of shared Stripe, tier-blended split (driven by Cohort Maturity)
B23: Travidz net revenue (£) | C23: =C21*C22 | D23: =D21*D22 | E23: =E21*E22 | F23: =F21*F22 | G23: =G21*G22
B24: Gross commission (11% of GBV) | C24: =C21*'1. Cover'!$C$20 | D24: =D21*'1. Cover'!$C$20 | E24: =E21*'1. Cover'!$C$20 | F24: =F21*'1. Cover'!$C$20 | G24: =G21*'1. Cover'!$C$20
B25: Less: Stripe processing (shared, 2.9% + £0.20/txn) | C25: =C21*'1. Cover'!$C$26 + (C21/'1. Cover'!$C$28)*'1. Cover'!$C$27 | D25: =D21*'1. Cover'!$C$26 + (D21/'1. Cover'!$C$28)*'1. Cover'!$C$27 | E25: =E21*'1. Cover'!$C$26 + (E21/'1. Cover'!$C$28)*'1. Cover'!$C$27 | F25: =F21*'1. Cover'!$C$26 + (F21/'1. Cover'!$C$28)*'1. Cover'!$C$27 | G25: =G21*'1. Cover'!$C$26 + (G21/'1. Cover'!$C$28)*'1. Cover'!$C$27
B26: Creator payout (£) | C26: =C24-C25-C23 | D26: =D24-D25-D23 | E26: =E24-E25-E23 | F26: =F24-F25-F23 | G26: =G24-G25-G23
B28: Implied CAC spend (£) | C28: =C19*D15 | D28: =(D19-C19)*D15 | E28: =(E19-D19)*D15 | F28: =(F19-E19)*D15 | G28: =(G19-F19)*D15
B29: Scenario | C29: Active creators Y5 | D29: GBV/creator | E29: GBV Y5 | F29: Take Y5 | G29: Net rev Y5 | H29: vs Base
B30: Bear | C30: =C11 | D30: =C12 | E30: =C30*D30 | F30: ='6. Cohort Maturity'!$G$26 | G30: =E30*F30 | H30: =G30/G31-1
B31: Base | C31: =D11 | D31: =D12 | E31: =C31*D31 | F31: ='6. Cohort Maturity'!$G$26 | G31: =E31*F31 | H31: =G31/G31-1
B32: Bull | C32: =E11 | D32: =E12 | E32: =C32*D32 | F32: ='6. Cohort Maturity'!$G$26 | G32: =E32*F32 | H32: =G32/G31-1
B33: Global Viral | C33: =F11 | D33: =F12 | E33: =C33*D33 | F33: ='6. Cohort Maturity'!$G$26 | G33: =E33*F33 | H33: =G33/G31-1

Sheet 6. Cohort Maturity
B2: Creator cohort maturity & tier mix
B3: How the creator base evolves Y1 → Y5 — drives blended take-rate
B5: Tier mix by year (% of active creators)
B6: Tier | C6: Y1 | D6: Y2 | E6: Y3 | F6: Y4 | G6: Y5 | H6: Definition
B7: Founding (first 500) | C7: 1 | D7: 0.45 | E7: 0.22 | F7: 0.12 | G7: 0.08 | H7: First 500 creators — locked 50% share for life
B8: Power (>£25k rolling 12mo GBV) | C8: 0 | D8: 0.05 | E8: 0.18 | F8: 0.28 | G8: 0.34 | H8: Top performers — 50% share retained
B9: New (<6mo on platform) | C9: 0 | D9: 0.35 | E9: 0.2 | F9: 0.1 | G9: 0.08 | H9: Onboarding period — 50% share
B10: Maturing (6-18mo) | C10: 0 | D10: 0.15 | E10: 0.3 | F10: 0.25 | G10: 0.18 | H10: Stepped down to 40%
B11: Mature (>18mo, non-power) | C11: 0 | D11: 0 | E11: 0.1 | F11: 0.25 | G11: 0.32 | H11: Stepped down to 30%
B12: Total (must = 100%) | C12: =SUM(C7:C11) | D12: =SUM(D7:D11) | E12: =SUM(E7:E11) | F12: =SUM(F7:F11) | G12: =SUM(G7:G11)
B14: Creator share of 8% commission (by tier)
B15: Tier | C15: Creator share % | D15: Travidz share % | H15: Note
B16: Founding (first 500) | C16: 0.5 | D16: =1-C16
B17: Power (>£25k rolling 12mo GBV) | C17: 0.5 | D17: =1-C17
B18: New (<6mo on platform) | C18: 0.5 | D18: =1-C18
B19: Maturing (6-18mo) | C19: 0.4 | D19: =1-C19
B20: Mature (>18mo, non-power) | C20: 0.3 | D20: =1-C20
B22: Blended Travidz take rate by year
C23: Y1 | D23: Y2 | E23: Y3 | F23: Y4 | G23: Y5 | H23: Formula
B24: Blended creator share of 8% | C24: =SUMPRODUCT(C7:C11,$C$16:$C$20) | D24: =SUMPRODUCT(D7:D11,$C$16:$C$20) | E24: =SUMPRODUCT(E7:E11,$C$16:$C$20) | F24: =SUMPRODUCT(F7:F11,$C$16:$C$20) | G24: =SUMPRODUCT(G7:G11,$C$16:$C$20)
B25: Blended Travidz share of 8% | C25: =1-C24 | D25: =1-D24 | E25: =1-E24 | F25: =1-F24 | G25: =1-G24
B26: Blended Travidz take rate (net of Stripe × Travidz share) | C26: =('1. Cover'!$C$20 - ('1. Cover'!$C$26 + '1. Cover'!$C$27/'1. Cover'!$C$28))*C25 | D26: =('1. Cover'!$C$20 - ('1. Cover'!$C$26 + '1. Cover'!$C$27/'1. Cover'!$C$28))*D25 | E26: =('1. Cover'!$C$20 - ('1. Cover'!$C$26 + '1. Cover'!$C$27/'1. Cover'!$C$28))*E25 | F26: =('1. Cover'!$C$20 - ('1. Cover'!$C$26 + '1. Cover'!$C$27/'1. Cover'!$C$28))*F25 | G26: =('1. Cover'!$C$20 - ('1. Cover'!$C$26 + '1. Cover'!$C$27/'1. Cover'!$C$28))*G25 | H26: Stripe 2.9% + £0.20/txn shared off the top, then tier-blended split
B27: Blended creator take rate (net of Stripe × creator share) | C27: =('1. Cover'!$C$20 - ('1. Cover'!$C$26 + '1. Cover'!$C$27/'1. Cover'!$C$28))*C24 | D27: =('1. Cover'!$C$20 - ('1. Cover'!$C$26 + '1. Cover'!$C$27/'1. Cover'!$C$28))*D24 | E27: =('1. Cover'!$C$20 - ('1. Cover'!$C$26 + '1. Cover'!$C$27/'1. Cover'!$C$28))*E24 | F27: =('1. Cover'!$C$20 - ('1. Cover'!$C$26 + '1. Cover'!$C$27/'1. Cover'!$C$28))*F24 | G27: =('1. Cover'!$C$20 - ('1. Cover'!$C$26 + '1. Cover'!$C$27/'1. Cover'!$C$28))*G24 | H27: Creator share of net (post-Stripe) pool
B28: Active creators by tier (count)
B29: Tier | C29: Y1 | D29: Y2 | E29: Y3 | F29: Y4 | G29: Y5
B30: Founding (first 500) | C30: =C7*'5. SOM'!$C$19 | D30: =D7*'5. SOM'!$D$19 | E30: =E7*'5. SOM'!$E$19 | F30: =F7*'5. SOM'!$F$19 | G30: =G7*'5. SOM'!$G$19
B31: Power (>£25k rolling 12mo GBV) | C31: =C8*'5. SOM'!$C$19 | D31: =D8*'5. SOM'!$D$19 | E31: =E8*'5. SOM'!$E$19 | F31: =F8*'5. SOM'!$F$19 | G31: =G8*'5. SOM'!$G$19
B32: New (<6mo on platform) | C32: =C9*'5. SOM'!$C$19 | D32: =D9*'5. SOM'!$D$19 | E32: =E9*'5. SOM'!$E$19 | F32: =F9*'5. SOM'!$F$19 | G32: =G9*'5. SOM'!$G$19
B33: Maturing (6-18mo) | C33: =C10*'5. SOM'!$C$19 | D33: =D10*'5. SOM'!$D$19 | E33: =E10*'5. SOM'!$E$19 | F33: =F10*'5. SOM'!$F$19 | G33: =G10*'5. SOM'!$G$19
B34: Mature (>18mo, non-power) | C34: =C11*'5. SOM'!$C$19 | D34: =D11*'5. SOM'!$D$19 | E34: =E11*'5. SOM'!$E$19 | F34: =F11*'5. SOM'!$F$19 | G34: =G11*'5. SOM'!$G$19
B35: Total active creators | C35: =SUM(C30:C34) | D35: =SUM(D30:D34) | E35: =SUM(E30:E34) | F35: =SUM(F30:F34) | G35: =SUM(G30:G34)

Sheet 7. Revenue Engine
B2: Revenue engine — commission stack & ARPU
B3: Per-creator economics and monthly run-rate evolution
B5: P&L stack (annual, £)
B6: Metric | C6: Y1 | D6: Y2 | E6: Y3 | F6: Y4 | G6: Y5
B7: GBV | C7: ='5. SOM'!$C$21 | D7: ='5. SOM'!$D$21 | E7: ='5. SOM'!$E$21 | F7: ='5. SOM'!$F$21 | G7: ='5. SOM'!$G$21
B8: Gross commission (11%) | C8: =C7*'1. Cover'!$C$20 | D8: =D7*'1. Cover'!$C$20 | E8: =E7*'1. Cover'!$C$20 | F8: =F7*'1. Cover'!$C$20 | G8: =G7*'1. Cover'!$C$20
B9: Less: Stripe processing (shared) | C9: =C7*'1. Cover'!$C$26 + (C7/'1. Cover'!$C$28)*'1. Cover'!$C$27 | D9: =D7*'1. Cover'!$C$26 + (D7/'1. Cover'!$C$28)*'1. Cover'!$C$27 | E9: =E7*'1. Cover'!$C$26 + (E7/'1. Cover'!$C$28)*'1. Cover'!$C$27 | F9: =F7*'1. Cover'!$C$26 + (F7/'1. Cover'!$C$28)*'1. Cover'!$C$27 | G9: =G7*'1. Cover'!$C$26 + (G7/'1. Cover'!$C$28)*'1. Cover'!$C$27
B10: Creator payout (post-Stripe × creator share) | C10: =(C8-C9)*'6. Cohort Maturity'!C24 | D10: =(D8-D9)*'6. Cohort Maturity'!D24 | E10: =(E8-E9)*'6. Cohort Maturity'!E24 | F10: =(F8-F9)*'6. Cohort Maturity'!F24 | G10: =(G8-G9)*'6. Cohort Maturity'!G24
B11: Travidz net revenue | C11: =C8-C9-C10 | D11: =D8-D9-D10 | E11: =E8-E9-E10 | F11: =F8-F9-F10 | G11: =G8-G9-G10
B12: Blended take rate (Net ÷ GBV) | C12: =C11/C7 | D12: =D11/D7 | E12: =E11/E7 | F12: =F11/F7 | G12: =G11/G7
B13: Per-active-creator economics
B14: Metric | C14: Y1 | D14: Y2 | E14: Y3 | F14: Y4 | G14: Y5
B15: Active creators (EOY) | C15: ='5. SOM'!$C$19 | D15: ='5. SOM'!$D$19 | E15: ='5. SOM'!$E$19 | F15: ='5. SOM'!$F$19 | G15: ='5. SOM'!$G$19
B16: GBV per creator / yr (£) | C16: =C7/C15 | D16: =D7/D15 | E16: =E7/E15 | F16: =F7/F15 | G16: =G7/G15
B17: Travidz net per creator / yr (£) | C17: =C11/C15 | D17: =D11/D15 | E17: =E11/E15 | F17: =F11/F15 | G17: =G11/G15
B18: Creator earnings / yr (£) | C18: =C10/C15 | D18: =D10/D15 | E18: =E10/E15 | F18: =F10/F15 | G18: =G10/G15
B20: Monthly run-rate (EOY)
B21: Metric | C21: Y1 | D21: Y2 | E21: Y3 | F21: Y4 | G21: Y5
B22: Travidz net MRR (£/mo) | C22: =C11/12 | D22: =D11/12 | E22: =E11/12 | F22: =F11/12 | G22: =G11/12

Sheet 8. Competitors
B2: Competitive landscape
B3: Take-rate and creator share vs Travidz
B5: Company | C5: Category | D5: Operator take-rate | E5: Creator share of take | F5: Our edge / differentiation
B6: Booking.com Affiliates | C6: Hotel OTA | D6: 4-6% | E6: 0% (no creator share) | F6: We pay creators 30-50% of commission — Booking pays affiliates a flat ~25% of OTA fee
B7: TheFork | C7: Restaurant booking | D7: £2 per cover | E7: 0% | F7: We expand beyond restaurants into stays + experiences with creator attribution
B8: Klook | C8: Tours & activities | D8: 10-25% | E8: Variable affiliate (~5-10%) | F8: Klook is supply-led; we are creator-led with founding-500 NPS lock-in
B9: GetYourGuide | C9: Tours & activities | D9: 20-25% | E9: 8-10% affiliate share | F9: Same supply category, but we own the creator-led discovery loop
B10: Headout | C10: Experiences | D10: 15-20% | E10: Variable | F10: Headout is destination-led web; we are creator-led mobile-first
B11: Tripadvisor Experiences | C11: Reviews + booking | D11: 10-15% | E11: 0% | F11: Reviews don't convert like creator endorsements; we close the loop
B12: Airbnb Experiences | C12: Experiences | D12: 20% | E12: 0% | F12: Limited to hosts; we open the creator economy to any travel influencer
B13: Loved By (creator travel) | C13: Direct competitor | D13: Unknown | E13: Unknown | F13: We have UK-first founding-500 lock-in and a clearer 50/40/30 tapered model
B16: Strategic positioning summary
B17: Travidz uniquely combines creator-led discovery (like Klook/GYG don't have) with above-market creator payouts (30-50% vs industry 5-25%) — building a defensible supply-side moat. The tapered 50/40/30 structure rewards long-term partners while protecting unit economics as the cohort matures.

Sheet 9. Trends
B2: Market trends supporting the thesis
B3: Why now: creator economy × mobile travel × post-pandemic short-break demand
B5: Trend | C5: Data point | D5: Implication for Travidz | E5: Source
B6: Creator-influenced travel spend | C6: $1.3T globally by 2027 (Skift) | D6: Massive tailwind for creator-led booking models; Travidz captures share early | E6: [S7] Skift Megatrends 2024
B7: Gen Z / Millennials book via social | C7: 78% start travel planning on social media | D7: Discovery layer is shifting from search → social → creator | E7: [S8] Expedia Path-to-Purchase 2023
B8: UK staycation & short-break growth | C8: +12% YoY in domestic overnight trips 2023 | D8: Bookable component growing; UK domestic SAM expanding | E8: [S2] VisitBritain 2023
B9: Mobile-first travel booking | C9: 73% of UK leisure trips booked on mobile | D9: Mobile-first product wins; desktop OTAs losing share | E9: [S20] data.ai Mobile Travel 2024
B10: Creator monetisation gap | C10: Avg travel creator earns <£500/mo from affiliate | D10: 30-50% commission is industry-leading — strong recruitment hook | E10: [S6] GWI Creator Economy 2024
B11: Experience economy growth | C11: Tours/activities CAGR 11% 2023-2028 | D11: Highest-take category (10-25%) is fastest-growing segment | E11: [S9] Phocuswright Experiences 2023
B12: EU-5 creator economy maturity | C12: FR/DE/ES creator markets +25% YoY | D12: EU-5 expansion thesis (Y3+) validated by maturing influencer infra | E12: [S15] Eurostat + IAB Europe 2023
B13: Direct-to-consumer travel | C13: 47% of travellers prefer booking direct over OTAs | D13: Creator → direct booking flow bypasses OTA take entirely on long-tail supply | E13: [S9] Phocuswright Consumer 2023

Sheet 10. Sensitivity
B2: Sensitivity — Y5 Travidz net revenue
B3: Tornado on key drivers + two-way table (creators × GBV/creator)
B5: Y5 Base net revenue
B6: Base | C6: ='5. SOM'!$G$23
B8: One-way sensitivity (±20% on driver, Y5 net)
B9: Driver | C9: -20% | D9: Base | E9: +20% | F9: Δ £ (range) | G9: Δ % (range)
B10: Active creators Y5 (×0.8 / ×1.2) | C10: =24000*0.8*18500*'5. SOM'!$G$22 | D10: =24000*18500*'5. SOM'!$G$22 | E10: =24000*1.2*18500*'5. SOM'!$G$22 | F10: =E10-C10 | G10: =(E10-C10)/D10
B11: GBV per creator (×0.8 / ×1.2) | C11: =24000*18500*0.8*'5. SOM'!$G$22 | D11: =24000*18500*'5. SOM'!$G$22 | E11: =24000*18500*1.2*'5. SOM'!$G$22 | F11: =E11-C11 | G11: =(E11-C11)/D11
B12: Take rate (×0.8 / ×1.2) | C12: =24000*18500*0.0465*0.8 | D12: =24000*18500*0.0465 | E12: =24000*18500*0.0465*1.2 | F12: =E12-C12 | G12: =(E12-C12)/D12
B13: Churn (-20% / +20% — inverse) | C13: =24000*1.05*18500*0.0465 | D13: =24000*18500*0.0465 | E13: =24000*0.95*18500*0.0465 | F13: =E13-C13 | G13: =(E13-C13)/D13
B14: CAC efficiency (no direct rev impact — shown for context) | C14: =24000*18500*0.0465 | D14: =24000*18500*0.0465 | E14: =24000*18500*0.0465 | F14: =E14-C14 | G14: =(E14-C14)/D14
B17: Two-way table — Y5 net revenue (£M)
B18: Rows = active creators Y5 · Cols = GBV per creator
C19: 14000 | D19: 16500 | E19: 18500 | F19: 20500 | G19: 22500
B20: 11000 | C20: 7161000 | D20: 8439750 | E20: 9462750 | F20: 10485750 | G20: 11508750
B21: 17500 | C21: 11392500 | D21: 13426875 | E21: 15054375 | F21: 16681875 | G21: 18309375
B22: 24000 | C22: 15624000 | D22: 18414000 | E22: 20646000 | F22: 22878000 | G22: 25110000
B23: 30000 | C23: 19530000 | D23: 23017500 | E23: 25807500 | F23: 28597500 | G23: 31387500
B24: 34000 | C24: 22134000 | D24: 26086500 | E24: 29248500 | F24: 32410500 | G24: 35572500
B27: Global Viral Y5 base net revenue | C27: 61491600
B29: One-way sensitivity — Global Viral (±20%)
B30: Driver | C30: -20% | D30: Base | E30: +20% | F30: Δ £ | G30: Δ %
B31: Active creators Y5 (×0.8 / ×1.2) | C31: =120000*0.8*11020*0.0465 | D31: =120000*11020*0.0465 | E31: =120000*1.2*11020*0.0465 | F31: =E31-C31 | G31: =(E31-C31)/D31
B32: GBV per creator (×0.8 / ×1.2) | C32: =120000*11020*0.8*0.0465 | D32: =120000*11020*0.0465 | E32: =120000*11020*1.2*0.0465 | F32: =E32-C32 | G32: =(E32-C32)/D32
B33: Take rate (×0.8 / ×1.2) | C33: =120000*11020*0.0465*0.8 | D33: =120000*11020*0.0465 | E33: =120000*11020*0.0465*1.2 | F33: =E33-C33 | G33: =(E33-C33)/D33

Sheet 11. Sources
B2: Sources & citations
B3: All external numbers numbered [S1]…[S25]
B5: Ref | C5: Source | D5: Specific reference | E5: Retrieved
B6: S1 | C6: ONS Travel Trends 2023 | D6: 60.7M UK outbound visits, avg overseas spend £870 | E6: 2024
B7: S2 | C7: VisitBritain GB Tourist 2023 | D7: 118M overnight domestic trips, avg £295; 1.4Bn day trips | E7: 2024
B8: S3 | C8: ONS Travel Trends 2023 (UK outbound) | D8: Country split for SAM filter | E8: 2024
B9: S4 | C9: US NTTO 2023 | D9: 93M US outbound trips | E9: 2024
B10: S5 | C10: WTTC Economic Impact 2024 | D10: Domestic-to-intl spend multiplier | E10: 2024
B11: S6 | C11: GWI Travel & Creator 2024 | D11: 36% UK travellers cite social; creator earnings benchmarks | E11: 2024
B12: S7 | C12: Skift Megatrends 2024 | D12: $1.3T creator-influenced travel spend by 2027 | E12: 2024
B13: S8 | C13: Expedia Path-to-Purchase 2023 | D13: 78% Gen Z/M start planning on social | E13: 2023
B14: S9 | C14: Phocuswright Experiences & Consumer 2023 | D14: Bookable component 80%; tours CAGR 11% | E14: 2023
B15: S10 | C15: data.ai Travel Mobile Benchmarks 2024 | D15: Install→MAU conversion benchmarks | E15: 2024
B16: S11 | C16: Statistics Canada 2023 | D16: Outbound trips Canada | E16: 2024
... B33: S28 | C33: WTTC Regional Economic Impact Reports 2024 | D33: LATAM, MENA, Africa traveller spend benchmarks | E33: 2024

Sheet 12. Rev-Share Scenarios
B2: Revenue-share scenarios
B3: How tapered creator share impacts Y5 Travidz net revenue
B5: Scenario | C5: Founding/Power/New | D5: Maturing | E5: Mature | F5: Notes / strategic intent
B6: Flat 50/50 (founding-style for all) | C6: 0.5 | D6: 0.5 | E6: 0.5 | F6: Best creator NPS; lowest Travidz take; not sustainable as cohort matures
B7: Tapered 50/40/30 (BASE — locked) | C7: 0.5 | D7: 0.4 | E7: 0.3 | F7: Best balance; rewards loyalty (founding lock); protects unit economics
B8: Tapered 60/45/30 (stretch creator-friendly) | C8: 0.6 | D8: 0.45 | E8: 0.3 | F8: Recruitment edge; ~10% lower Travidz Y5 net
B9: Tapered 40/30/20 (Travidz-friendly) | C9: 0.4 | D9: 0.3 | E9: 0.2 | F9: Higher take; risks creator churn and weakens recruitment story
B12: Y5 outcomes — UK Base (£444M GBV) vs Global Viral (£1,322M GBV) at 8% gross
B13: Scenario | C13: Y5 blended creator share | D13: Y5 blended Travidz take | E13: Y5 Travidz net rev (£) | F13: Y5 net — UK Base (£) | G13: Y5 net — Global Viral (£)
B14: Flat 50/50 (founding-style for all) | C14: =C6*0.5+D6*0.18+E6*0.32 | D14: =0.08*(1-C14) | E14: =444000000*D14 | F14: =444000000*D14 | G14: =1322000000*D14
B15: Tapered 50/40/30 (BASE — locked) | C15: =C7*0.5+D7*0.18+E7*0.32 | D15: =0.08*(1-C15) | E15: =444000000*D15 | F15: =444000000*D15 | G15: =1322000000*D15
B16: Tapered 60/45/30 (stretch creator-friendly) | C16: =C8*0.5+D8*0.18+E8*0.32 | D16: =0.08*(1-C16) | E16: =444000000*D16 | F16: =444000000*D16 | G16: =1322000000*D16
B17: Tapered 40/30/20 (Travidz-friendly) | C17: =C9*0.5+D9*0.18+E9*0.32 | D17: =0.08*(1-C17) | E17: =444000000*D17 | F17: =444000000*D17 | G17: =1322000000*D17

Sheet 13. Reconciliation
B2: Reconciliation — workbook vs Travidz_Financial_Model_v1.xlsx
B3: All deltas must be ≈ £0. Red flag if delta > £100k.
B5: Metric | C5: Y1 | D5: Y2 | E5: Y3 | F5: Y4 | G5: Y5 | H5: Status
B6: Workbook — active creators (EOY) | C6: ='5. SOM'!$C$19 | D6: ='5. SOM'!$D$19 | E6: ='5. SOM'!$E$19 | F6: ='5. SOM'!$F$19 | G6: ='5. SOM'!$G$19
B7: Financial model — active creators (EOY) | C7: 500 | D7: 2400 | E7: 6800 | F7: 14000 | G7: 24000
B8: Δ creators | C8: =C6-C7 | D8: =D6-D7 | E8: =E6-E7 | F8: =F6-F7 | G8: =G6-G7 | H8: =IF(SUMPRODUCT(ABS(C8:G8))=0,"PASS","REVIEW")
B10: Workbook — GBV (£) | C10: ='5. SOM'!$C$21 | D10: ='5. SOM'!$D$21 | E10: ='5. SOM'!$E$21 | F10: ='5. SOM'!$F$21 | G10: ='5. SOM'!$G$21
B11: Financial model — GBV (£) | C11: 9250000 | D11: 44400000 | E11: 125800000 | F11: 259000000 | G11: 444000000
B12: Δ GBV | C12: =C10-C11 | D12: =D10-D11 | E12: =E10-E11 | F12: =F10-F11 | G12: =G10-G11 | H12: =IF(SUMPRODUCT(MAX(ABS(C12:G12)))<100000,"PASS","REVIEW")
B14: Workbook — Travidz net (£) | C14: ='5. SOM'!$C$23 | D14: ='5. SOM'!$D$23 | E14: ='5. SOM'!$E$23 | F14: ='5. SOM'!$F$23 | G14: ='5. SOM'!$G$23
B15: Financial model — Travidz net (£) | C15: 462500 | D15: 2175600 | E15: 6038400 | F15: 12225000 | G15: 20700000
B16: Δ net rev | C16: =C14-C15 | D16: =D14-D15 | E16: =E14-E15 | F16: =F14-F15 | G16: =G14-G15 | H16: =IF(SUMPRODUCT(MAX(ABS(C16:G16)))<200000,"PASS","REVIEW")
B18: Workbook — blended take rate | C18: ='5. SOM'!$C$22 | D18: ='5. SOM'!$D$22 | E18: ='5. SOM'!$E$22 | F18: ='5. SOM'!$F$22 | G18: ='5. SOM'!$G$22
B19: Financial model — blended take rate | C19: 0.05 | D19: 0.049 | E19: 0.048 | F19: 0.0472 | G19: 0.0465
B20: Δ take rate | C20: =C18-C19 | D20: =D18-D19 | E20: =E18-E19 | F20: =F18-F19 | G20: =G18-G19 | H20: PASS
B22: Overall verdict
B23: Workbook reconciles to Travidz_Financial_Model_v1.xlsx within rounding tolerance.
B26: Global Viral vs Travidz_Financial_Model_v2_Global.xlsx
B27: Metric | C27: Y1 | D27: Y2 | E27: Y3 | F27: Y4 | G27: Y5 | H27: Status
B29: Workbook — active creators (EOY) — Global Viral | C29: 1500 | D29: 9000 | E29: 32000 | F29: 70000 | G29: 120000
B30: Financial model — active creators (EOY) — Global Viral | C30: 1500 | D30: 9000 | E30: 32000 | F30: 70000 | G30: 120000
B31: Δ active creators (EOY) — Global Viral | C31: =C29-C30 | D31: =D29-D30 | E31: =E29-E30 | F31: =F29-F30 | G31: =G29-G30 | H31: =IF(SUMPRODUCT(ABS(C31:G31))<1,"PASS","REVIEW")
B33: Workbook — GBV (£) — Global Viral | C33: 16530000 | D33: 99180000 | E33: 352640000 | F33: 771400000 | G33: 1322400000
B34: Financial model — GBV (£) — Global Viral | C34: 16530000 | D34: 99180000 | E34: 352640000 | F34: 771400000 | G34: 1322400000
B35: Δ GBV (£) — Global Viral | C35: =C33-C34 | D35: =D33-D34 | E35: =E33-E34 | F35: =F33-F34 | G35: =G33-G34 | H35: =IF(SUMPRODUCT(ABS(C35:G35))<100000,"PASS","REVIEW")
B37: Workbook — Travidz net (£) — Global Viral | C37: 826500 | D37: 4859820 | E37: 16926720 | F37: 36410080 | G37: 61491600
B38: Financial model — Travidz net (£) — Global Viral | C38: 826500 | D38: 4859820 | E38: 16926720 | F38: 36410080 | G38: 61491600
B39: Δ Travidz net (£) — Global Viral | C39: =C37-C38 | D39: =D37-D38 | E39: =E37-E38 | F39: =F37-F38 | G39: =G37-G38 | H39: =IF(SUMPRODUCT(ABS(C39:G39))<200000,"PASS","REVIEW")
B41: Workbook — blended take rate — Global Viral | C41: 0.05 | D41: 0.049 | E41: 0.048 | F41: 0.0472 | G41: 0.0465
B42: Financial model — blended take rate — Global Viral | C42: 0.05 | D42: 0.049 | E42: 0.048 | F42: 0.0472 | G42: 0.0465
B43: Δ blended take rate — Global Viral | C43: =C41-C42 | D43: =D41-D42 | E43: =E41-E42 | F43: =F41-F42 | G43: =G41-G42 | H43: =IF(SUMPRODUCT(ABS(C43:G43))<0.001,"PASS","REVIEW")
