Workbook
Name scenario_idx: MATCH(summary_dashboard!$B$2,{"Base","Bear","Bull","Global Viral"},0)

Sheet summary_dashboard
A1: Travidz — Financial Model v1 (60 months)
A2: Scenario: | B2: Base | C2: (Base / Bear / Bull)
A4: KEY METRICS
A5: Metric | B5: M12 (Y1) | C5: M24 (Y2) | D5: M36 (Y3) | E5: M48 (Y4) | F5: M60 (Y5)
A6: Active creators (EOY) | B6: =creator_cohorts!M5 | C6: =creator_cohorts!Y5 | D6: =creator_cohorts!AK5 | E6: =creator_cohorts!AW5 | F6: =creator_cohorts!BI5
A7: Active operators (EOY) | B7: =operator_supply!M5 | C7: =operator_supply!Y5 | D7: =operator_supply!AK5 | E7: =operator_supply!AW5 | F7: =operator_supply!BI5
A8: Active FTE (EOY) | B8: =headcount_uk!R45 | C8: =headcount_uk!AD45 | D8: =headcount_uk!AP45 | E8: =headcount_uk!BB45 | F8: =headcount_uk!BN45
A9: Annual GBV | B9: =SUM(creator_cohorts!B11:M11) | C9: =SUM(creator_cohorts!N11:Y11) | D9: =SUM(creator_cohorts!Z11:AK11) | E9: =SUM(creator_cohorts!AL11:AW11) | F9: =SUM(creator_cohorts!AX11:BI11)
A10: Annual Travidz net revenue | B10: =SUM(creator_cohorts!B22:M22) | C10: =SUM(creator_cohorts!N22:Y22) | D10: =SUM(creator_cohorts!Z22:AK22) | E10: =SUM(creator_cohorts!AL22:AW22) | F10: =SUM(creator_cohorts!AX22:BI22)
A11: Blended take-rate | B11: =SUM(creator_cohorts!B22:M22)/SUM(creator_cohorts!B11:M11) | C11: =SUM(creator_cohorts!N22:Y22)/SUM(creator_cohorts!N11:Y11) | D11: =SUM(creator_cohorts!Z22:AK22)/SUM(creator_cohorts!Z11:AK11) | E11: =SUM(creator_cohorts!AL22:AW22)/SUM(creator_cohorts!AL11:AW11) | F11: =SUM(creator_cohorts!AX22:BI22)/SUM(creator_cohorts!AX11:BI11)
A12: Annual EBITDA | B12: =SUM(combined_pnl_cash!B31:M31) | C12: =SUM(combined_pnl_cash!N31:Y31) | D12: =SUM(combined_pnl_cash!Z31:AK31) | E12: =SUM(combined_pnl_cash!AL31:AW31) | F12: =SUM(combined_pnl_cash!AX31:BI31)
A13: EBITDA margin | B13: =SUM(combined_pnl_cash!B31:M31)/SUM(creator_cohorts!B22:M22) | C13: =SUM(combined_pnl_cash!N31:Y31)/SUM(creator_cohorts!N22:Y22) | D13: =SUM(combined_pnl_cash!Z31:AK31)/SUM(creator_cohorts!Z22:AK22) | E13: =SUM(combined_pnl_cash!AL31:AW31)/SUM(creator_cohorts!AL22:AW22) | F13: =SUM(combined_pnl_cash!AX31:BI31)/SUM(creator_cohorts!AX22:BI22)
A14: Closing cash (EOY) | B14: =combined_pnl_cash!M39 | C14: =combined_pnl_cash!Y39 | D14: =combined_pnl_cash!AK39 | E14: =combined_pnl_cash!AW39 | F14: =combined_pnl_cash!BI39
A15: Peak cash deficit | B15: =combined_pnl_cash!M40 | C15: =combined_pnl_cash!Y40 | D15: =combined_pnl_cash!AK40 | E15: =combined_pnl_cash!AW40 | F15: =combined_pnl_cash!BI40
A17: SUMMARY KPIs
A18: Peak monthly burn (£) | B18: =-MIN(combined_pnl_cash!B31:BI31)
A19: Month of peak burn | B19: ="M"&MATCH(MIN(combined_pnl_cash!B31:BI31),combined_pnl_cash!B31:BI31,0)
A20: Months to EBITDA breakeven | B20: =IFERROR(MATCH(TRUE,INDEX(combined_pnl_cash!B31:BI31>0,0),0),"not in 60mo")
A21: Peak cash deficit (£) | B21: =MIN(combined_pnl_cash!B40:BI40)
A22: Required seed (peak burn × -1 + 25% buffer) | B22: =-MIN(combined_pnl_cash!B40:BI40)*1.25-assumptions!$G$125-assumptions!$G$127
A23: Y5 ARR-equivalent (Travidz net × 12 at M60) | B23: =combined_pnl_cash!BI5*12
A24: Y5 Annual GBV | B24: =SUM(creator_cohorts!AX11:BI11)
A25: Y5 Travidz net revenue | B25: =SUM(creator_cohorts!AX22:BI22)
A26: Y5 Active creators | B26: =creator_cohorts!BI5
A27: Y5 Active FTE | B27: =headcount_uk!BN45
A28: Y5 Blended take-rate | B28: =SUM(creator_cohorts!AX22:BI22)/SUM(creator_cohorts!AX11:BI11)
A31: v6 TS-MODEL CROSS-CHECK (target — should match Base)
A32: v6 TS-MODEL CROSS-CHECK (11% / Stripe shared / tiered — UK Base Y5) | B32: Target (v6) | C32: Model Y5 | D32: Delta
A33: Y5 Active creators | B33: 24000 | C33: =creator_cohorts!BI5 | D33: =C33-B33
A34: Y5 Annual GBV | B34: 350102510 | C34: =SUM(creator_cohorts!AX11:BI11) | D34: =C34-B34
A35: Y5 Travidz net | B35: 16416811 | C35: =SUM(creator_cohorts!AX22:BI22) | D35: =C35-B35
A36: Y5 Take-rate | B36: 0.046891442 | C36: =SUM(creator_cohorts!AX22:BI22)/SUM(creator_cohorts!AX11:BI11) | D36: =C36-B36
A39: Charts inserted to the right →

Sheet global_viral_summary
A1: Travidz — Global Viral Scenario (Y1–Y5)
A2: Pre-launch model. UK Base remains the funded plan. Global Viral assumes one breakout region per year (US, AUS/NZ, LATAM, MENA, SEA, India) and a TikTok-style creator loop.
A4: Metric | B4: Y1 | C4: Y2 | D4: Y3 | E4: Y4 | F4: Y5 | G4: vs UK Base Y5
A5: Active creators (EOY) | B5: 1500 | C5: 9000 | D5: 32000 | E5: 70000 | F5: 120000 | G5: 5.0x
A6: Annual GBV (£) | B6: 4050000 | C6: 59850000 | D6: 255840000 | E6: 679320000 | F6: 1322400000 | G6: 3.8x
A7: Gross commission (£) | B7: 445500 | C7: 6583500 | D7: 28142400 | E7: 74725200 | F7: 145464000 | G7: 3.8x
A8: Creator payout (£) | B8: 163037.2 | C8: 2337047.6 | D8: 9269208 | E8: 23244756 | F8: 44514826 | G8: see v6 UK Base re-run
A9: Travidz net revenue (£) | B9: 163037.2 | C9: 2481607.3 | D9: 11329032 | E9: 31448788 | F9: 61954501 | G9: 3.8x
A10: Blended take-rate | B10: 0.040256098 | C10: 0.04146378 | D10: 0.044281707 | E10: 0.046294512 | F10: 0.046850046 | G10: 1.0x
A13: Y5 SIDE-BY-SIDE
A14: Metric | B14: UK Base | C14: Global Viral | D14: Multiplier
A15: Active creators | B15: 24000 | C15: 120000 | D15: 5.0x
A16: Annual GBV (£) | B16: 350102510 | C16: 1322400000 | D16: 3.8x
A17: Travidz net revenue (£) | B17: 16416811 | C17: 61954501 | D17: 3.8x
A18: Blended take-rate | B18: 0.046891442 | C18: 0.046850046 | D18: 1.0x

Sheet regions
A1: Travidz — Regional Build (Y5, Global Viral)
A2: Bottom-up Y5 split across launch regions. Sum of creators and GBV ties back to global_viral_summary Y5.
A4: Region | B4: Reachable travellers (M) | C4: Active creators @ Y5 | D4: ABV (£) | E4: Annual GBV (£) | F4: Travidz net (£)
A5: United Kingdom | B5: 25 | C5: 6000 | D5: 480 | E5: 84558437 | F5: 3937040.8
A6: EU-5 (FR/DE/ES/IT/NL) | B6: 150 | C6: 14000 | D6: 460 | E6: 1.8908206e+08 | F6: 8803660.7
A7: USA | B7: 180 | C7: 22000 | D7: 540 | E7: 3.4880355e+08 | F7: 16240293
A8: Australia / NZ | B8: 18 | C8: 6000 | D8: 580 | E8: 1.0217478e+08 | F8: 4757257.7
A9: LATAM (Brazil-led) | B9: 110 | C9: 14000 | D9: 280 | E9: 1.1509343e+08 | F9: 5358750
A10: MENA | B10: 70 | C10: 8000 | D10: 380 | E10: 89256128 | F10: 4155765.3
A11: Africa | B11: 90 | C11: 6000 | D11: 220 | E11: 38755950 | F11: 1804477
A12: India | B12: 140 | C12: 16000 | D12: 200 | E12: 93953819 | F12: 4374489.8
A13: SEA | B13: 160 | C13: 16000 | D13: 240 | E13: 1.1274458e+08 | F13: 5249387.8
A14: Greater China | B14: 280 | C14: 12000 | D14: 420 | E14: 1.4797726e+08 | F14: 6889821.4
A15: TOTAL | B15: 1223 | C15: 120000 | E15: 1322400000 | F15: 61570944

Sheet assumptions
A1: Travidz — Assumptions (60 months)
A2: Blue = input. Edit Base / Bear / Bull. Active column drives all sheets via scenario_idx on summary_dashboard.
A3: Parameter | B3: Base | C3: Bear | D3: Bull | E3: Global Viral | F3: Notes | G3: Active | H3: Default note
A4: MARKET & COMMISSION (v6 base case)
A5: TAM travellers (#) | B5: 85000000 | C5: 70000000 | D5: 95000000 | E5: 520000000 | F5: Reachable UK + key EU traveller pool | G5: =CHOOSE(scenario_idx,B5,C5,D5,E5)
A6: Average booking value (£) | B6: 480 | C6: 420 | D6: 540 | E6: 410 | F6: Avg per booking | G6: =CHOOSE(scenario_idx,B6,C6,D6,E6)
A7: Bookings per traveller / yr | B7: 1.6 | C7: 1.4 | D7: 1.8 | E7: 1.5 | F7: Attach rate | G7: =CHOOSE(scenario_idx,B7,C7,D7,E7)
A8: SAM % of TAM | B8: 0.28 | C8: 0.22 | D8: 0.35 | E8: 0.26 | F8: Creator-led discoverable inventory | G8: =CHOOSE(scenario_idx,B8,C8,D8,E8)
A9: Gross commission % | B9: 0.11 | C9: 0.11 | D9: 0.11 | E9: 0.11 | F9: 11% headline to operators (v6 — was 8%) | G9: 0.11
A10: Creator share — Founding | B10: 0.5 | C10: 0.5 | D10: 0.5 | E10: 0.5 | F10: First 500, lifetime | G10: =CHOOSE(scenario_idx,B10,C10,D10,E10)
A11: Creator share — Power | B11: 0.5 | C11: 0.5 | D11: 0.5 | E11: 0.5 | F11: >£25k rolling 12mo | G11: =CHOOSE(scenario_idx,B11,C11,D11,E11)
A12: Creator share — New (0–6mo) | B12: 0.5 | C12: 0.5 | D12: 0.5 | E12: 0.5 | G12: =CHOOSE(scenario_idx,B12,C12,D12,E12)
A13: Creator share — Maturing (7–18mo) | B13: 0.4 | C13: 0.4 | D13: 0.4 | E13: 0.4 | G13: =CHOOSE(scenario_idx,B13,C13,D13,E13)
A14: Creator share — Mature (19mo+) | B14: 0.3 | C14: 0.3 | D14: 0.3 | E14: 0.3 | G14: =CHOOSE(scenario_idx,B14,C14,D14,E14)
A15: CREATOR FUNNEL — Active creators (year-end anchors)
A16: Active creators @ M0 | B16: 0 | C16: 0 | D16: 0 | E16: 0 | G16: =CHOOSE(scenario_idx,B16,C16,D16,E16)
A17: Active creators @ M12 | B17: 500 | C17: 350 | D17: 700 | E17: 1500 | F17: v6 Y1 | G17: =CHOOSE(scenario_idx,B17,C17,D17,E17)
A18: Active creators @ M24 | B18: 2400 | C18: 1500 | D18: 3500 | E18: 9000 | F18: v6 Y2 | G18: =CHOOSE(scenario_idx,B18,C18,D18,E18)
A19: Active creators @ M36 | B19: 6800 | C19: 4200 | D19: 9500 | E19: 32000 | F19: v6 Y3 | G19: =CHOOSE(scenario_idx,B19,C19,D19,E19)
A20: Active creators @ M48 | B20: 14000 | C20: 9000 | D20: 19000 | E20: 70000 | F20: v6 Y4 | G20: =CHOOSE(scenario_idx,B20,C20,D20,E20)
A21: Active creators @ M60 | B21: 24000 | C21: 16000 | D21: 32000 | E21: 120000 | F21: v6 Y5 | G21: =CHOOSE(scenario_idx,B21,C21,D21,E21)
A22: Monthly creator churn % | B22: 0.02 | C22: 0.035 | D22: 0.012 | E22: 0.018 | F22: Logo churn | G22: =CHOOSE(scenario_idx,B22,C22,D22,E22)
A23: CREATOR GBV/active (monthly £, year-end anchors)
A24: GBV/active/mo @ M12 (£) | B24: 1000 | C24: 850 | D24: 1150 | E24: 900 | F24: Ramp anchor | G24: =CHOOSE(scenario_idx,B24,C24,D24,E24)
A25: GBV/active/mo @ M24 (£) | B25: 1200 | C25: 1000 | D25: 1350 | E25: 1000 | G25: =CHOOSE(scenario_idx,B25,C25,D25,E25)
A26: GBV/active/mo @ M36 (£) | B26: 1350 | C26: 1100 | D26: 1500 | E26: 1080 | G26: =CHOOSE(scenario_idx,B26,C26,D26,E26)
A27: GBV/active/mo @ M48 (£) | B27: 1450 | C27: 1180 | D27: 1620 | E27: 1140 | G27: =CHOOSE(scenario_idx,B27,C27,D27,E27)
A28: GBV/active/mo @ M60 (£) | B28: 1540 | C28: 1250 | D28: 1700 | E28: 1180 | F28: v6 implied £18.5k/yr | G28: =CHOOSE(scenario_idx,B28,C28,D28,E28)
A29: CREATOR TIER MIX (year-end shares)
A30: Mix — Founding Y1 | B30: 1 | C30: 1 | D30: 1 | E30: 1 | G30: =CHOOSE(scenario_idx,B30,C30,D30,E30)
A31: Mix — Founding Y2 | B31: 0.45 | C31: 0.45 | D31: 0.45 | E31: 0.45 | G31: =CHOOSE(scenario_idx,B31,C31,D31,E31)
A32: Mix — Founding Y3 | B32: 0.22 | C32: 0.22 | D32: 0.22 | E32: 0.22 | G32: =CHOOSE(scenario_idx,B32,C32,D32,E32)
A33: Mix — Founding Y4 | B33: 0.12 | C33: 0.12 | D33: 0.12 | E33: 0.12 | G33: =CHOOSE(scenario_idx,B33,C33,D33,E33)
A34: Mix — Founding Y5 | B34: 0.08 | C34: 0.08 | D34: 0.08 | E34: 0.08 | G34: =CHOOSE(scenario_idx,B34,C34,D34,E34)
A35: Mix — Power Y1 | B35: 0 | C35: 0 | D35: 0 | E35: 0 | G35: =CHOOSE(scenario_idx,B35,C35,D35,E35)
A36: Mix — Power Y2 | B36: 0.05 | C36: 0.05 | D36: 0.05 | E36: 0.05 | G36: =CHOOSE(scenario_idx,B36,C36,D36,E36)
A37: Mix — Power Y3 | B37: 0.18 | C37: 0.18 | D37: 0.18 | E37: 0.18 | G37: =CHOOSE(scenario_idx,B37,C37,D37,E37)
A38: Mix — Power Y4 | B38: 0.28 | C38: 0.28 | D38: 0.28 | E38: 0.28 | G38: =CHOOSE(scenario_idx,B38,C38,D38,E38)
A39: Mix — Power Y5 | B39: 0.34 | C39: 0.34 | D39: 0.34 | E39: 0.34 | G39: =CHOOSE(scenario_idx,B39,C39,D39,E39)
A40: Mix — New Y1 | B40: 0 | C40: 0 | D40: 0 | E40: 0 | G40: =CHOOSE(scenario_idx,B40,C40,D40,E40)
A41: Mix — New Y2 | B41: 0.35 | C41: 0.35 | D41: 0.35 | E41: 0.35 | G41: =CHOOSE(scenario_idx,B41,C41,D41,E41)
... A54: Mix — Mature Y5 | B54: 0.32 | C54: 0.32 | D54: 0.32 | E54: 0.32 | G54: =CHOOSE(scenario_idx,B54,C54,D54,E54)
A55: OPERATOR SUPPLY
A56: Starting operators @ M0 | B56: 20 | C56: 10 | D56: 35 | E56: 60 | F56: Verified hotel/experience partners | G56: =CHOOSE(scenario_idx,B56,C56,D56,E56)
A57: New operators / month | B57: 12 | C57: 7 | D57: 18 | E57: 60 | F57: Net add | G57: =CHOOSE(scenario_idx,B57,C57,D57,E57)
A58: Monthly operator churn % | B58: 0.01 | C58: 0.02 | D58: 0.005 | E58: 0.01 | G58: =CHOOSE(scenario_idx,B58,C58,D58,E58)
A59: Partner success £/operator/mo | B59: 30 | C59: 30 | D59: 25 | E59: 28 | F59: Account mgmt | G59: =CHOOSE(scenario_idx,B59,C59,D59,E59)
A60: UNIT COSTS
A61: Payment processing % of GBV | B61: 0.029 | C61: 0.029 | D61: 0.029 | E61: 0.029 | F61: Stripe blended global (v6 — was 1.5%) | G61: 0.029
A62: Payment processing fixed £ / booking | B62: 0.2 | C62: 0.2 | D62: 0.2 | E62: 0.2 | G62: =CHOOSE(scenario_idx,B62,C62,D62,E62)
A63: Cloud hosting £/active creator/mo | B63: 0.4 | C63: 0.5 | D63: 0.3 | E63: 0.4 | F63: Supabase + CF | G63: =CHOOSE(scenario_idx,B63,C63,D63,E63)
A64: Video CDN £/1k plays | B64: 0.8 | C64: 1 | D64: 0.6 | E64: 0.8 | F64: Bunny.net-class | G64: =CHOOSE(scenario_idx,B64,C64,D64,E64)
A65: Avg video plays / active creator / mo | B65: 1500 | C65: 1200 | D65: 1800 | E65: 1500 | G65: =CHOOSE(scenario_idx,B65,C65,D65,E65)
A66: AI / Lovable Cloud £/mo @ M1 | B66: 500 | C66: 500 | D66: 500 | E66: 800 | G66: =CHOOSE(scenario_idx,B66,C66,D66,E66)
A67: AI cost monthly growth % | B67: 0.05 | C67: 0.06 | D67: 0.04 | E67: 0.05 | F67: Compounded | G67: =CHOOSE(scenario_idx,B67,C67,D67,E67)
A68: Creator support £/active/mo | B68: 0.8 | C68: 1 | D68: 0.6 | E68: 0.8 | F68: Tier-1 | G68: =CHOOSE(scenario_idx,B68,C68,D68,E68)
A69: UK PAYROLL ON-COSTS
A70: Employer NIC % | B70: 0.138 | C70: 0.138 | D70: 0.138 | F70: Flat applied to base | G70: =CHOOSE(scenario_idx,B70,C70,D70,E70)
A71: Employer pension % | B71: 0.03 | C71: 0.03 | D71: 0.03 | F71: Auto-enrol minimum | G71: =CHOOSE(scenario_idx,B71,C71,D71,E71)
A72: Apprenticeship Levy % | B72: 0.005 | C72: 0.005 | D72: 0.005 | F72: If paybill > £3M | G72: =CHOOSE(scenario_idx,B72,C72,D72,E72)
A73: Apprenticeship Levy from month | B73: 24 | C73: 24 | D73: 24 | G73: =CHOOSE(scenario_idx,B73,C73,D73,E73)
A74: Benefits £/FTE/yr | B74: 3600 | C74: 3000 | D74: 4500 | F74: Health, equipment | G74: =CHOOSE(scenario_idx,B74,C74,D74,E74)
A75: Recruitment fee % of base | B75: 0.15 | C75: 0.18 | D75: 0.12 | F75: One-off in hire month | G75: =CHOOSE(scenario_idx,B75,C75,D75,E75)
A76: Annual salary inflation % | B76: 0.04 | C76: 0.05 | D76: 0.03 | F76: Applied at M13/25/37/49 | G76: =CHOOSE(scenario_idx,B76,C76,D76,E76)
A77: NON-PAYROLL OPEX (£/month by band)
A78: Co-working / office — M1-6 | B78: 2000 | C78: 2200 | D78: 1800 | G78: =CHOOSE(scenario_idx,B78,C78,D78,E78)
A79: Co-working / office — M7-12 | B79: 4000 | C79: 4400 | D79: 3600 | G79: =CHOOSE(scenario_idx,B79,C79,D79,E79)
A80: Co-working / office — M13-24 | B80: 6000 | C80: 6600 | D80: 5400 | G80: =CHOOSE(scenario_idx,B80,C80,D80,E80)
A81: Co-working / office — M25-36 | B81: 10000 | C81: 11000 | D81: 9000 | G81: =CHOOSE(scenario_idx,B81,C81,D81,E81)
A82: Co-working / office — M37-60 | B82: 18000 | C82: 19800 | D82: 16200 | G82: =CHOOSE(scenario_idx,B82,C82,D82,E82)
A83: Legal & company sec — M1-6 | B83: 1500 | C83: 1650 | D83: 1350 | G83: =CHOOSE(scenario_idx,B83,C83,D83,E83)
A84: Legal & company sec — M7-12 | B84: 1500 | C84: 1650 | D84: 1350 | G84: =CHOOSE(scenario_idx,B84,C84,D84,E84)
A85: Legal & company sec — M13-24 | B85: 2000 | C85: 2200 | D85: 1800 | G85: =CHOOSE(scenario_idx,B85,C85,D85,E85)
A86: Legal & company sec — M25-36 | B86: 3000 | C86: 3300 | D86: 2700 | G86: =CHOOSE(scenario_idx,B86,C86,D86,E86)
A87: Legal & company sec — M37-60 | B87: 4500 | C87: 4950 | D87: 4050 | G87: =CHOOSE(scenario_idx,B87,C87,D87,E87)
A88: Accounting / R&D tax — M1-6 | B88: 1000 | C88: 1100 | D88: 900 | G88: =CHOOSE(scenario_idx,B88,C88,D88,E88)
A89: Accounting / R&D tax — M7-12 | B89: 1500 | C89: 1650 | D89: 1350 | G89: =CHOOSE(scenario_idx,B89,C89,D89,E89)
... A112: Travel / events — M37-60 | B112: 18000 | C112: 19800 | D112: 16200 | G112: =CHOOSE(scenario_idx,B112,C112,D112,E112)
A113: Contingency % of non-payroll opex | B113: 0.1 | C113: 0.12 | D113: 0.08 | F113: Applied to sum of above | G113: =CHOOSE(scenario_idx,B113,C113,D113,E113)
A114: CREATOR ACQUISITION SPEND (channel total £/month)
A115: Creator acq — M1-6 (£/mo) | B115: 8000 | C115: 6000 | D115: 12000 | F115: Founding-500 seed + events | G115: =CHOOSE(scenario_idx,B115,C115,D115,E115)
A116: Creator acq — M7-12 | B116: 20000 | C116: 15000 | D116: 30000 | G116: =CHOOSE(scenario_idx,B116,C116,D116,E116)
A117: Creator acq — M13-24 | B117: 35000 | C117: 25000 | D117: 55000 | G117: =CHOOSE(scenario_idx,B117,C117,D117,E117)
A118: Creator acq — M25-36 | B118: 60000 | C118: 45000 | D118: 90000 | G118: =CHOOSE(scenario_idx,B118,C118,D118,E118)
A119: Creator acq — M37-60 | B119: 90000 | C119: 65000 | D119: 140000 | G119: =CHOOSE(scenario_idx,B119,C119,D119,E119)
A120: Operator GTM £/mo | B120: 5000 | C120: 4000 | D120: 7000 | F120: Outbound + events | G120: =CHOOSE(scenario_idx,B120,C120,D120,E120)
A121: FUNDING — multi-tranche
A122: Starting cash @ M0 (£) | B122: 50000 | C122: 25000 | D122: 100000 | F122: Pre-seed | G122: =CHOOSE(scenario_idx,B122,C122,D122,E122)
A123: Seed raise (£) | B123: 2000000 | C123: 1500000 | D123: 3000000 | G123: =CHOOSE(scenario_idx,B123,C123,D123,E123)
A124: Seed close month | B124: 1 | C124: 1 | D124: 1 | G124: =CHOOSE(scenario_idx,B124,C124,D124,E124)
A125: Series A raise (£) | B125: 8000000 | C125: 5000000 | D125: 12000000 | G125: =CHOOSE(scenario_idx,B125,C125,D125,E125)
A126: Series A close month | B126: 22 | C126: 26 | D126: 18 | G126: =CHOOSE(scenario_idx,B126,C126,D126,E126)
A127: Series B raise (£) | B127: 20000000 | C127: 12000000 | D127: 35000000 | G127: =CHOOSE(scenario_idx,B127,C127,D127,E127)
A128: Series B close month | B128: 44 | C128: 50 | D128: 38 | G128: =CHOOSE(scenario_idx,B128,C128,D128,E128)

Sheet channel_cac
A1: Channel CAC — Creator & Operator acquisition
A3: Channel split shown for CAC discipline. Monthly £ totals on assumptions drive cash.
A5: CREATOR ACQUISITION
A6: Channel | B6: Spend share | C6: CPL £ | D6: Conv % | E6: CAC £ | F6: New creators/mo @ M12 | G6: CAC @ M36 | H6: New /mo @ M36
A7: Paid Social (TikTok/IG) | B7: 0.4 | C7: 8 | D7: 0.06 | E7: =IF(D7>0,C7/D7,0) | F7: =IFERROR(assumptions!$G$116*B7/E7,0) | G7: =E7*1.1 | H7: =IFERROR(assumptions!$G$118*B7/G7,0)
A8: Creator Referral | B8: 0.2 | C8: 3 | D8: 0.18 | E8: =IF(D8>0,C8/D8,0) | F8: =IFERROR(assumptions!$G$116*B8/E8,0) | G8: =E8*1.1 | H8: =IFERROR(assumptions!$G$118*B8/G8,0)
A9: Founding-500 Programme | B9: 0.15 | C9: 0 | D9: 0 | E9: 200 | F9: =IFERROR(assumptions!$G$116*B9/E9,0) | G9: =E9*1.1 | H9: =IFERROR(assumptions!$G$118*B9/G9,0)
A10: SEO / Content | B10: 0.1 | C10: 4 | D10: 0.05 | E10: =IF(D10>0,C10/D10,0) | F10: =IFERROR(assumptions!$G$116*B10/E10,0) | G10: =E10*1.1 | H10: =IFERROR(assumptions!$G$118*B10/G10,0)
A11: Events / meetups | B11: 0.1 | C11: 25 | D11: 0.1 | E11: =IF(D11>0,C11/D11,0) | F11: =IFERROR(assumptions!$G$116*B11/E11,0) | G11: =E11*1.1 | H11: =IFERROR(assumptions!$G$118*B11/G11,0)
A12: Direct outreach | B12: 0.05 | C12: 12 | D12: 0.08 | E12: =IF(D12>0,C12/D12,0) | F12: =IFERROR(assumptions!$G$116*B12/E12,0) | G12: =E12*1.1 | H12: =IFERROR(assumptions!$G$118*B12/G12,0)
A13: Total | B13: =SUM(B7:B12) | E13: =SUMPRODUCT(B7:B12,E7:E12) | F13: =SUM(F7:F12) | G13: =SUMPRODUCT(B7:B12,G7:G12) | H13: =SUM(H7:H12)
A16: OPERATOR ACQUISITION
A17: Channel | B17: Spend share | C17: CPL £ | D17: Conv % | E17: CAC £ | F17: New ops/mo @ M12 | G17: CAC @ M36 | H17: New ops/mo @ M36
A18: Outbound sales | B18: 0.55 | C18: 0 | D18: 0 | E18: 400 | F18: =IFERROR(assumptions!$G$120*B18/E18,0) | G18: =E18*1.1 | H18: =IFERROR(assumptions!$G$120*B18/G18,0)
A19: Inbound demo | B19: 0.2 | C19: 20 | D19: 0.25 | E19: =IF(D19>0,C19/D19,0) | F19: =IFERROR(assumptions!$G$120*B19/E19,0) | G19: =E19*1.1 | H19: =IFERROR(assumptions!$G$120*B19/G19,0)
A20: Partner referral | B20: 0.15 | C20: 10 | D20: 0.4 | E20: =IF(D20>0,C20/D20,0) | F20: =IFERROR(assumptions!$G$120*B20/E20,0) | G20: =E20*1.1 | H20: =IFERROR(assumptions!$G$120*B20/G20,0)
A21: Events/trade show | B21: 0.1 | C21: 50 | D21: 0.15 | E21: =IF(D21>0,C21/D21,0) | F21: =IFERROR(assumptions!$G$120*B21/E21,0) | G21: =E21*1.1 | H21: =IFERROR(assumptions!$G$120*B21/G21,0)
A22: Total | E22: =SUMPRODUCT(B18:B21,E18:E21) | F22: =SUM(F18:F21)

Sheet headcount_uk
A1: UK Headcount Plan (60 months) — loaded cost incl. NIC, pension, benefits, recruitment
A3: # | B3: Role | C3: Team | D3: Base £/yr | E3: Start M | F3: End M | G3: M1 | H3: M2 | I3: M3 | J3: M4 | K3: M5 | L3: M6 | M3: M7 | N3: M8 | O3: M9 | P3: M10 | Q3: M11 | R3: M12 | S3: M13 | T3: M14 | U3: M15 | V3: M16 | W3: M17 | X3: M18 | Y3: M19 | Z3: M20 | AA3: M21 | AB3: M22 | AC3: M23 | AD3: M24 | AE3: M25 | AF3: M26 | AG3: M27 | AH3: M28 | AI3: M29 | AJ3: M30 | AK3: M31 | AL3: M32 | AM3: M33 | AN3: M34 | AO3: M35 | AP3: M36 | AQ3: M37 | AR3: M38 | AS3: M39 | AT3: M40 | AU3: M41 | AV3: M42 | AW3: M43 | AX3: M44 | AY3: M45 | AZ3: M46 | BA3: M47 | BB3: M48 | BC3: M49 | BD3: M50 | BE3: M51 | BF3: M52 | BG3: M53 | BH3: M54 | BI3: M55 | BJ3: M56 | BK3: M57 | BL3: M58 | BM3: M59 | BN3: M60
A4: 1 | B4: CEO / Founder | C4: exec | D4: 85000 | E4: 1 | G4: =IF(AND(1>=E4,OR(F4="",1<=F4)),(D4*(1+assumptions!$G$76)^0/12*(1+assumptions!$G$70+assumptions!$G$71+IF(1>=assumptions!$G$73,assumptions!$G$72,0))+assumptions!$G$74/12)+IF(1=E4,D4*assumptions!$G$75,0),0) | H4: =IF(AND(2>=E4,OR(F4="",2<=F4)),(D4*(1+assumptions!$G$76)^0/12*(1+assumptions!$G$70+assumptions!$G$71+IF(2>=assumptions!$G$73,assumptions!$G$72,0))+assumptions!$G$74/12)+IF(2=E4,D4*assumptions!$G$75,0),0) | I4: =IF(AND(3>=E4,OR(F4="",3<=F4)),(D4*(1+assumptions!$G$76)^0/12*(1+assumptions!$G$70+assumptions!$G$71+IF(3>=assumptions!$G$73,assumptions!$G$72,0))+assumptions!$G$74/12)+IF(3=E4,D4*assumptions!$G$75,0),0) | J4: =IF(AND(4>=E4,OR(F4="",4<=F4)),(D4*(1+assumptions!$G$76)^0/12*(1+assumptions!$G$70+assumptions!$G$71+IF(4>=assumptions!$G$73,assumptions!$G$72,0))+assumptions!$G$74/12)+IF(4=E4,D4*assumptions!$G$75,0),0) | K4: =IF(AND(5>=E4,OR(F4="",5<=F4)),(D4*(1+assumptions!$G$76)^0/12*(1+assumptions!$G$70+assumptions!$G$71+IF(5>=assumptions!$G$73,assumptions!$G$72,0))+assumptions!$G$74/12)+IF(5=E4,D4*assumptions!$G$75,0),0) | L4: =IF(AND(6>=E4,OR(F4="",6<=F4)),(D4*(1+assumptions!$G$76)^0/12*(1+assumptions!$G$70+assumptions!$G$71+IF(6>=assumptions!$G$73,assumptions!$G$72,0))+assumptions!$G$74/12)+IF(6=E4,D4*assumptions!$G$75,0),0) | M4: =IF(AND(7>=E4,OR(F4="",7<=F4)),(D4*(1+assumptions!$G$76)^0/12*(1+assumptions!$G$70+assumptions!$G$71+IF(7>=assumptions!$G$73,assumptions!$G$72,0))+assumptions!$G$74/12)+IF(7=E4,D4*assumptions!$G$75,0),0) | N4: =IF(AND(8>=E4,OR(F4="",8<=F4)),(D4*(1+assumptions!$G$76)^0/12*(1+assumptions!$G$70+assumptions!$G$71+IF(8>=assumptions!$G$73,assumptions!$G$72,0))+assumptions!$G$74/12)+IF(8=E4,D4*assumptions!$G$75,0),0) | O4: =IF(AND(9>=E4,OR(F4="",9<=F4)),(D4*(1+assumptions!$G$76)^0/12*(1+assumptions!$G$70+assumptions!$G$71+IF(9>=assumptions!$G$73,assumptions!$G$72,0))+assumptions!$G$74/12)+IF(9=E4,D4*assumptions!$G$75,0),0) | P4: =IF(AND(10>=E4,OR(F4="",10<=F4)),(D4*(1+assumptions!$G$76)^0/12*(1+assumptions!$G$70+assumptions!$G$71+IF(10>=assumptions!$G$73,assumptions!$G$72,0))+assumptions!$G$74/12)+IF(10=E4,D4*assumptions!$G$75,0),0) | Q4: =IF(AND(11>=E4,OR(F4="",11<=F4)),(D4*(1+assumptions!$G$76)^0/12*(1+assumptions!$G$70+assumptions!$G$71+IF(11>=assumptions!$G$73,assumptions!$G$72,0))+assumptions!$G$74/12)+IF(11=E4,D4*assumptions!$G$75,0),0) | R4: =IF(AND(12>=E4,OR(F4="",12<=F4)),(D4*(1+assumptions!$G$76)^0/12*(1+assumptions!$G$70+assumptions!$G$71+IF(12>=assumptions!$G$73,assumptions!$G$72,0))+assumptions!$G$74/12)+IF(12=E4,D4*assumptions!$G$75,0),0) | S4: =IF(AND(13>=E4,OR(F4="",13<=F4)),(D4*(1+assumptions!$G$76)^1/12*(1+assumptions!$G$70+assumptions!$G$71+IF(13>=assumptions!$G$73,assumptions!$G$72,0))+assumptions!$G$74/12)+IF(13=E4,D4*assumptions!$G$75,0),0) | T4: =IF(AND(14>=E4,OR(F4="",14<=F4)),(D4*(1+assumptions!$G$76)^1/12*(1+assumptions!$G$70+assumptions!$G$71+IF(14>=assumptions!$G$73,assumptions!$G$72,0))+assumptions!$G$74/12)+IF(14=E4,D4*assumptions!$G$75,0),0) | U4: =IF(AND(15>=E4,OR(F4="",15<=F4)),(D4*(1+assumptions!$G$76)^1/12*(1+assumptions!$G$70+assumptions!$G$71+IF(15>=assumptions!$G$73,assumptions!$G$72,0))+assumptions!$G$74/12)+IF(15=E4,D4*assumptions!$G$75,0),0) | V4: =IF(AND(16>=E4,OR(F4="",16<=F4)),(D4*(1+assumptions!$G$76)^1/12*(1+assumptions!$G$70+assumptions!$G$71+IF(16>=assumptions!$G$73,assumptions!$G$72,0))+assumptions!$G$74/12)+IF(16=E4,D4*assumptions!$G$75,0),0) | W4: =IF(AND(17>=E4,OR(F4="",17<=F4)),(D4*(1+assumptions!$G$76)^1/12*(1+assumptions!$G$70+assumptions!$G$71+IF(17>=assumptions!$G$73,assumptions!$G$72,0))+assumptions!$G$74/12)+IF(17=E4,D4*assumptions!$G$75,0),0) | X4: =IF(AND(18>=E4,OR(F4="",18<=F4)),(D4*(1+assumptions!$G$76)^1/12*(1+assumptions!$G$70+assumptions!$G$71+IF(18>=assumptions!$G$73,assumptions!$G$72,0))+assumptions!$G$74/12)+IF(18=E4,D4*assumptions!$G$75,0),0) | Y4: =IF(AND(19>=E4,OR(F4="",19<=F4)),(D4*(1+assumptions!$G$76)^1/12*(1+assumptions!$G$70+assumptions!$G$71+IF(19>=assumptions!$G$73,assumptions!$G$72,0))+assumptions!$G$74/12)+IF(19=E4,D4*assumptions!$G$75,0),0) | Z4: =IF(AND(20>=E4,OR(F4="",20<=F4)),(D4*(1+assumptions!$G$76)^1/12*(1+assumptions!$G$70+assumptions!$G$71+IF(20>=assumptions!$G$73,assumptions!$G$72,0))+assumptions!$G$74/12)+IF(20=E4,D4*assumptions!$G$75,0),0) | AA4: =IF(AND(21>=E4,OR(F4="",21<=F4)),(D4*(1+assumptions!$G$76)^1/12*(1+assumptions!$G$70+assumptions!$G$71+IF(21>=assumptions!$G$73,assumptions!$G$72,0))+assumptions!$G$74/12)+IF(21=E4,D4*assumptions!$G$75,0),0) | AB4: =IF(AND(22>=E4,OR(F4="",22<=F4)),(D4*(1+assumptions!$G$76)^1/12*(1+assumptions!$G$70+assumptions!$G$71+IF(22>=assumptions!$G$73,assumptions!$G$72,0))+assumptions!$G$74/12)+IF(22=E4,D4*assumptions!$G$75,0),0) | AC4: =IF(AND(23>=E4,OR(F4="",23<=F4)),(D4*(1+assumptions!$G$76)^1/12*(1+assumptions!$G$70+assumptions!$G$71+IF(23>=assumptions!$G$73,assumptions!$G$72,0))+assumptions!$G$74/12)+IF(23=E4,D4*assumptions!$G$75,0),0) | AD4: =IF(AND(24>=E4,OR(F4="",24<=F4)),(D4*(1+assumptions!$G$76)^1/12*(1+assumptions!$G$70+assumptions!$G$71+IF(24>=assumptions!$G$73,assumptions!$G$72,0))+assumptions!$G$74/12)+IF(24=E4,D4*assumptions!$G$75,0),0) | AE4: =IF(AND(25>=E4,OR(F4="",25<=F4)),(D4*(1+assumptions!$G$76)^2/12*(1+assumptions!$G$70+assumptions!$G$71+IF(25>=assumptions!$G$73,assumptions!$G$72,0))+assumptions!$G$74/12)+IF(25=E4,D4*assumptions!$G$75,0),0) | AF4: =IF(AND(26>=E4,OR(F4="",26<=F4)),(D4*(1+assumptions!$G$76)^2/12*(1+assumptions!$G$70+assumptions!$G$71+IF(26>=assumptions!$G$73,assumptions!$G$72,0))+assumptions!$G$74/12)+IF(26=E4,D4*assumptions!$G$75,0),0) | AG4: =IF(AND(27>=E4,OR(F4="",27<=F4)),(D4*(1+assumptions!$G$76)^2/12*(1+assumptions!$G$70+assumptions!$G$71+IF(27>=assumptions!$G$73,assumptions!$G$72,0))+assumptions!$G$74/12)+IF(27=E4,D4*assumptions!$G$75,0),0) | AH4: =IF(AND(28>=E4,OR(F4="",28<=F4)),(D4*(1+assumptions!$G$76)^2/12*(1+assumptions!$G$70+assumptions!$G$71+IF(28>=assumptions!$G$73,assumptions!$G$72,0))+assumptions!$G$74/12)+IF(28=E4,D4*assumptions!$G$75,0),0) | AI4: =IF(AND(29>=E4,OR(F4="",29<=F4)),(D4*(1+assumptions!$G$76)^2/12*(1+assumptions!$G$70+assumptions!$G$71+IF(29>=assumptions!$G$73,assumptions!$G$72,0))+assumptions!$G$74/12)+IF(29=E4,D4*assumptions!$G$75,0),0) | AJ4: =IF(AND(30>=E4,OR(F4="",30<=F4)),(D4*(1+assumptions!$G$76)^2/12*(1+assumptions!$G$70+assumptions!$G$71+IF(30>=assumptions!$G$73,assumptions!$G$72,0))+assumptions!$G$74/12)+IF(30=E4,D4*assumptions!$G$75,0),0) | AK4: =IF(AND(31>=E4,OR(F4="",31<=F4)),(D4*(1+assumptions!$G$76)^2/12*(1+assumptions!$G$70+assumptions!$G$71+IF(31>=assumptions!$G$73,assumptions!$G$72,0))+assumptions!$G$74/12)+IF(31=E4,D4*assumptions!$G$75,0),0) | AL4: =IF(AND(32>=E4,OR(F4="",32<=F4)),(D4*(1+assumptions!$G$76)^2/12*(1+assumptions!$G$70+assumptions!$G$71+IF(32>=assumptions!$G$73,assumptions!$G$72,0))+assumptions!$G$74/12)+IF(32=E4,D4*assumptions!$G$75,0),0) | AM4: =IF(AND(33>=E4,OR(F4="",33<=F4)),(D4*(1+assumptions!$G$76)^2/12*(1+assumptions!$G$70+assumptions!$G$71+IF(33>=assumptions!$G$73,assumptions!$G$72,0))+assumptions!$G$74/12)+IF(33=E4,D4*assumptions!$G$75,0),0) | AN4: =IF(AND(34>=E4,OR(F4="",34<=F4)),(D4*(1+assumptions!$G$76)^2/12*(1+assumptions!$G$70+assumptions!$G$71+IF(34>=assumptions!$G$73,assumptions!$G$72,0))+assumptions!$G$74/12)+IF(34=E4,D4*assumptions!$G$75,0),0) | AO4: =IF(AND(35>=E4,OR(F4="",35<=F4)),(D4*(1+assumptions!$G$76)^2/12*(1+assumptions!$G$70+assumptions!$G$71+IF(35>=assumptions!$G$73,assumptions!$G$72,0))+assumptions!$G$74/12)+IF(35=E4,D4*assumptions!$G$75,0),0) | AP4: =IF(AND(36>=E4,OR(F4="",36<=F4)),(D4*(1+assumptions!$G$76)^2/12*(1+assumptions!$G$70+assumptions!$G$71+IF(36>=assumptions!$G$73,assumptions!$G$72,0))+assumptions!$G$74/12)+IF(36=E4,D4*assumptions!$G$75,0),0) | AQ4: =IF(AND(37>=E4,OR(F4="",37<=F4)),(D4*(1+assumptions!$G$76)^3/12*(1+assumptions!$G$70+assumptions!$G$71+IF(37>=assumptions!$G$73,assumptions!$G$72,0))+assumptions!$G$74/12)+IF(37=E4,D4*assumptions!$G$75,0),0) | AR4: =IF(AND(38>=E4,OR(F4="",38<=F4)),(D4*(1+assumptions!$G$76)^3/12*(1+assumptions!$G$70+assumptions!$G$71+IF(38>=assumptions!$G$73,assumptions!$G$72,0))+assumptions!$G$74/12)+IF(38=E4,D4*assumptions!$G$75,0),0) | AS4: =IF(AND(39>=E4,OR(F4="",39<=F4)),(D4*(1+assumptions!$G$76)^3/12*(1+assumptions!$G$70+assumptions!$G$71+IF(39>=assumptions!$G$73,assumptions!$G$72,0))+assumptions!$G$74/12)+IF(39=E4,D4*assumptions!$G$75,0),0) | AT4: =IF(AND(40>=E4,OR(F4="",40<=F4)),(D4*(1+assumptions!$G$76)^3/12*(1+assumptions!$G$70+assumptions!$G$71+IF(40>=assumptions!$G$73,assumptions!$G$72,0))+assumptions!$G$74/12)+IF(40=E4,D4*assumptions!$G$75,0),0) | AU4: =IF(AND(41>=E4,OR(F4="",41<=F4)),(D4*(1+assumptions!$G$76)^3/12*(1+assumptions!$G$70+assumptions!$G$71+IF(41>=assumptions!$G$73,assumptions!$G$72,0))+assumptions!$G$74/12)+IF(41=E4,D4*assumptions!$G$75,0),0) | AV4: =IF(AND(42>=E4,OR(F4="",42<=F4)),(D4*(1+assumptions!$G$76)^3/12*(1+assumptions!$G$70+assumptions!$G$71+IF(42>=assumptions!$G$73,assumptions!$G$72,0))+assumptions!$G$74/12)+IF(42=E4,D4*assumptions!$G$75,0),0) | AW4: =IF(AND(43>=E4,OR(F4="",43<=F4)),(D4*(1+assumptions!$G$76)^3/12*(1+assumptions!$G$70+assumptions!$G$71+IF(43>=assumptions!$G$73,assumptions!$G$72,0))+assumptions!$G$74/12)+IF(43=E4,D4*assumptions!$G$75,0),0) | AX4: =IF(AND(44>=E4,OR(F4="",44<=F4)),(D4*(1+assumptions!$G$76)^3/12*(1+assumptions!$G$70+assumptions!$G$71+IF(44>=assumptions!$G$73,assumptions!$G$72,0))+assumptions!$G$74/12)+IF(44=E4,D4*assumptions!$G$75,0),0) | AY4: =IF(AND(45>=E4,OR(F4="",45<=F4)),(D4*(1+assumptions!$G$76)^3/12*(1+assumptions!$G$70+assumptions!$G$71+IF(45>=assumptions!$G$73,assumptions!$G$72,0))+assumptions!$G$74/12)+IF(45=E4,D4*assumptions!$G$75,0),0) | AZ4: =IF(AND(46>=E4,OR(F4="",46<=F4)),(D4*(1+assumptions!$G$76)^3/12*(1+assumptions!$G$70+assumptions!$G$71+IF(46>=assumptions!$G$73,assumptions!$G$72,0))+assumptions!$G$74/12)+IF(46=E4,D4*assumptions!$G$75,0),0) | BA4: =IF(AND(47>=E4,OR(F4="",47<=F4)),(D4*(1+assumptions!$G$76)^3/12*(1+assumptions!$G$70+assumptions!$G$71+IF(47>=assumptions!$G$73,assumptions!$G$72,0))+assumptions!$G$74/12)+IF(47=E4,D4*assumptions!$G$75,0),0) | BB4: =IF(AND(48>=E4,OR(F4="",48<=F4)),(D4*(1+assumptions!$G$76)^3/12*(1+assumptions!$G$70+assumptions!$G$71+IF(48>=assumptions!$G$73,assumptions!$G$72,0))+assumptions!$G$74/12)+IF(48=E4,D4*assumptions!$G$75,0),0) | BC4: =IF(AND(49>=E4,OR(F4="",49<=F4)),(D4*(1+assumptions!$G$76)^4/12*(1+assumptions!$G$70+assumptions!$G$71+IF(49>=assumptions!$G$73,assumptions!$G$72,0))+assumptions!$G$74/12)+IF(49=E4,D4*assumptions!$G$75,0),0) | BD4: =IF(AND(50>=E4,OR(F4="",50<=F4)),(D4*(1+assumptions!$G$76)^4/12*(1+assumptions!$G$70+assumptions!$G$71+IF(50>=assumptions!$G$73,assumptions!$G$72,0))+assumptions!$G$74/12)+IF(50=E4,D4*assumptions!$G$75,0),0) | BE4: =IF(AND(51>=E4,OR(F4="",51<=F4)),(D4*(1+assumptions!$G$76)^4/12*(1+assumptions!$G$70+assumptions!$G$71+IF(51>=assumptions!$G$73,assumptions!$G$72,0))+assumptions!$G$74/12)+IF(51=E4,D4*assumptions!$G$75,0),0) | BF4: =IF(AND(52>=E4,OR(F4="",52<=F4)),(D4*(1+assumptions!$G$76)^4/12*(1+assumptions!$G$70+assumptions!$G$71+IF(52>=assumptions!$G$73,assumptions!$G$72,0))+assumptions!$G$74/12)+IF(52=E4,D4*assumptions!$G$75,0),0) | BG4: =IF(AND(53>=E4,OR(F4="",53<=F4)),(D4*(1+assumptions!$G$76)^4/12*(1+assumptions!$G$70+assumptions!$G$71+IF(53>=assumptions!$G$73,assumptions!$G$72,0))+assumptions!$G$74/12)+IF(53=E4,D4*assumptions!$G$75,0),0) | BH4: =IF(AND(54>=E4,OR(F4="",54<=F4)),(D4*(1+assumptions!$G$76)^4/12*(1+assumptions!$G$70+assumptions!$G$71+IF(54>=assumptions!$G$73,assumptions!$G$72,0))+assumptions!$G$74/12)+IF(54=E4,D4*assumptions!$G$75,0),0) | BI4: =IF(AND(55>=E4,OR(F4="",55<=F4)),(D4*(1+assumptions!$G$76)^4/12*(1+assumptions!$G$70+assumptions!$G$71+IF(55>=assumptions!$G$73,assumptions!$G$72,0))+assumptions!$G$74/12)+IF(55=E4,D4*assumptions!$G$75,0),0) | BJ4: =IF(AND(56>=E4,OR(F4="",56<=F4)),(D4*(1+assumptions!$G$76)^4/12*(1+assumptions!$G$70+assumptions!$G$71+IF(56>=assumptions!$G$73,assumptions!$G$72,0))+assumptions!$G$74/12)+IF(56=E4,D4*assumptions!$G$75,0),0) | BK4: =IF(AND(57>=E4,OR(F4="",57<=F4)),(D4*(1+assumptions!$G$76)^4/12*(1+assumptions!$G$70+assumptions!$G$71+IF(57>=assumptions!$G$73,assumptions!$G$72,0))+assumptions!$G$74/12)+IF(57=E4,D4*assumptions!$G$75,0),0) | BL4: =IF(AND(58>=E4,OR(F4="",58<=F4)),(D4*(1+assumptions!$G$76)^4/12*(1+assumptions!$G$70+assumptions!$G$71+IF(58>=assumptions!$G$73,assumptions!$G$72,0))+assumptions!$G$74/12)+IF(58=E4,D4*assumptions!$G$75,0),0) | BM4: =IF(AND(59>=E4,OR(F4="",59<=F4)),(D4*(1+assumptions!$G$76)^4/12*(1+assumptions!$G$70+assumptions!$G$71+IF(59>=assumptions!$G$73,assumptions!$G$72,0))+assumptions!$G$74/12)+IF(59=E4,D4*assumptions!$G$75,0),0) | BN4: =IF(AND(60>=E4,OR(F4="",60<=F4)),(D4*(1+assumptions!$G$76)^4/12*(1+assumptions!$G$70+assumptions!$G$71+IF(60>=assumptions!$G$73,assumptions!$G$72,0))+assumptions!$G$74/12)+IF(60=E4,D4*assumptions!$G$75,0),0)
A5: 2 | B5: CTO / Co-founder | C5: exec | D5: 85000 | E5: 1 | G5: =IF(AND(1>=E5,OR(F5="",1<=F5)),(D5*(1+assumptions!$G$76)^0/12*(1+assumptions!$G$70+assumptions!$G$71+IF(1>=assumptions!$G$73,assumptions!$G$72,0))+assumptions!$G$74/12)+IF(1=E5,D5*assumptions!$G$75,0),0) | H5: =IF(AND(2>=E5,OR(F5="",2<=F5)),(D5*(1+assumptions!$G$76)^0/12*(1+assumptions!$G$70+assumptions!$G$71+IF(2>=assumptions!$G$73,assumptions!$G$72,0))+assumptions!$G$74/12)+IF(2=E5,D5*assumptions!$G$75,0),0) | I5: =IF(AND(3>=E5,OR(F5="",3<=F5)),(D5*(1+assumptions!$G$76)^0/12*(1+assumptions!$G$70+assumptions!$G$71+IF(3>=assumptions!$G$73,assumptions!$G$72,0))+assumptions!$G$74/12)+IF(3=E5,D5*assumptions!$G$75,0),0) | J5: =IF(AND(4>=E5,OR(F5="",4<=F5)),(D5*(1+assumptions!$G$76)^0/12*(1+assumptions!$G$70+assumptions!$G$71+IF(4>=assumptions!$G$73,assumptions!$G$72,0))+assumptions!$G$74/12)+IF(4=E5,D5*assumptions!$G$75,0),0) | K5: =IF(AND(5>=E5,OR(F5="",5<=F5)),(D5*(1+assumptions!$G$76)^0/12*(1+assumptions!$G$70+assumptions!$G$71+IF(5>=assumptions!$G$73,assumptions!$G$72,0))+assumptions!$G$74/12)+IF(5=E5,D5*assumptions!$G$75,0),0) | L5: =IF(AND(6>=E5,OR(F5="",6<=F5)),(D5*(1+assumptions!$G$76)^0/12*(1+assumptions!$G$70+assumptions!$G$71+IF(6>=assumptions!$G$73,assumptions!$G$72,0))+assumptions!$G$74/12)+IF(6=E5,D5*assumptions!$G$75,0),0) | M5: =IF(AND(7>=E5,OR(F5="",7<=F5)),(D5*(1+assumptions!$G$76)^0/12*(1+assumptions!$G$70+assumptions!$G$71+IF(7>=assumptions!$G$73,assumptions!$G$72,0))+assumptions!$G$74/12)+IF(7=E5,D5*assumptions!$G$75,0),0) | N5: =IF(AND(8>=E5,OR(F5="",8<=F5)),(D5*(1+assumptions!$G$76)^0/12*(1+assumptions!$G$70+assumptions!$G$71+IF(8>=assumptions!$G$73,assumptions!$G$72,0))+assumptions!$G$74/12)+IF(8=E5,D5*assumptions!$G$75,0),0) | O5: =IF(AND(9>=E5,OR(F5="",9<=F5)),(D5*(1+assumptions!$G$76)^0/12*(1+assumptions!$G$70+assumptions!$G$71+IF(9>=assumptions!$G$73,assumptions!$G$72,0))+assumptions!$G$74/12)+IF(9=E5,D5*assumptions!$G$75,0),0) | P5: =IF(AND(10>=E5,OR(F5="",10<=F5)),(D5*(1+assumptions!$G$76)^0/12*(1+assumptions!$G$70+assumptions!$G$71+IF(10>=assumptions!$G$73,assumptions!$G$72,0))+assumptions!$G$74/12)+IF(10=E5,D5*assumptions!$G$75,0),0) | Q5: =IF(AND(11>=E5,OR(F5="",11<=F5)),(D5*(1+assumptions!$G$76)^0/12*(1+assumptions!$G$70+assumptions!$G$71+IF(11>=assumptions!$G$73,assumptions!$G$72,0))+assumptions!$G$74/12)+IF(11=E5,D5*assumptions!$G$75,0),0) | R5: =IF(AND(12>=E5,OR(F5="",12<=F5)),(D5*(1+assumptions!$G$76)^0/12*(1+assumptions!$G$70+assumptions!$G$71+IF(12>=assumptions!$G$73,assumptions!$G$72,0))+assumptions!$G$74/12)+IF(12=E5,D5*assumptions!$G$75,0),0) | S5: =IF(AND(13>=E5,OR(F5="",13<=F5)),(D5*(1+assumptions!$G$76)^1/12*(1+assumptions!$G$70+assumptions!$G$71+IF(13>=assumptions!$G$73,assumptions!$G$72,0))+assumptions!$G$74/12)+IF(13=E5,D5*assumptions!$G$75,0),0) | T5: =IF(AND(14>=E5,OR(F5="",14<=F5)),(D5*(1+assumptions!$G$76)^1/12*(1+assumptions!$G$70+assumptions!$G$71+IF(14>=assumptions!$G$73,assumptions!$G$72,0))+assumptions!$G$74/12)+IF(14=E5,D5*assumptions!$G$75,0),0) | U5: =IF(AND(15>=E5,OR(F5="",15<=F5)),(D5*(1+assumptions!$G$76)^1/12*(1+assumptions!$G$70+assumptions!$G$71+IF(15>=assumptions!$G$73,assumptions!$G$72,0))+assumptions!$G$74/12)+IF(15=E5,D5*assumptions!$G$75,0),0) | V5: =IF(AND(16>=E5,OR(F5="",16<=F5)),(D5*(1+assumptions!$G$76)^1/12*(1+assumptions!$G$70+assumptions!$G$71+IF(16>=assumptions!$G$73,assumptions!$G$72,0))+assumptions!$G$74/12)+IF(16=E5,D5*assumptions!$G$75,0),0) | W5: =IF(AND(17>=E5,OR(F5="",17<=F5)),(D5*(1+assumptions!$G$76)^1/12*(1+assumptions!$G$70+assumptions!$G$71+IF(17>=assumptions!$G$73,assumptions!$G$72,0))+assumptions!$G$74/12)+IF(17=E5,D5*assumptions!$G$75,0),0) | X5: =IF(AND(18>=E5,OR(F5="",18<=F5)),(D5*(1+assumptions!$G$76)^1/12*(1+assumptions!$G$70+assumptions!$G$71+IF(18>=assumptions!$G$73,assumptions!$G$72,0))+assumptions!$G$74/12)+IF(18=E5,D5*assumptions!$G$75,0),0) | Y5: =IF(AND(19>=E5,OR(F5="",19<=F5)),(D5*(1+assumptions!$G$76)^1/12*(1+assumptions!$G$70+assumptions!$G$71+IF(19>=assumptions!$G$73,assumptions!$G$72,0))+assumptions!$G$74/12)+IF(19=E5,D5*assumptions!$G$75,0),0) | Z5: =IF(AND(20>=E5,OR(F5="",20<=F5)),(D5*(1+assumptions!$G$76)^1/12*(1+assumptions!$G$70+assumptions!$G$71+IF(20>=assumptions!$G$73,assumptions!$G$72,0))+assumptions!$G$74/12)+IF(20=E5,D5*assumptions!$G$75,0),0) | AA5: =IF(AND(21>=E5,OR(F5="",21<=F5)),(D5*(1+assumptions!$G$76)^1/12*(1+assumptions!$G$70+assumptions!$G$71+IF(21>=assumptions!$G$73,assumptions!$G$72,0))+assumptions!$G$74/12)+IF(21=E5,D5*assumptions!$G$75,0),0) | AB5: =IF(AND(22>=E5,OR(F5="",22<=F5)),(D5*(1+assumptions!$G$76)^1/12*(1+assumptions!$G$70+assumptions!$G$71+IF(22>=assumptions!$G$73,assumptions!$G$72,0))+assumptions!$G$74/12)+IF(22=E5,D5*assumptions!$G$75,0),0) | AC5: =IF(AND(23>=E5,OR(F5="",23<=F5)),(D5*(1+assumptions!$G$76)^1/12*(1+assumptions!$G$70+assumptions!$G$71+IF(23>=assumptions!$G$73,assumptions!$G$72,0))+assumptions!$G$74/12)+IF(23=E5,D5*assumptions!$G$75,0),0) | AD5: =IF(AND(24>=E5,OR(F5="",24<=F5)),(D5*(1+assumptions!$G$76)^1/12*(1+assumptions!$G$70+assumptions!$G$71+IF(24>=assumptions!$G$73,assumptions!$G$72,0))+assumptions!$G$74/12)+IF(24=E5,D5*assumptions!$G$75,0),0) | AE5: =IF(AND(25>=E5,OR(F5="",25<=F5)),(D5*(1+assumptions!$G$76)^2/12*(1+assumptions!$G$70+assumptions!$G$71+IF(25>=assumptions!$G$73,assumptions!$G$72,0))+assumptions!$G$74/12)+IF(25=E5,D5*assumptions!$G$75,0),0) | AF5: =IF(AND(26>=E5,OR(F5="",26<=F5)),(D5*(1+assumptions!$G$76)^2/12*(1+assumptions!$G$70+assumptions!$G$71+IF(26>=assumptions!$G$73,assumptions!$G$72,0))+assumptions!$G$74/12)+IF(26=E5,D5*assumptions!$G$75,0),0) | AG5: =IF(AND(27>=E5,OR(F5="",27<=F5)),(D5*(1+assumptions!$G$76)^2/12*(1+assumptions!$G$70+assumptions!$G$71+IF(27>=assumptions!$G$73,assumptions!$G$72,0))+assumptions!$G$74/12)+IF(27=E5,D5*assumptions!$G$75,0),0) | AH5: =IF(AND(28>=E5,OR(F5="",28<=F5)),(D5*(1+assumptions!$G$76)^2/12*(1+assumptions!$G$70+assumptions!$G$71+IF(28>=assumptions!$G$73,assumptions!$G$72,0))+assumptions!$G$74/12)+IF(28=E5,D5*assumptions!$G$75,0),0) | AI5: =IF(AND(29>=E5,OR(F5="",29<=F5)),(D5*(1+assumptions!$G$76)^2/12*(1+assumptions!$G$70+assumptions!$G$71+IF(29>=assumptions!$G$73,assumptions!$G$72,0))+assumptions!$G$74/12)+IF(29=E5,D5*assumptions!$G$75,0),0) | AJ5: =IF(AND(30>=E5,OR(F5="",30<=F5)),(D5*(1+assumptions!$G$76)^2/12*(1+assumptions!$G$70+assumptions!$G$71+IF(30>=assumptions!$G$73,assumptions!$G$72,0))+assumptions!$G$74/12)+IF(30=E5,D5*assumptions!$G$75,0),0) | AK5: =IF(AND(31>=E5,OR(F5="",31<=F5)),(D5*(1+assumptions!$G$76)^2/12*(1+assumptions!$G$70+assumptions!$G$71+IF(31>=assumptions!$G$73,assumptions!$G$72,0))+assumptions!$G$74/12)+IF(31=E5,D5*assumptions!$G$75,0),0) | AL5: =IF(AND(32>=E5,OR(F5="",32<=F5)),(D5*(1+assumptions!$G$76)^2/12*(1+assumptions!$G$70+assumptions!$G$71+IF(32>=assumptions!$G$73,assumptions!$G$72,0))+assumptions!$G$74/12)+IF(32=E5,D5*assumptions!$G$75,0),0) | AM5: =IF(AND(33>=E5,OR(F5="",33<=F5)),(D5*(1+assumptions!$G$76)^2/12*(1+assumptions!$G$70+assumptions!$G$71+IF(33>=assumptions!$G$73,assumptions!$G$72,0))+assumptions!$G$74/12)+IF(33=E5,D5*assumptions!$G$75,0),0) | AN5: =IF(AND(34>=E5,OR(F5="",34<=F5)),(D5*(1+assumptions!$G$76)^2/12*(1+assumptions!$G$70+assumptions!$G$71+IF(34>=assumptions!$G$73,assumptions!$G$72,0))+assumptions!$G$74/12)+IF(34=E5,D5*assumptions!$G$75,0),0) | AO5: =IF(AND(35>=E5,OR(F5="",35<=F5)),(D5*(1+assumptions!$G$76)^2/12*(1+assumptions!$G$70+assumptions!$G$71+IF(35>=assumptions!$G$73,assumptions!$G$72,0))+assumptions!$G$74/12)+IF(35=E5,D5*assumptions!$G$75,0),0) | AP5: =IF(AND(36>=E5,OR(F5="",36<=F5)),(D5*(1+assumptions!$G$76)^2/12*(1+assumptions!$G$70+assumptions!$G$71+IF(36>=assumptions!$G$73,assumptions!$G$72,0))+assumptions!$G$74/12)+IF(36=E5,D5*assumptions!$G$75,0),0) | AQ5: =IF(AND(37>=E5,OR(F5="",37<=F5)),(D5*(1+assumptions!$G$76)^3/12*(1+assumptions!$G$70+assumptions!$G$71+IF(37>=assumptions!$G$73,assumptions!$G$72,0))+assumptions!$G$74/12)+IF(37=E5,D5*assumptions!$G$75,0),0) | AR5: =IF(AND(38>=E5,OR(F5="",38<=F5)),(D5*(1+assumptions!$G$76)^3/12*(1+assumptions!$G$70+assumptions!$G$71+IF(38>=assumptions!$G$73,assumptions!$G$72,0))+assumptions!$G$74/12)+IF(38=E5,D5*assumptions!$G$75,0),0) | AS5: =IF(AND(39>=E5,OR(F5="",39<=F5)),(D5*(1+assumptions!$G$76)^3/12*(1+assumptions!$G$70+assumptions!$G$71+IF(39>=assumptions!$G$73,assumptions!$G$72,0))+assumptions!$G$74/12)+IF(39=E5,D5*assumptions!$G$75,0),0) | AT5: =IF(AND(40>=E5,OR(F5="",40<=F5)),(D5*(1+assumptions!$G$76)^3/12*(1+assumptions!$G$70+assumptions!$G$71+IF(40>=assumptions!$G$73,assumptions!$G$72,0))+assumptions!$G$74/12)+IF(40=E5,D5*assumptions!$G$75,0),0) | AU5: =IF(AND(41>=E5,OR(F5="",41<=F5)),(D5*(1+assumptions!$G$76)^3/12*(1+assumptions!$G$70+assumptions!$G$71+IF(41>=assumptions!$G$73,assumptions!$G$72,0))+assumptions!$G$74/12)+IF(41=E5,D5*assumptions!$G$75,0),0) | AV5: =IF(AND(42>=E5,OR(F5="",42<=F5)),(D5*(1+assumptions!$G$76)^3/12*(1+assumptions!$G$70+assumptions!$G$71+IF(42>=assumptions!$G$73,assumptions!$G$72,0))+assumptions!$G$74/12)+IF(42=E5,D5*assumptions!$G$75,0),0) | AW5: =IF(AND(43>=E5,OR(F5="",43<=F5)),(D5*(1+assumptions!$G$76)^3/12*(1+assumptions!$G$70+assumptions!$G$71+IF(43>=assumptions!$G$73,assumptions!$G$72,0))+assumptions!$G$74/12)+IF(43=E5,D5*assumptions!$G$75,0),0) | AX5: =IF(AND(44>=E5,OR(F5="",44<=F5)),(D5*(1+assumptions!$G$76)^3/12*(1+assumptions!$G$70+assumptions!$G$71+IF(44>=assumptions!$G$73,assumptions!$G$72,0))+assumptions!$G$74/12)+IF(44=E5,D5*assumptions!$G$75,0),0) | AY5: =IF(AND(45>=E5,OR(F5="",45<=F5)),(D5*(1+assumptions!$G$76)^3/12*(1+assumptions!$G$70+assumptions!$G$71+IF(45>=assumptions!$G$73,assumptions!$G$72,0))+assumptions!$G$74/12)+IF(45=E5,D5*assumptions!$G$75,0),0) | AZ5: =IF(AND(46>=E5,OR(F5="",46<=F5)),(D5*(1+assumptions!$G$76)^3/12*(1+assumptions!$G$70+assumptions!$G$71+IF(46>=assumptions!$G$73,assumptions!$G$72,0))+assumptions!$G$74/12)+IF(46=E5,D5*assumptions!$G$75,0),0) | BA5: =IF(AND(47>=E5,OR(F5="",47<=F5)),(D5*(1+assumptions!$G$76)^3/12*(1+assumptions!$G$70+assumptions!$G$71+IF(47>=assumptions!$G$73,assumptions!$G$72,0))+assumptions!$G$74/12)+IF(47=E5,D5*assumptions!$G$75,0),0) | BB5: =IF(AND(48>=E5,OR(F5="",48<=F5)),(D5*(1+assumptions!$G$76)^3/12*(1+assumptions!$G$70+assumptions!$G$71+IF(48>=assumptions!$G$73,assumptions!$G$72,0))+assumptions!$G$74/12)+IF(48=E5,D5*assumptions!$G$75,0),0) | BC5: =IF(AND(49>=E5,OR(F5="",49<=F5)),(D5*(1+assumptions!$G$76)^4/12*(1+assumptions!$G$70+assumptions!$G$71+IF(49>=assumptions!$G$73,assumptions!$G$72,0))+assumptions!$G$74/12)+IF(49=E5,D5*assumptions!$G$75,0),0) | BD5: =IF(AND(50>=E5,OR(F5="",50<=F5)),(D5*(1+assumptions!$G$76)^4/12*(1+assumptions!$G$70+assumptions!$G$71+IF(50>=assumptions!$G$73,assumptions!$G$72,0))+assumptions!$G$74/12)+IF(50=E5,D5*assumptions!$G$75,0),0) | BE5: =IF(AND(51>=E5,OR(F5="",51<=F5)),(D5*(1+assumptions!$G$76)^4/12*(1+assumptions!$G$70+assumptions!$G$71+IF(51>=assumptions!$G$73,assumptions!$G$72,0))+assumptions!$G$74/12)+IF(51=E5,D5*assumptions!$G$75,0),0) | BF5: =IF(AND(52>=E5,OR(F5="",52<=F5)),(D5*(1+assumptions!$G$76)^4/12*(1+assumptions!$G$70+assumptions!$G$71+IF(52>=assumptions!$G$73,assumptions!$G$72,0))+assumptions!$G$74/12)+IF(52=E5,D5*assumptions!$G$75,0),0) | BG5: =IF(AND(53>=E5,OR(F5="",53<=F5)),(D5*(1+assumptions!$G$76)^4/12*(1+assumptions!$G$70+assumptions!$G$71+IF(53>=assumptions!$G$73,assumptions!$G$72,0))+assumptions!$G$74/12)+IF(53=E5,D5*assumptions!$G$75,0),0) | BH5: =IF(AND(54>=E5,OR(F5="",54<=F5)),(D5*(1+assumptions!$G$76)^4/12*(1+assumptions!$G$70+assumptions!$G$71+IF(54>=assumptions!$G$73,assumptions!$G$72,0))+assumptions!$G$74/12)+IF(54=E5,D5*assumptions!$G$75,0),0) | BI5: =IF(AND(55>=E5,OR(F5="",55<=F5)),(D5*(1+assumptions!$G$76)^4/12*(1+assumptions!$G$70+assumptions!$G$71+IF(55>=assumptions!$G$73,assumptions!$G$72,0))+assumptions!$G$74/12)+IF(55=E5,D5*assumptions!$G$75,0),0) | BJ5: =IF(AND(56>=E5,OR(F5="",56<=F5)),(D5*(1+assumptions!$G$76)^4/12*(1+assumptions!$G$70+assumptions!$G$71+IF(56>=assumptions!$G$73,assumptions!$G$72,0))+assumptions!$G$74/12)+IF(56=E5,D5*assumptions!$G$75,0),0) | BK5: =IF(AND(57>=E5,OR(F5="",57<=F5)),(D5*(1+assumptions!$G$76)^4/12*(1+assumptions!$G$70+assumptions!$G$71+IF(57>=assumptions!$G$73,assumptions!$G$72,0))+assumptions!$G$74/12)+IF(57=E5,D5*assumptions!$G$75,0),0) | BL5: =IF(AND(58>=E5,OR(F5="",58<=F5)),(D5*(1+assumptions!$G$76)^4/12*(1+assumptions!$G$70+assumptions!$G$71+IF(58>=assumptions!$G$73,assumptions!$G$72,0))+assumptions!$G$74/12)+IF(58=E5,D5*assumptions!$G$75,0),0) | BM5: =IF(AND(59>=E5,OR(F5="",59<=F5)),(D5*(1+assumptions!$G$76)^4/12*(1+assumptions!$G$70+assumptions!$G$71+IF(59>=assumptions!$G$73,assumptions!$G$72,0))+assumptions!$G$74/12)+IF(59=E5,D5*assumptions!$G$75,0),0) | BN5: =IF(AND(60>=E5,OR(F5="",60<=F5)),(D5*(1+assumptions!$G$76)^4/12*(1+assumptions!$G$70+assumptions!$G$71+IF(60>=assumptions!$G$73,assumptions!$G$72,0))+assumptions!$G$74/12)+IF(60=E5,D5*assumptions!$G$75,0),0)
A6: 3 | B6: Engineer | C6: eng | D6: 80000 | E6: 1 | G6: =IF(AND(1>=E6,OR(F6="",1<=F6)),(D6*(1+assumptions!$G$76)^0/12*(1+assumptions!$G$70+assumptions!$G$71+IF(1>=assumptions!$G$73,assumptions!$G$72,0))+assumptions!$G$74/12)+IF(1=E6,D6*assumptions!$G$75,0),0) | H6: =IF(AND(2>=E6,OR(F6="",2<=F6)),(D6*(1+assumptions!$G$76)^0/12*(1+assumptions!$G$70+assumptions!$G$71+IF(2>=assumptions!$G$73,assumptions!$G$72,0))+assumptions!$G$74/12)+IF(2=E6,D6*assumptions!$G$75,0),0) | I6: =IF(AND(3>=E6,OR(F6="",3<=F6)),(D6*(1+assumptions!$G$76)^0/12*(1+assumptions!$G$70+assumptions!$G$71+IF(3>=assumptions!$G$73,assumptions!$G$72,0))+assumptions!$G$74/12)+IF(3=E6,D6*assumptions!$G$75,0),0) | J6: =IF(AND(4>=E6,OR(F6="",4<=F6)),(D6*(1+assumptions!$G$76)^0/12*(1+assumptions!$G$70+assumptions!$G$71+IF(4>=assumptions!$G$73,assumptions!$G$72,0))+assumptions!$G$74/12)+IF(4=E6,D6*assumptions!$G$75,0),0) | K6: =IF(AND(5>=E6,OR(F6="",5<=F6)),(D6*(1+assumptions!$G$76)^0/12*(1+assumptions!$G$70+assumptions!$G$71+IF(5>=assumptions!$G$73,assumptions!$G$72,0))+assumptions!$G$74/12)+IF(5=E6,D6*assumptions!$G$75,0),0) | L6: =IF(AND(6>=E6,OR(F6="",6<=F6)),(D6*(1+assumptions!$G$76)^0/12*(1+assumptions!$G$70+assumptions!$G$71+IF(6>=assumptions!$G$73,assumptions!$G$72,0))+assumptions!$G$74/12)+IF(6=E6,D6*assumptions!$G$75,0),0) | M6: =IF(AND(7>=E6,OR(F6="",7<=F6)),(D6*(1+assumptions!$G$76)^0/12*(1+assumptions!$G$70+assumptions!$G$71+IF(7>=assumptions!$G$73,assumptions!$G$72,0))+assumptions!$G$74/12)+IF(7=E6,D6*assumptions!$G$75,0),0) | N6: =IF(AND(8>=E6,OR(F6="",8<=F6)),(D6*(1+assumptions!$G$76)^0/12*(1+assumptions!$G$70+assumptions!$G$71+IF(8>=assumptions!$G$73,assumptions!$G$72,0))+assumptions!$G$74/12)+IF(8=E6,D6*assumptions!$G$75,0),0) | O6: =IF(AND(9>=E6,OR(F6="",9<=F6)),(D6*(1+assumptions!$G$76)^0/12*(1+assumptions!$G$70+assumptions!$G$71+IF(9>=assumptions!$G$73,assumptions!$G$72,0))+assumptions!$G$74/12)+IF(9=E6,D6*assumptions!$G$75,0),0) | P6: =IF(AND(10>=E6,OR(F6="",10<=F6)),(D6*(1+assumptions!$G$76)^0/12*(1+assumptions!$G$70+assumptions!$G$71+IF(10>=assumptions!$G$73,assumptions!$G$72,0))+assumptions!$G$74/12)+IF(10=E6,D6*assumptions!$G$75,0),0) | Q6: =IF(AND(11>=E6,OR(F6="",11<=F6)),(D6*(1+assumptions!$G$76)^0/12*(1+assumptions!$G$70+assumptions!$G$71+IF(11>=assumptions!$G$73,assumptions!$G$72,0))+assumptions!$G$74/12)+IF(11=E6,D6*assumptions!$G$75,0),0) | R6: =IF(AND(12>=E6,OR(F6="",12<=F6)),(D6*(1+assumptions!$G$76)^0/12*(1+assumptions!$G$70+assumptions!$G$71+IF(12>=assumptions!$G$73,assumptions!$G$72,0))+assumptions!$G$74/12)+IF(12=E6,D6*assumptions!$G$75,0),0) | S6: =IF(AND(13>=E6,OR(F6="",13<=F6)),(D6*(1+assumptions!$G$76)^1/12*(1+assumptions!$G$70+assumptions!$G$71+IF(13>=assumptions!$G$73,assumptions!$G$72,0))+assumptions!$G$74/12)+IF(13=E6,D6*assumptions!$G$75,0),0) | T6: =IF(AND(14>=E6,OR(F6="",14<=F6)),(D6*(1+assumptions!$G$76)^1/12*(1+assumptions!$G$70+assumptions!$G$71+IF(14>=assumptions!$G$73,assumptions!$G$72,0))+assumptions!$G$74/12)+IF(14=E6,D6*assumptions!$G$75,0),0) | U6: =IF(AND(15>=E6,OR(F6="",15<=F6)),(D6*(1+assumptions!$G$76)^1/12*(1+assumptions!$G$70+assumptions!$G$71+IF(15>=assumptions!$G$73,assumptions!$G$72,0))+assumptions!$G$74/12)+IF(15=E6,D6*assumptions!$G$75,0),0) | V6: =IF(AND(16>=E6,OR(F6="",16<=F6)),(D6*(1+assumptions!$G$76)^1/12*(1+assumptions!$G$70+assumptions!$G$71+IF(16>=assumptions!$G$73,assumptions!$G$72,0))+assumptions!$G$74/12)+IF(16=E6,D6*assumptions!$G$75,0),0) | W6: =IF(AND(17>=E6,OR(F6="",17<=F6)),(D6*(1+assumptions!$G$76)^1/12*(1+assumptions!$G$70+assumptions!$G$71+IF(17>=assumptions!$G$73,assumptions!$G$72,0))+assumptions!$G$74/12)+IF(17=E6,D6*assumptions!$G$75,0),0) | X6: =IF(AND(18>=E6,OR(F6="",18<=F6)),(D6*(1+assumptions!$G$76)^1/12*(1+assumptions!$G$70+assumptions!$G$71+IF(18>=assumptions!$G$73,assumptions!$G$72,0))+assumptions!$G$74/12)+IF(18=E6,D6*assumptions!$G$75,0),0) | Y6: =IF(AND(19>=E6,OR(F6="",19<=F6)),(D6*(1+assumptions!$G$76)^1/12*(1+assumptions!$G$70+assumptions!$G$71+IF(19>=assumptions!$G$73,assumptions!$G$72,0))+assumptions!$G$74/12)+IF(19=E6,D6*assumptions!$G$75,0),0) | Z6: =IF(AND(20>=E6,OR(F6="",20<=F6)),(D6*(1+assumptions!$G$76)^1/12*(1+assumptions!$G$70+assumptions!$G$71+IF(20>=assumptions!$G$73,assumptions!$G$72,0))+assumptions!$G$74/12)+IF(20=E6,D6*assumptions!$G$75,0),0) | AA6: =IF(AND(21>=E6,OR(F6="",21<=F6)),(D6*(1+assumptions!$G$76)^1/12*(1+assumptions!$G$70+assumptions!$G$71+IF(21>=assumptions!$G$73,assumptions!$G$72,0))+assumptions!$G$74/12)+IF(21=E6,D6*assumptions!$G$75,0),0) | AB6: =IF(AND(22>=E6,OR(F6="",22<=F6)),(D6*(1+assumptions!$G$76)^1/12*(1+assumptions!$G$70+assumptions!$G$71+IF(22>=assumptions!$G$73,assumptions!$G$72,0))+assumptions!$G$74/12)+IF(22=E6,D6*assumptions!$G$75,0),0) | AC6: =IF(AND(23>=E6,OR(F6="",23<=F6)),(D6*(1+assumptions!$G$76)^1/12*(1+assumptions!$G$70+assumptions!$G$71+IF(23>=assumptions!$G$73,assumptions!$G$72,0))+assumptions!$G$74/12)+IF(23=E6,D6*assumptions!$G$75,0),0) | AD6: =IF(AND(24>=E6,OR(F6="",24<=F6)),(D6*(1+assumptions!$G$76)^1/12*(1+assumptions!$G$70+assumptions!$G$71+IF(24>=assumptions!$G$73,assumptions!$G$72,0))+assumptions!$G$74/12)+IF(24=E6,D6*assumptions!$G$75,0),0) | AE6: =IF(AND(25>=E6,OR(F6="",25<=F6)),(D6*(1+assumptions!$G$76)^2/12*(1+assumptions!$G$70+assumptions!$G$71+IF(25>=assumptions!$G$73,assumptions!$G$72,0))+assumptions!$G$74/12)+IF(25=E6,D6*assumptions!$G$75,0),0) | AF6: =IF(AND(26>=E6,OR(F6="",26<=F6)),(D6*(1+assumptions!$G$76)^2/12*(1+assumptions!$G$70+assumptions!$G$71+IF(26>=assumptions!$G$73,assumptions!$G$72,0))+assumptions!$G$74/12)+IF(26=E6,D6*assumptions!$G$75,0),0) | AG6: =IF(AND(27>=E6,OR(F6="",27<=F6)),(D6*(1+assumptions!$G$76)^2/12*(1+assumptions!$G$70+assumptions!$G$71+IF(27>=assumptions!$G$73,assumptions!$G$72,0))+assumptions!$G$74/12)+IF(27=E6,D6*assumptions!$G$75,0),0) | AH6: =IF(AND(28>=E6,OR(F6="",28<=F6)),(D6*(1+assumptions!$G$76)^2/12*(1+assumptions!$G$70+assumptions!$G$71+IF(28>=assumptions!$G$73,assumptions!$G$72,0))+assumptions!$G$74/12)+IF(28=E6,D6*assumptions!$G$75,0),0) | AI6: =IF(AND(29>=E6,OR(F6="",29<=F6)),(D6*(1+assumptions!$G$76)^2/12*(1+assumptions!$G$70+assumptions!$G$71+IF(29>=assumptions!$G$73,assumptions!$G$72,0))+assumptions!$G$74/12)+IF(29=E6,D6*assumptions!$G$75,0),0) | AJ6: =IF(AND(30>=E6,OR(F6="",30<=F6)),(D6*(1+assumptions!$G$76)^2/12*(1+assumptions!$G$70+assumptions!$G$71+IF(30>=assumptions!$G$73,assumptions!$G$72,0))+assumptions!$G$74/12)+IF(30=E6,D6*assumptions!$G$75,0),0) | AK6: =IF(AND(31>=E6,OR(F6="",31<=F6)),(D6*(1+assumptions!$G$76)^2/12*(1+assumptions!$G$70+assumptions!$G$71+IF(31>=assumptions!$G$73,assumptions!$G$72,0))+assumptions!$G$74/12)+IF(31=E6,D6*assumptions!$G$75,0),0) | AL6: =IF(AND(32>=E6,OR(F6="",32<=F6)),(D6*(1+assumptions!$G$76)^2/12*(1+assumptions!$G$70+assumptions!$G$71+IF(32>=assumptions!$G$73,assumptions!$G$72,0))+assumptions!$G$74/12)+IF(32=E6,D6*assumptions!$G$75,0),0) | AM6: =IF(AND(33>=E6,OR(F6="",33<=F6)),(D6*(1+assumptions!$G$76)^2/12*(1+assumptions!$G$70+assumptions!$G$71+IF(33>=assumptions!$G$73,assumptions!$G$72,0))+assumptions!$G$74/12)+IF(33=E6,D6*assumptions!$G$75,0),0) | AN6: =IF(AND(34>=E6,OR(F6="",34<=F6)),(D6*(1+assumptions!$G$76)^2/12*(1+assumptions!$G$70+assumptions!$G$71+IF(34>=assumptions!$G$73,assumptions!$G$72,0))+assumptions!$G$74/12)+IF(34=E6,D6*assumptions!$G$75,0),0) | AO6: =IF(AND(35>=E6,OR(F6="",35<=F6)),(D6*(1+assumptions!$G$76)^2/12*(1+assumptions!$G$70+assumptions!$G$71+IF(35>=assumptions!$G$73,assumptions!$G$72,0))+assumptions!$G$74/12)+IF(35=E6,D6*assumptions!$G$75,0),0) | AP6: =IF(AND(36>=E6,OR(F6="",36<=F6)),(D6*(1+assumptions!$G$76)^2/12*(1+assumptions!$G$70+assumptions!$G$71+IF(36>=assumptions!$G$73,assumptions!$G$72,0))+assumptions!$G$74/12)+IF(36=E6,D6*assumptions!$G$75,0),0) | AQ6: =IF(AND(37>=E6,OR(F6="",37<=F6)),(D6*(1+assumptions!$G$76)^3/12*(1+assumptions!$G$70+assumptions!$G$71+IF(37>=assumptions!$G$73,assumptions!$G$72,0))+assumptions!$G$74/12)+IF(37=E6,D6*assumptions!$G$75,0),0) | AR6: =IF(AND(38>=E6,OR(F6="",38<=F6)),(D6*(1+assumptions!$G$76)^3/12*(1+assumptions!$G$70+assumptions!$G$71+IF(38>=assumptions!$G$73,assumptions!$G$72,0))+assumptions!$G$74/12)+IF(38=E6,D6*assumptions!$G$75,0),0) | AS6: =IF(AND(39>=E6,OR(F6="",39<=F6)),(D6*(1+assumptions!$G$76)^3/12*(1+assumptions!$G$70+assumptions!$G$71+IF(39>=assumptions!$G$73,assumptions!$G$72,0))+assumptions!$G$74/12)+IF(39=E6,D6*assumptions!$G$75,0),0) | AT6: =IF(AND(40>=E6,OR(F6="",40<=F6)),(D6*(1+assumptions!$G$76)^3/12*(1+assumptions!$G$70+assumptions!$G$71+IF(40>=assumptions!$G$73,assumptions!$G$72,0))+assumptions!$G$74/12)+IF(40=E6,D6*assumptions!$G$75,0),0) | AU6: =IF(AND(41>=E6,OR(F6="",41<=F6)),(D6*(1+assumptions!$G$76)^3/12*(1+assumptions!$G$70+assumptions!$G$71+IF(41>=assumptions!$G$73,assumptions!$G$72,0))+assumptions!$G$74/12)+IF(41=E6,D6*assumptions!$G$75,0),0) | AV6: =IF(AND(42>=E6,OR(F6="",42<=F6)),(D6*(1+assumptions!$G$76)^3/12*(1+assumptions!$G$70+assumptions!$G$71+IF(42>=assumptions!$G$73,assumptions!$G$72,0))+assumptions!$G$74/12)+IF(42=E6,D6*assumptions!$G$75,0),0) | AW6: =IF(AND(43>=E6,OR(F6="",43<=F6)),(D6*(1+assumptions!$G$76)^3/12*(1+assumptions!$G$70+assumptions!$G$71+IF(43>=assumptions!$G$73,assumptions!$G$72,0))+assumptions!$G$74/12)+IF(43=E6,D6*assumptions!$G$75,0),0) | AX6: =IF(AND(44>=E6,OR(F6="",44<=F6)),(D6*(1+assumptions!$G$76)^3/12*(1+assumptions!$G$70+assumptions!$G$71+IF(44>=assumptions!$G$73,assumptions!$G$72,0))+assumptions!$G$74/12)+IF(44=E6,D6*assumptions!$G$75,0),0) | AY6: =IF(AND(45>=E6,OR(F6="",45<=F6)),(D6*(1+assumptions!$G$76)^3/12*(1+assumptions!$G$70+assumptions!$G$71+IF(45>=assumptions!$G$73,assumptions!$G$72,0))+assumptions!$G$74/12)+IF(45=E6,D6*assumptions!$G$75,0),0) | AZ6: =IF(AND(46>=E6,OR(F6="",46<=F6)),(D6*(1+assumptions!$G$76)^3/12*(1+assumptions!$G$70+assumptions!$G$71+IF(46>=assumptions!$G$73,assumptions!$G$72,0))+assumptions!$G$74/12)+IF(46=E6,D6*assumptions!$G$75,0),0) | BA6: =IF(AND(47>=E6,OR(F6="",47<=F6)),(D6*(1+assumptions!$G$76)^3/12*(1+assumptions!$G$70+assumptions!$G$71+IF(47>=assumptions!$G$73,assumptions!$G$72,0))+assumptions!$G$74/12)+IF(47=E6,D6*assumptions!$G$75,0),0) | BB6: =IF(AND(48>=E6,OR(F6="",48<=F6)),(D6*(1+assumptions!$G$76)^3/12*(1+assumptions!$G$70+assumptions!$G$71+IF(48>=assumptions!$G$73,assumptions!$G$72,0))+assumptions!$G$74/12)+IF(48=E6,D6*assumptions!$G$75,0),0) | BC6: =IF(AND(49>=E6,OR(F6="",49<=F6)),(D6*(1+assumptions!$G$76)^4/12*(1+assumptions!$G$70+assumptions!$G$71+IF(49>=assumptions!$G$73,assumptions!$G$72,0))+assumptions!$G$74/12)+IF(49=E6,D6*assumptions!$G$75,0),0) | BD6: =IF(AND(50>=E6,OR(F6="",50<=F6)),(D6*(1+assumptions!$G$76)^4/12*(1+assumptions!$G$70+assumptions!$G$71+IF(50>=assumptions!$G$73,assumptions!$G$72,0))+assumptions!$G$74/12)+IF(50=E6,D6*assumptions!$G$75,0),0) | BE6: =IF(AND(51>=E6,OR(F6="",51<=F6)),(D6*(1+assumptions!$G$76)^4/12*(1+assumptions!$G$70+assumptions!$G$71+IF(51>=assumptions!$G$73,assumptions!$G$72,0))+assumptions!$G$74/12)+IF(51=E6,D6*assumptions!$G$75,0),0) | BF6: =IF(AND(52>=E6,OR(F6="",52<=F6)),(D6*(1+assumptions!$G$76)^4/12*(1+assumptions!$G$70+assumptions!$G$71+IF(52>=assumptions!$G$73,assumptions!$G$72,0))+assumptions!$G$74/12)+IF(52=E6,D6*assumptions!$G$75,0),0) | BG6: =IF(AND(53>=E6,OR(F6="",53<=F6)),(D6*(1+assumptions!$G$76)^4/12*(1+assumptions!$G$70+assumptions!$G$71+IF(53>=assumptions!$G$73,assumptions!$G$72,0))+assumptions!$G$74/12)+IF(53=E6,D6*assumptions!$G$75,0),0) | BH6: =IF(AND(54>=E6,OR(F6="",54<=F6)),(D6*(1+assumptions!$G$76)^4/12*(1+assumptions!$G$70+assumptions!$G$71+IF(54>=assumptions!$G$73,assumptions!$G$72,0))+assumptions!$G$74/12)+IF(54=E6,D6*assumptions!$G$75,0),0) | BI6: =IF(AND(55>=E6,OR(F6="",55<=F6)),(D6*(1+assumptions!$G$76)^4/12*(1+assumptions!$G$70+assumptions!$G$71+IF(55>=assumptions!$G$73,assumptions!$G$72,0))+assumptions!$G$74/12)+IF(55=E6,D6*assumptions!$G$75,0),0) | BJ6: =IF(AND(56>=E6,OR(F6="",56<=F6)),(D6*(1+assumptions!$G$76)^4/12*(1+assumptions!$G$70+assumptions!$G$71+IF(56>=assumptions!$G$73,assumptions!$G$72,0))+assumptions!$G$74/12)+IF(56=E6,D6*assumptions!$G$75,0),0) | BK6: =IF(AND(57>=E6,OR(F6="",57<=F6)),(D6*(1+assumptions!$G$76)^4/12*(1+assumptions!$G$70+assumptions!$G$71+IF(57>=assumptions!$G$73,assumptions!$G$72,0))+assumptions!$G$74/12)+IF(57=E6,D6*assumptions!$G$75,0),0) | BL6: =IF(AND(58>=E6,OR(F6="",58<=F6)),(D6*(1+assumptions!$G$76)^4/12*(1+assumptions!$G$70+assumptions!$G$71+IF(58>=assumptions!$G$73,assumptions!$G$72,0))+assumptions!$G$74/12)+IF(58=E6,D6*assumptions!$G$75,0),0) | BM6: =IF(AND(59>=E6,OR(F6="",59<=F6)),(D6*(1+assumptions!$G$76)^4/12*(1+assumptions!$G$70+assumptions!$G$71+IF(59>=assumptions!$G$73,assumptions!$G$72,0))+assumptions!$G$74/12)+IF(59=E6,D6*assumptions!$G$75,0),0) | BN6: =IF(AND(60>=E6,OR(F6="",60<=F6)),(D6*(1+assumptions!$G$76)^4/12*(1+assumptions!$G$70+assumptions!$G$71+IF(60>=assumptions!$G$73,assumptions!$G$72,0))+assumptions!$G$74/12)+IF(60=E6,D6*assumptions!$G$75,0),0)
A7: 4 | B7: Head of Creator Growth | C7: growth | D7: 75000 | E7: 1 | G7: =IF(AND(1>=E7,OR(F7="",1<=F7)),(D7*(1+assumptions!$G$76)^0/12*(1+assumptions!$G$70+assumptions!$G$71+IF(1>=assumptions!$G$73,assumptions!$G$72,0))+assumptions!$G$74/12)+IF(1=E7,D7*assumptions!$G$75,0),0) | H7: =IF(AND(2>=E7,OR(F7="",2<=F7)),(D7*(1+assumptions!$G$76)^0/12*(1+assumptions!$G$70+assumptions!$G$71+IF(2>=assumptions!$G$73,assumptions!$G$72,0))+assumptions!$G$74/12)+IF(2=E7,D7*assumptions!$G$75,0),0) | I7: =IF(AND(3>=E7,OR(F7="",3<=F7)),(D7*(1+assumptions!$G$76)^0/12*(1+assumptions!$G$70+assumptions!$G$71+IF(3>=assumptions!$G$73,assumptions!$G$72,0))+assumptions!$G$74/12)+IF(3=E7,D7*assumptions!$G$75,0),0) | J7: =IF(AND(4>=E7,OR(F7="",4<=F7)),(D7*(1+assumptions!$G$76)^0/12*(1+assumptions!$G$70+assumptions!$G$71+IF(4>=assumptions!$G$73,assumptions!$G$72,0))+assumptions!$G$74/12)+IF(4=E7,D7*assumptions!$G$75,0),0) | K7: =IF(AND(5>=E7,OR(F7="",5<=F7)),(D7*(1+assumptions!$G$76)^0/12*(1+assumptions!$G$70+assumptions!$G$71+IF(5>=assumptions!$G$73,assumptions!$G$72,0))+assumptions!$G$74/12)+IF(5=E7,D7*assumptions!$G$75,0),0) | L7: =IF(AND(6>=E7,OR(F7="",6<=F7)),(D7*(1+assumptions!$G$76)^0/12*(1+assumptions!$G$70+assumptions!$G$71+IF(6>=assumptions!$G$73,assumptions!$G$72,0))+assumptions!$G$74/12)+IF(6=E7,D7*assumptions!$G$75,0),0) | M7: =IF(AND(7>=E7,OR(F7="",7<=F7)),(D7*(1+assumptions!$G$76)^0/12*(1+assumptions!$G$70+assumptions!$G$71+IF(7>=assumptions!$G$73,assumptions!$G$72,0))+assumptions!$G$74/12)+IF(7=E7,D7*assumptions!$G$75,0),0) | N7: =IF(AND(8>=E7,OR(F7="",8<=F7)),(D7*(1+assumptions!$G$76)^0/12*(1+assumptions!$G$70+assumptions!$G$71+IF(8>=assumptions!$G$73,assumptions!$G$72,0))+assumptions!$G$74/12)+IF(8=E7,D7*assumptions!$G$75,0),0) | O7: =IF(AND(9>=E7,OR(F7="",9<=F7)),(D7*(1+assumptions!$G$76)^0/12*(1+assumptions!$G$70+assumptions!$G$71+IF(9>=assumptions!$G$73,assumptions!$G$72,0))+assumptions!$G$74/12)+IF(9=E7,D7*assumptions!$G$75,0),0) | P7: =IF(AND(10>=E7,OR(F7="",10<=F7)),(D7*(1+assumptions!$G$76)^0/12*(1+assumptions!$G$70+assumptions!$G$71+IF(10>=assumptions!$G$73,assumptions!$G$72,0))+assumptions!$G$74/12)+IF(10=E7,D7*assumptions!$G$75,0),0) | Q7: =IF(AND(11>=E7,OR(F7="",11<=F7)),(D7*(1+assumptions!$G$76)^0/12*(1+assumptions!$G$70+assumptions!$G$71+IF(11>=assumptions!$G$73,assumptions!$G$72,0))+assumptions!$G$74/12)+IF(11=E7,D7*assumptions!$G$75,0),0) | R7: =IF(AND(12>=E7,OR(F7="",12<=F7)),(D7*(1+assumptions!$G$76)^0/12*(1+assumptions!$G$70+assumptions!$G$71+IF(12>=assumptions!$G$73,assumptions!$G$72,0))+assumptions!$G$74/12)+IF(12=E7,D7*assumptions!$G$75,0),0) | S7: =IF(AND(13>=E7,OR(F7="",13<=F7)),(D7*(1+assumptions!$G$76)^1/12*(1+assumptions!$G$70+assumptions!$G$71+IF(13>=assumptions!$G$73,assumptions!$G$72,0))+assumptions!$G$74/12)+IF(13=E7,D7*assumptions!$G$75,0),0) | T7: =IF(AND(14>=E7,OR(F7="",14<=F7)),(D7*(1+assumptions!$G$76)^1/12*(1+assumptions!$G$70+assumptions!$G$71+IF(14>=assumptions!$G$73,assumptions!$G$72,0))+assumptions!$G$74/12)+IF(14=E7,D7*assumptions!$G$75,0),0) | U7: =IF(AND(15>=E7,OR(F7="",15<=F7)),(D7*(1+assumptions!$G$76)^1/12*(1+assumptions!$G$70+assumptions!$G$71+IF(15>=assumptions!$G$73,assumptions!$G$72,0))+assumptions!$G$74/12)+IF(15=E7,D7*assumptions!$G$75,0),0) | V7: =IF(AND(16>=E7,OR(F7="",16<=F7)),(D7*(1+assumptions!$G$76)^1/12*(1+assumptions!$G$70+assumptions!$G$71+IF(16>=assumptions!$G$73,assumptions!$G$72,0))+assumptions!$G$74/12)+IF(16=E7,D7*assumptions!$G$75,0),0) | W7: =IF(AND(17>=E7,OR(F7="",17<=F7)),(D7*(1+assumptions!$G$76)^1/12*(1+assumptions!$G$70+assumptions!$G$71+IF(17>=assumptions!$G$73,assumptions!$G$72,0))+assumptions!$G$74/12)+IF(17=E7,D7*assumptions!$G$75,0),0) | X7: =IF(AND(18>=E7,OR(F7="",18<=F7)),(D7*(1+assumptions!$G$76)^1/12*(1+assumptions!$G$70+assumptions!$G$71+IF(18>=assumptions!$G$73,assumptions!$G$72,0))+assumptions!$G$74/12)+IF(18=E7,D7*assumptions!$G$75,0),0) | Y7: =IF(AND(19>=E7,OR(F7="",19<=F7)),(D7*(1+assumptions!$G$76)^1/12*(1+assumptions!$G$70+assumptions!$G$71+IF(19>=assumptions!$G$73,assumptions!$G$72,0))+assumptions!$G$74/12)+IF(19=E7,D7*assumptions!$G$75,0),0) | Z7: =IF(AND(20>=E7,OR(F7="",20<=F7)),(D7*(1+assumptions!$G$76)^1/12*(1+assumptions!$G$70+assumptions!$G$71+IF(20>=assumptions!$G$73,assumptions!$G$72,0))+assumptions!$G$74/12)+IF(20=E7,D7*assumptions!$G$75,0),0) | AA7: =IF(AND(21>=E7,OR(F7="",21<=F7)),(D7*(1+assumptions!$G$76)^1/12*(1+assumptions!$G$70+assumptions!$G$71+IF(21>=assumptions!$G$73,assumptions!$G$72,0))+assumptions!$G$74/12)+IF(21=E7,D7*assumptions!$G$75,0),0) | AB7: =IF(AND(22>=E7,OR(F7="",22<=F7)),(D7*(1+assumptions!$G$76)^1/12*(1+assumptions!$G$70+assumptions!$G$71+IF(22>=assumptions!$G$73,assumptions!$G$72,0))+assumptions!$G$74/12)+IF(22=E7,D7*assumptions!$G$75,0),0) | AC7: =IF(AND(23>=E7,OR(F7="",23<=F7)),(D7*(1+assumptions!$G$76)^1/12*(1+assumptions!$G$70+assumptions!$G$71+IF(23>=assumptions!$G$73,assumptions!$G$72,0))+assumptions!$G$74/12)+IF(23=E7,D7*assumptions!$G$75,0),0) | AD7: =IF(AND(24>=E7,OR(F7="",24<=F7)),(D7*(1+assumptions!$G$76)^1/12*(1+assumptions!$G$70+assumptions!$G$71+IF(24>=assumptions!$G$73,assumptions!$G$72,0))+assumptions!$G$74/12)+IF(24=E7,D7*assumptions!$G$75,0),0) | AE7: =IF(AND(25>=E7,OR(F7="",25<=F7)),(D7*(1+assumptions!$G$76)^2/12*(1+assumptions!$G$70+assumptions!$G$71+IF(25>=assumptions!$G$73,assumptions!$G$72,0))+assumptions!$G$74/12)+IF(25=E7,D7*assumptions!$G$75,0),0) | AF7: =IF(AND(26>=E7,OR(F7="",26<=F7)),(D7*(1+assumptions!$G$76)^2/12*(1+assumptions!$G$70+assumptions!$G$71+IF(26>=assumptions!$G$73,assumptions!$G$72,0))+assumptions!$G$74/12)+IF(26=E7,D7*assumptions!$G$75,0),0) | AG7: =IF(AND(27>=E7,OR(F7="",27<=F7)),(D7*(1+assumptions!$G$76)^2/12*(1+assumptions!$G$70+assumptions!$G$71+IF(27>=assumptions!$G$73,assumptions!$G$72,0))+assumptions!$G$74/12)+IF(27=E7,D7*assumptions!$G$75,0),0) | AH7: =IF(AND(28>=E7,OR(F7="",28<=F7)),(D7*(1+assumptions!$G$76)^2/12*(1+assumptions!$G$70+assumptions!$G$71+IF(28>=assumptions!$G$73,assumptions!$G$72,0))+assumptions!$G$74/12)+IF(28=E7,D7*assumptions!$G$75,0),0) | AI7: =IF(AND(29>=E7,OR(F7="",29<=F7)),(D7*(1+assumptions!$G$76)^2/12*(1+assumptions!$G$70+assumptions!$G$71+IF(29>=assumptions!$G$73,assumptions!$G$72,0))+assumptions!$G$74/12)+IF(29=E7,D7*assumptions!$G$75,0),0) | AJ7: =IF(AND(30>=E7,OR(F7="",30<=F7)),(D7*(1+assumptions!$G$76)^2/12*(1+assumptions!$G$70+assumptions!$G$71+IF(30>=assumptions!$G$73,assumptions!$G$72,0))+assumptions!$G$74/12)+IF(30=E7,D7*assumptions!$G$75,0),0) | AK7: =IF(AND(31>=E7,OR(F7="",31<=F7)),(D7*(1+assumptions!$G$76)^2/12*(1+assumptions!$G$70+assumptions!$G$71+IF(31>=assumptions!$G$73,assumptions!$G$72,0))+assumptions!$G$74/12)+IF(31=E7,D7*assumptions!$G$75,0),0) | AL7: =IF(AND(32>=E7,OR(F7="",32<=F7)),(D7*(1+assumptions!$G$76)^2/12*(1+assumptions!$G$70+assumptions!$G$71+IF(32>=assumptions!$G$73,assumptions!$G$72,0))+assumptions!$G$74/12)+IF(32=E7,D7*assumptions!$G$75,0),0) | AM7: =IF(AND(33>=E7,OR(F7="",33<=F7)),(D7*(1+assumptions!$G$76)^2/12*(1+assumptions!$G$70+assumptions!$G$71+IF(33>=assumptions!$G$73,assumptions!$G$72,0))+assumptions!$G$74/12)+IF(33=E7,D7*assumptions!$G$75,0),0) | AN7: =IF(AND(34>=E7,OR(F7="",34<=F7)),(D7*(1+assumptions!$G$76)^2/12*(1+assumptions!$G$70+assumptions!$G$71+IF(34>=assumptions!$G$73,assumptions!$G$72,0))+assumptions!$G$74/12)+IF(34=E7,D7*assumptions!$G$75,0),0) | AO7: =IF(AND(35>=E7,OR(F7="",35<=F7)),(D7*(1+assumptions!$G$76)^2/12*(1+assumptions!$G$70+assumptions!$G$71+IF(35>=assumptions!$G$73,assumptions!$G$72,0))+assumptions!$G$74/12)+IF(35=E7,D7*assumptions!$G$75,0),0) | AP7: =IF(AND(36>=E7,OR(F7="",36<=F7)),(D7*(1+assumptions!$G$76)^2/12*(1+assumptions!$G$70+assumptions!$G$71+IF(36>=assumptions!$G$73,assumptions!$G$72,0))+assumptions!$G$74/12)+IF(36=E7,D7*assumptions!$G$75,0),0) | AQ7: =IF(AND(37>=E7,OR(F7="",37<=F7)),(D7*(1+assumptions!$G$76)^3/12*(1+assumptions!$G$70+assumptions!$G$71+IF(37>=assumptions!$G$73,assumptions!$G$72,0))+assumptions!$G$74/12)+IF(37=E7,D7*assumptions!$G$75,0),0) | AR7: =IF(AND(38>=E7,OR(F7="",38<=F7)),(D7*(1+assumptions!$G$76)^3/12*(1+assumptions!$G$70+assumptions!$G$71+IF(38>=assumptions!$G$73,assumptions!$G$72,0))+assumptions!$G$74/12)+IF(38=E7,D7*assumptions!$G$75,0),0) | AS7: =IF(AND(39>=E7,OR(F7="",39<=F7)),(D7*(1+assumptions!$G$76)^3/12*(1+assumptions!$G$70+assumptions!$G$71+IF(39>=assumptions!$G$73,assumptions!$G$72,0))+assumptions!$G$74/12)+IF(39=E7,D7*assumptions!$G$75,0),0) | AT7: =IF(AND(40>=E7,OR(F7="",40<=F7)),(D7*(1+assumptions!$G$76)^3/12*(1+assumptions!$G$70+assumptions!$G$71+IF(40>=assumptions!$G$73,assumptions!$G$72,0))+assumptions!$G$74/12)+IF(40=E7,D7*assumptions!$G$75,0),0) | AU7: =IF(AND(41>=E7,OR(F7="",41<=F7)),(D7*(1+assumptions!$G$76)^3/12*(1+assumptions!$G$70+assumptions!$G$71+IF(41>=assumptions!$G$73,assumptions!$G$72,0))+assumptions!$G$74/12)+IF(41=E7,D7*assumptions!$G$75,0),0) | AV7: =IF(AND(42>=E7,OR(F7="",42<=F7)),(D7*(1+assumptions!$G$76)^3/12*(1+assumptions!$G$70+assumptions!$G$71+IF(42>=assumptions!$G$73,assumptions!$G$72,0))+assumptions!$G$74/12)+IF(42=E7,D7*assumptions!$G$75,0),0) | AW7: =IF(AND(43>=E7,OR(F7="",43<=F7)),(D7*(1+assumptions!$G$76)^3/12*(1+assumptions!$G$70+assumptions!$G$71+IF(43>=assumptions!$G$73,assumptions!$G$72,0))+assumptions!$G$74/12)+IF(43=E7,D7*assumptions!$G$75,0),0) | AX7: =IF(AND(44>=E7,OR(F7="",44<=F7)),(D7*(1+assumptions!$G$76)^3/12*(1+assumptions!$G$70+assumptions!$G$71+IF(44>=assumptions!$G$73,assumptions!$G$72,0))+assumptions!$G$74/12)+IF(44=E7,D7*assumptions!$G$75,0),0) | AY7: =IF(AND(45>=E7,OR(F7="",45<=F7)),(D7*(1+assumptions!$G$76)^3/12*(1+assumptions!$G$70+assumptions!$G$71+IF(45>=assumptions!$G$73,assumptions!$G$72,0))+assumptions!$G$74/12)+IF(45=E7,D7*assumptions!$G$75,0),0) | AZ7: =IF(AND(46>=E7,OR(F7="",46<=F7)),(D7*(1+assumptions!$G$76)^3/12*(1+assumptions!$G$70+assumptions!$G$71+IF(46>=assumptions!$G$73,assumptions!$G$72,0))+assumptions!$G$74/12)+IF(46=E7,D7*assumptions!$G$75,0),0) | BA7: =IF(AND(47>=E7,OR(F7="",47<=F7)),(D7*(1+assumptions!$G$76)^3/12*(1+assumptions!$G$70+assumptions!$G$71+IF(47>=assumptions!$G$73,assumptions!$G$72,0))+assumptions!$G$74/12)+IF(47=E7,D7*assumptions!$G$75,0),0) | BB7: =IF(AND(48>=E7,OR(F7="",48<=F7)),(D7*(1+assumptions!$G$76)^3/12*(1+assumptions!$G$70+assumptions!$G$71+IF(48>=assumptions!$G$73,assumptions!$G$72,0))+assumptions!$G$74/12)+IF(48=E7,D7*assumptions!$G$75,0),0) | BC7: =IF(AND(49>=E7,OR(F7="",49<=F7)),(D7*(1+assumptions!$G$76)^4/12*(1+assumptions!$G$70+assumptions!$G$71+IF(49>=assumptions!$G$73,assumptions!$G$72,0))+assumptions!$G$74/12)+IF(49=E7,D7*assumptions!$G$75,0),0) | BD7: =IF(AND(50>=E7,OR(F7="",50<=F7)),(D7*(1+assumptions!$G$76)^4/12*(1+assumptions!$G$70+assumptions!$G$71+IF(50>=assumptions!$G$73,assumptions!$G$72,0))+assumptions!$G$74/12)+IF(50=E7,D7*assumptions!$G$75,0),0) | BE7: =IF(AND(51>=E7,OR(F7="",51<=F7)),(D7*(1+assumptions!$G$76)^4/12*(1+assumptions!$G$70+assumptions!$G$71+IF(51>=assumptions!$G$73,assumptions!$G$72,0))+assumptions!$G$74/12)+IF(51=E7,D7*assumptions!$G$75,0),0) | BF7: =IF(AND(52>=E7,OR(F7="",52<=F7)),(D7*(1+assumptions!$G$76)^4/12*(1+assumptions!$G$70+assumptions!$G$71+IF(52>=assumptions!$G$73,assumptions!$G$72,0))+assumptions!$G$74/12)+IF(52=E7,D7*assumptions!$G$75,0),0) | BG7: =IF(AND(53>=E7,OR(F7="",53<=F7)),(D7*(1+assumptions!$G$76)^4/12*(1+assumptions!$G$70+assumptions!$G$71+IF(53>=assumptions!$G$73,assumptions!$G$72,0))+assumptions!$G$74/12)+IF(53=E7,D7*assumptions!$G$75,0),0) | BH7: =IF(AND(54>=E7,OR(F7="",54<=F7)),(D7*(1+assumptions!$G$76)^4/12*(1+assumptions!$G$70+assumptions!$G$71+IF(54>=assumptions!$G$73,assumptions!$G$72,0))+assumptions!$G$74/12)+IF(54=E7,D7*assumptions!$G$75,0),0) | BI7: =IF(AND(55>=E7,OR(F7="",55<=F7)),(D7*(1+assumptions!$G$76)^4/12*(1+assumptions!$G$70+assumptions!$G$71+IF(55>=assumptions!$G$73,assumptions!$G$72,0))+assumptions!$G$74/12)+IF(55=E7,D7*assumptions!$G$75,0),0) | BJ7: =IF(AND(56>=E7,OR(F7="",56<=F7)),(D7*(1+assumptions!$G$76)^4/12*(1+assumptions!$G$70+assumptions!$G$71+IF(56>=assumptions!$G$73,assumptions!$G$72,0))+assumptions!$G$74/12)+IF(56=E7,D7*assumptions!$G$75,0),0) | BK7: =IF(AND(57>=E7,OR(F7="",57<=F7)),(D7*(1+assumptions!$G$76)^4/12*(1+assumptions!$G$70+assumptions!$G$71+IF(57>=assumptions!$G$73,assumptions!$G$72,0))+assumptions!$G$74/12)+IF(57=E7,D7*assumptions!$G$75,0),0) | BL7: =IF(AND(58>=E7,OR(F7="",58<=F7)),(D7*(1+assumptions!$G$76)^4/12*(1+assumptions!$G$70+assumptions!$G$71+IF(58>=assumptions!$G$73,assumptions!$G$72,0))+assumptions!$G$74/12)+IF(58=E7,D7*assumptions!$G$75,0),0) | BM7: =IF(AND(59>=E7,OR(F7="",59<=F7)),(D7*(1+assumptions!$G$76)^4/12*(1+assumptions!$G$70+assumptions!$G$71+IF(59>=assumptions!$G$73,assumptions!$G$72,0))+assumptions!$G$74/12)+IF(59=E7,D7*assumptions!$G$75,0),0) | BN7: =IF(AND(60>=E7,OR(F7="",60<=F7)),(D7*(1+assumptions!$G$76)^4/12*(1+assumptions!$G$70+assumptions!$G$71+IF(60>=assumptions!$G$73,assumptions!$G$72,0))+assumptions!$G$74/12)+IF(60=E7,D7*assumptions!$G$75,0),0)
A8: 5 | B8: Senior full-stack engineer | C8: eng | D8: 90000 | E8: 2 | G8: =IF(AND(1>=E8,OR(F8="",1<=F8)),(D8*(1+assumptions!$G$76)^0/12*(1+assumptions!$G$70+assumptions!$G$71+IF(1>=assumptions!$G$73,assumptions!$G$72,0))+assumptions!$G$74/12)+IF(1=E8,D8*assumptions!$G$75,0),0) | H8: =IF(AND(2>=E8,OR(F8="",2<=F8)),(D8*(1+assumptions!$G$76)^0/12*(1+assumptions!$G$70+assumptions!$G$71+IF(2>=assumptions!$G$73,assumptions!$G$72,0))+assumptions!$G$74/12)+IF(2=E8,D8*assumptions!$G$75,0),0) | I8: =IF(AND(3>=E8,OR(F8="",3<=F8)),(D8*(1+assumptions!$G$76)^0/12*(1+assumptions!$G$70+assumptions!$G$71+IF(3>=assumptions!$G$73,assumptions!$G$72,0))+assumptions!$G$74/12)+IF(3=E8,D8*assumptions!$G$75,0),0) | J8: =IF(AND(4>=E8,OR(F8="",4<=F8)),(D8*(1+assumptions!$G$76)^0/12*(1+assumptions!$G$70+assumptions!$G$71+IF(4>=assumptions!$G$73,assumptions!$G$72,0))+assumptions!$G$74/12)+IF(4=E8,D8*assumptions!$G$75,0),0) | K8: =IF(AND(5>=E8,OR(F8="",5<=F8)),(D8*(1+assumptions!$G$76)^0/12*(1+assumptions!$G$70+assumptions!$G$71+IF(5>=assumptions!$G$73,assumptions!$G$72,0))+assumptions!$G$74/12)+IF(5=E8,D8*assumptions!$G$75,0),0) | L8: =IF(AND(6>=E8,OR(F8="",6<=F8)),(D8*(1+assumptions!$G$76)^0/12*(1+assumptions!$G$70+assumptions!$G$71+IF(6>=assumptions!$G$73,assumptions!$G$72,0))+assumptions!$G$74/12)+IF(6=E8,D8*assumptions!$G$75,0),0) | M8: =IF(AND(7>=E8,OR(F8="",7<=F8)),(D8*(1+assumptions!$G$76)^0/12*(1+assumptions!$G$70+assumptions!$G$71+IF(7>=assumptions!$G$73,assumptions!$G$72,0))+assumptions!$G$74/12)+IF(7=E8,D8*assumptions!$G$75,0),0) | N8: =IF(AND(8>=E8,OR(F8="",8<=F8)),(D8*(1+assumptions!$G$76)^0/12*(1+assumptions!$G$70+assumptions!$G$71+IF(8>=assumptions!$G$73,assumptions!$G$72,0))+assumptions!$G$74/12)+IF(8=E8,D8*assumptions!$G$75,0),0) | O8: =IF(AND(9>=E8,OR(F8="",9<=F8)),(D8*(1+assumptions!$G$76)^0/12*(1+assumptions!$G$70+assumptions!$G$71+IF(9>=assumptions!$G$73,assumptions!$G$72,0))+assumptions!$G$74/12)+IF(9=E8,D8*assumptions!$G$75,0),0) | P8: =IF(AND(10>=E8,OR(F8="",10<=F8)),(D8*(1+assumptions!$G$76)^0/12*(1+assumptions!$G$70+assumptions!$G$71+IF(10>=assumptions!$G$73,assumptions!$G$72,0))+assumptions!$G$74/12)+IF(10=E8,D8*assumptions!$G$75,0),0) | Q8: =IF(AND(11>=E8,OR(F8="",11<=F8)),(D8*(1+assumptions!$G$76)^0/12*(1+assumptions!$G$70+assumptions!$G$71+IF(11>=assumptions!$G$73,assumptions!$G$72,0))+assumptions!$G$74/12)+IF(11=E8,D8*assumptions!$G$75,0),0) | R8: =IF(AND(12>=E8,OR(F8="",12<=F8)),(D8*(1+assumptions!$G$76)^0/12*(1+assumptions!$G$70+assumptions!$G$71+IF(12>=assumptions!$G$73,assumptions!$G$72,0))+assumptions!$G$74/12)+IF(12=E8,D8*assumptions!$G$75,0),0) | S8: =IF(AND(13>=E8,OR(F8="",13<=F8)),(D8*(1+assumptions!$G$76)^1/12*(1+assumptions!$G$70+assumptions!$G$71+IF(13>=assumptions!$G$73,assumptions!$G$72,0))+assumptions!$G$74/12)+IF(13=E8,D8*assumptions!$G$75,0),0) | T8: =IF(AND(14>=E8,OR(F8="",14<=F8)),(D8*(1+assumptions!$G$76)^1/12*(1+assumptions!$G$70+assumptions!$G$71+IF(14>=assumptions!$G$73,assumptions!$G$72,0))+assumptions!$G$74/12)+IF(14=E8,D8*assumptions!$G$75,0),0) | U8: =IF(AND(15>=E8,OR(F8="",15<=F8)),(D8*(1+assumptions!$G$76)^1/12*(1+assumptions!$G$70+assumptions!$G$71+IF(15>=assumptions!$G$73,assumptions!$G$72,0))+assumptions!$G$74/12)+IF(15=E8,D8*assumptions!$G$75,0),0) | V8: =IF(AND(16>=E8,OR(F8="",16<=F8)),(D8*(1+assumptions!$G$76)^1/12*(1+assumptions!$G$70+assumptions!$G$71+IF(16>=assumptions!$G$73,assumptions!$G$72,0))+assumptions!$G$74/12)+IF(16=E8,D8*assumptions!$G$75,0),0) | W8: =IF(AND(17>=E8,OR(F8="",17<=F8)),(D8*(1+assumptions!$G$76)^1/12*(1+assumptions!$G$70+assumptions!$G$71+IF(17>=assumptions!$G$73,assumptions!$G$72,0))+assumptions!$G$74/12)+IF(17=E8,D8*assumptions!$G$75,0),0) | X8: =IF(AND(18>=E8,OR(F8="",18<=F8)),(D8*(1+assumptions!$G$76)^1/12*(1+assumptions!$G$70+assumptions!$G$71+IF(18>=assumptions!$G$73,assumptions!$G$72,0))+assumptions!$G$74/12)+IF(18=E8,D8*assumptions!$G$75,0),0) | Y8: =IF(AND(19>=E8,OR(F8="",19<=F8)),(D8*(1+assumptions!$G$76)^1/12*(1+assumptions!$G$70+assumptions!$G$71+IF(19>=assumptions!$G$73,assumptions!$G$72,0))+assumptions!$G$74/12)+IF(19=E8,D8*assumptions!$G$75,0),0) | Z8: =IF(AND(20>=E8,OR(F8="",20<=F8)),(D8*(1+assumptions!$G$76)^1/12*(1+assumptions!$G$70+assumptions!$G$71+IF(20>=assumptions!$G$73,assumptions!$G$72,0))+assumptions!$G$74/12)+IF(20=E8,D8*assumptions!$G$75,0),0) | AA8: =IF(AND(21>=E8,OR(F8="",21<=F8)),(D8*(1+assumptions!$G$76)^1/12*(1+assumptions!$G$70+assumptions!$G$71+IF(21>=assumptions!$G$73,assumptions!$G$72,0))+assumptions!$G$74/12)+IF(21=E8,D8*assumptions!$G$75,0),0) | AB8: =IF(AND(22>=E8,OR(F8="",22<=F8)),(D8*(1+assumptions!$G$76)^1/12*(1+assumptions!$G$70+assumptions!$G$71+IF(22>=assumptions!$G$73,assumptions!$G$72,0))+assumptions!$G$74/12)+IF(22=E8,D8*assumptions!$G$75,0),0) | AC8: =IF(AND(23>=E8,OR(F8="",23<=F8)),(D8*(1+assumptions!$G$76)^1/12*(1+assumptions!$G$70+assumptions!$G$71+IF(23>=assumptions!$G$73,assumptions!$G$72,0))+assumptions!$G$74/12)+IF(23=E8,D8*assumptions!$G$75,0),0) | AD8: =IF(AND(24>=E8,OR(F8="",24<=F8)),(D8*(1+assumptions!$G$76)^1/12*(1+assumptions!$G$70+assumptions!$G$71+IF(24>=assumptions!$G$73,assumptions!$G$72,0))+assumptions!$G$74/12)+IF(24=E8,D8*assumptions!$G$75,0),0) | AE8: =IF(AND(25>=E8,OR(F8="",25<=F8)),(D8*(1+assumptions!$G$76)^2/12*(1+assumptions!$G$70+assumptions!$G$71+IF(25>=assumptions!$G$73,assumptions!$G$72,0))+assumptions!$G$74/12)+IF(25=E8,D8*assumptions!$G$75,0),0) | AF8: =IF(AND(26>=E8,OR(F8="",26<=F8)),(D8*(1+assumptions!$G$76)^2/12*(1+assumptions!$G$70+assumptions!$G$71+IF(26>=assumptions!$G$73,assumptions!$G$72,0))+assumptions!$G$74/12)+IF(26=E8,D8*assumptions!$G$75,0),0) | AG8: =IF(AND(27>=E8,OR(F8="",27<=F8)),(D8*(1+assumptions!$G$76)^2/12*(1+assumptions!$G$70+assumptions!$G$71+IF(27>=assumptions!$G$73,assumptions!$G$72,0))+assumptions!$G$74/12)+IF(27=E8,D8*assumptions!$G$75,0),0) | AH8: =IF(AND(28>=E8,OR(F8="",28<=F8)),(D8*(1+assumptions!$G$76)^2/12*(1+assumptions!$G$70+assumptions!$G$71+IF(28>=assumptions!$G$73,assumptions!$G$72,0))+assumptions!$G$74/12)+IF(28=E8,D8*assumptions!$G$75,0),0) | AI8: =IF(AND(29>=E8,OR(F8="",29<=F8)),(D8*(1+assumptions!$G$76)^2/12*(1+assumptions!$G$70+assumptions!$G$71+IF(29>=assumptions!$G$73,assumptions!$G$72,0))+assumptions!$G$74/12)+IF(29=E8,D8*assumptions!$G$75,0),0) | AJ8: =IF(AND(30>=E8,OR(F8="",30<=F8)),(D8*(1+assumptions!$G$76)^2/12*(1+assumptions!$G$70+assumptions!$G$71+IF(30>=assumptions!$G$73,assumptions!$G$72,0))+assumptions!$G$74/12)+IF(30=E8,D8*assumptions!$G$75,0),0) | AK8: =IF(AND(31>=E8,OR(F8="",31<=F8)),(D8*(1+assumptions!$G$76)^2/12*(1+assumptions!$G$70+assumptions!$G$71+IF(31>=assumptions!$G$73,assumptions!$G$72,0))+assumptions!$G$74/12)+IF(31=E8,D8*assumptions!$G$75,0),0) | AL8: =IF(AND(32>=E8,OR(F8="",32<=F8)),(D8*(1+assumptions!$G$76)^2/12*(1+assumptions!$G$70+assumptions!$G$71+IF(32>=assumptions!$G$73,assumptions!$G$72,0))+assumptions!$G$74/12)+IF(32=E8,D8*assumptions!$G$75,0),0) | AM8: =IF(AND(33>=E8,OR(F8="",33<=F8)),(D8*(1+assumptions!$G$76)^2/12*(1+assumptions!$G$70+assumptions!$G$71+IF(33>=assumptions!$G$73,assumptions!$G$72,0))+assumptions!$G$74/12)+IF(33=E8,D8*assumptions!$G$75,0),0) | AN8: =IF(AND(34>=E8,OR(F8="",34<=F8)),(D8*(1+assumptions!$G$76)^2/12*(1+assumptions!$G$70+assumptions!$G$71+IF(34>=assumptions!$G$73,assumptions!$G$72,0))+assumptions!$G$74/12)+IF(34=E8,D8*assumptions!$G$75,0),0) | AO8: =IF(AND(35>=E8,OR(F8="",35<=F8)),(D8*(1+assumptions!$G$76)^2/12*(1+assumptions!$G$70+assumptions!$G$71+IF(35>=assumptions!$G$73,assumptions!$G$72,0))+assumptions!$G$74/12)+IF(35=E8,D8*assumptions!$G$75,0),0) | AP8: =IF(AND(36>=E8,OR(F8="",36<=F8)),(D8*(1+assumptions!$G$76)^2/12*(1+assumptions!$G$70+assumptions!$G$71+IF(36>=assumptions!$G$73,assumptions!$G$72,0))+assumptions!$G$74/12)+IF(36=E8,D8*assumptions!$G$75,0),0) | AQ8: =IF(AND(37>=E8,OR(F8="",37<=F8)),(D8*(1+assumptions!$G$76)^3/12*(1+assumptions!$G$70+assumptions!$G$71+IF(37>=assumptions!$G$73,assumptions!$G$72,0))+assumptions!$G$74/12)+IF(37=E8,D8*assumptions!$G$75,0),0) | AR8: =IF(AND(38>=E8,OR(F8="",38<=F8)),(D8*(1+assumptions!$G$76)^3/12*(1+assumptions!$G$70+assumptions!$G$71+IF(38>=assumptions!$G$73,assumptions!$G$72,0))+assumptions!$G$74/12)+IF(38=E8,D8*assumptions!$G$75,0),0) | AS8: =IF(AND(39>=E8,OR(F8="",39<=F8)),(D8*(1+assumptions!$G$76)^3/12*(1+assumptions!$G$70+assumptions!$G$71+IF(39>=assumptions!$G$73,assumptions!$G$72,0))+assumptions!$G$74/12)+IF(39=E8,D8*assumptions!$G$75,0),0) | AT8: =IF(AND(40>=E8,OR(F8="",40<=F8)),(D8*(1+assumptions!$G$76)^3/12*(1+assumptions!$G$70+assumptions!$G$71+IF(40>=assumptions!$G$73,assumptions!$G$72,0))+assumptions!$G$74/12)+IF(40=E8,D8*assumptions!$G$75,0),0) | AU8: =IF(AND(41>=E8,OR(F8="",41<=F8)),(D8*(1+assumptions!$G$76)^3/12*(1+assumptions!$G$70+assumptions!$G$71+IF(41>=assumptions!$G$73,assumptions!$G$72,0))+assumptions!$G$74/12)+IF(41=E8,D8*assumptions!$G$75,0),0) | AV8: =IF(AND(42>=E8,OR(F8="",42<=F8)),(D8*(1+assumptions!$G$76)^3/12*(1+assumptions!$G$70+assumptions!$G$71+IF(42>=assumptions!$G$73,assumptions!$G$72,0))+assumptions!$G$74/12)+IF(42=E8,D8*assumptions!$G$75,0),0) | AW8: =IF(AND(43>=E8,OR(F8="",43<=F8)),(D8*(1+assumptions!$G$76)^3/12*(1+assumptions!$G$70+assumptions!$G$71+IF(43>=assumptions!$G$73,assumptions!$G$72,0))+assumptions!$G$74/12)+IF(43=E8,D8*assumptions!$G$75,0),0) | AX8: =IF(AND(44>=E8,OR(F8="",44<=F8)),(D8*(1+assumptions!$G$76)^3/12*(1+assumptions!$G$70+assumptions!$G$71+IF(44>=assumptions!$G$73,assumptions!$G$72,0))+assumptions!$G$74/12)+IF(44=E8,D8*assumptions!$G$75,0),0) | AY8: =IF(AND(45>=E8,OR(F8="",45<=F8)),(D8*(1+assumptions!$G$76)^3/12*(1+assumptions!$G$70+assumptions!$G$71+IF(45>=assumptions!$G$73,assumptions!$G$72,0))+assumptions!$G$74/12)+IF(45=E8,D8*assumptions!$G$75,0),0) | AZ8: =IF(AND(46>=E8,OR(F8="",46<=F8)),(D8*(1+assumptions!$G$76)^3/12*(1+assumptions!$G$70+assumptions!$G$71+IF(46>=assumptions!$G$73,assumptions!$G$72,0))+assumptions!$G$74/12)+IF(46=E8,D8*assumptions!$G$75,0),0) | BA8: =IF(AND(47>=E8,OR(F8="",47<=F8)),(D8*(1+assumptions!$G$76)^3/12*(1+assumptions!$G$70+assumptions!$G$71+IF(47>=assumptions!$G$73,assumptions!$G$72,0))+assumptions!$G$74/12)+IF(47=E8,D8*assumptions!$G$75,0),0) | BB8: =IF(AND(48>=E8,OR(F8="",48<=F8)),(D8*(1+assumptions!$G$76)^3/12*(1+assumptions!$G$70+assumptions!$G$71+IF(48>=assumptions!$G$73,assumptions!$G$72,0))+assumptions!$G$74/12)+IF(48=E8,D8*assumptions!$G$75,0),0) | BC8: =IF(AND(49>=E8,OR(F8="",49<=F8)),(D8*(1+assumptions!$G$76)^4/12*(1+assumptions!$G$70+assumptions!$G$71+IF(49>=assumptions!$G$73,assumptions!$G$72,0))+assumptions!$G$74/12)+IF(49=E8,D8*assumptions!$G$75,0),0) | BD8: =IF(AND(50>=E8,OR(F8="",50<=F8)),(D8*(1+assumptions!$G$76)^4/12*(1+assumptions!$G$70+assumptions!$G$71+IF(50>=assumptions!$G$73,assumptions!$G$72,0))+assumptions!$G$74/12)+IF(50=E8,D8*assumptions!$G$75,0),0) | BE8: =IF(AND(51>=E8,OR(F8="",51<=F8)),(D8*(1+assumptions!$G$76)^4/12*(1+assumptions!$G$70+assumptions!$G$71+IF(51>=assumptions!$G$73,assumptions!$G$72,0))+assumptions!$G$74/12)+IF(51=E8,D8*assumptions!$G$75,0),0) | BF8: =IF(AND(52>=E8,OR(F8="",52<=F8)),(D8*(1+assumptions!$G$76)^4/12*(1+assumptions!$G$70+assumptions!$G$71+IF(52>=assumptions!$G$73,assumptions!$G$72,0))+assumptions!$G$74/12)+IF(52=E8,D8*assumptions!$G$75,0),0) | BG8: =IF(AND(53>=E8,OR(F8="",53<=F8)),(D8*(1+assumptions!$G$76)^4/12*(1+assumptions!$G$70+assumptions!$G$71+IF(53>=assumptions!$G$73,assumptions!$G$72,0))+assumptions!$G$74/12)+IF(53=E8,D8*assumptions!$G$75,0),0) | BH8: =IF(AND(54>=E8,OR(F8="",54<=F8)),(D8*(1+assumptions!$G$76)^4/12*(1+assumptions!$G$70+assumptions!$G$71+IF(54>=assumptions!$G$73,assumptions!$G$72,0))+assumptions!$G$74/12)+IF(54=E8,D8*assumptions!$G$75,0),0) | BI8: =IF(AND(55>=E8,OR(F8="",55<=F8)),(D8*(1+assumptions!$G$76)^4/12*(1+assumptions!$G$70+assumptions!$G$71+IF(55>=assumptions!$G$73,assumptions!$G$72,0))+assumptions!$G$74/12)+IF(55=E8,D8*assumptions!$G$75,0),0) | BJ8: =IF(AND(56>=E8,OR(F8="",56<=F8)),(D8*(1+assumptions!$G$76)^4/12*(1+assumptions!$G$70+assumptions!$G$71+IF(56>=assumptions!$G$73,assumptions!$G$72,0))+assumptions!$G$74/12)+IF(56=E8,D8*assumptions!$G$75,0),0) | BK8: =IF(AND(57>=E8,OR(F8="",57<=F8)),(D8*(1+assumptions!$G$76)^4/12*(1+assumptions!$G$70+assumptions!$G$71+IF(57>=assumptions!$G$73,assumptions!$G$72,0))+assumptions!$G$74/12)+IF(57=E8,D8*assumptions!$G$75,0),0) | BL8: =IF(AND(58>=E8,OR(F8="",58<=F8)),(D8*(1+assumptions!$G$76)^4/12*(1+assumptions!$G$70+assumptions!$G$71+IF(58>=assumptions!$G$73,assumptions!$G$72,0))+assumptions!$G$74/12)+IF(58=E8,D8*assumptions!$G$75,0),0) | BM8: =IF(AND(59>=E8,OR(F8="",59<=F8)),(D8*(1+assumptions!$G$76)^4/12*(1+assumptions!$G$70+assumptions!$G$71+IF(59>=assumptions!$G$73,assumptions!$G$72,0))+assumptions!$G$74/12)+IF(59=E8,D8*assumptions!$G$75,0),0) | BN8: =IF(AND(60>=E8,OR(F8="",60<=F8)),(D8*(1+assumptions!$G$76)^4/12*(1+assumptions!$G$70+assumptions!$G$71+IF(60>=assumptions!$G$73,assumptions!$G$72,0))+assumptions!$G$74/12)+IF(60=E8,D8*assumptions!$G$75,0),0)
A9: 6 | B9: Product designer | C9: design | D9: 75000 | E9: 2 | G9: =IF(AND(1>=E9,OR(F9="",1<=F9)),(D9*(1+assumptions!$G$76)^0/12*(1+assumptions!$G$70+assumptions!$G$71+IF(1>=assumptions!$G$73,assumptions!$G$72,0))+assumptions!$G$74/12)+IF(1=E9,D9*assumptions!$G$75,0),0) | H9: =IF(AND(2>=E9,OR(F9="",2<=F9)),(D9*(1+assumptions!$G$76)^0/12*(1+assumptions!$G$70+assumptions!$G$71+IF(2>=assumptions!$G$73,assumptions!$G$72,0))+assumptions!$G$74/12)+IF(2=E9,D9*assumptions!$G$75,0),0) | I9: =IF(AND(3>=E9,OR(F9="",3<=F9)),(D9*(1+assumptions!$G$76)^0/12*(1+assumptions!$G$70+assumptions!$G$71+IF(3>=assumptions!$G$73,assumptions!$G$72,0))+assumptions!$G$74/12)+IF(3=E9,D9*assumptions!$G$75,0),0) | J9: =IF(AND(4>=E9,OR(F9="",4<=F9)),(D9*(1+assumptions!$G$76)^0/12*(1+assumptions!$G$70+assumptions!$G$71+IF(4>=assumptions!$G$73,assumptions!$G$72,0))+assumptions!$G$74/12)+IF(4=E9,D9*assumptions!$G$75,0),0) | K9: =IF(AND(5>=E9,OR(F9="",5<=F9)),(D9*(1+assumptions!$G$76)^0/12*(1+assumptions!$G$70+assumptions!$G$71+IF(5>=assumptions!$G$73,assumptions!$G$72,0))+assumptions!$G$74/12)+IF(5=E9,D9*assumptions!$G$75,0),0) | L9: =IF(AND(6>=E9,OR(F9="",6<=F9)),(D9*(1+assumptions!$G$76)^0/12*(1+assumptions!$G$70+assumptions!$G$71+IF(6>=assumptions!$G$73,assumptions!$G$72,0))+assumptions!$G$74/12)+IF(6=E9,D9*assumptions!$G$75,0),0) | M9: =IF(AND(7>=E9,OR(F9="",7<=F9)),(D9*(1+assumptions!$G$76)^0/12*(1+assumptions!$G$70+assumptions!$G$71+IF(7>=assumptions!$G$73,assumptions!$G$72,0))+assumptions!$G$74/12)+IF(7=E9,D9*assumptions!$G$75,0),0) | N9: =IF(AND(8>=E9,OR(F9="",8<=F9)),(D9*(1+assumptions!$G$76)^0/12*(1+assumptions!$G$70+assumptions!$G$71+IF(8>=assumptions!$G$73,assumptions!$G$72,0))+assumptions!$G$74/12)+IF(8=E9,D9*assumptions!$G$75,0),0) | O9: =IF(AND(9>=E9,OR(F9="",9<=F9)),(D9*(1+assumptions!$G$76)^0/12*(1+assumptions!$G$70+assumptions!$G$71+IF(9>=assumptions!$G$73,assumptions!$G$72,0))+assumptions!$G$74/12)+IF(9=E9,D9*assumptions!$G$75,0),0) | P9: =IF(AND(10>=E9,OR(F9="",10<=F9)),(D9*(1+assumptions!$G$76)^0/12*(1+assumptions!$G$70+assumptions!$G$71+IF(10>=assumptions!$G$73,assumptions!$G$72,0))+assumptions!$G$74/12)+IF(10=E9,D9*assumptions!$G$75,0),0) | Q9: =IF(AND(11>=E9,OR(F9="",11<=F9)),(D9*(1+assumptions!$G$76)^0/12*(1+assumptions!$G$70+assumptions!$G$71+IF(11>=assumptions!$G$73,assumptions!$G$72,0))+assumptions!$G$74/12)+IF(11=E9,D9*assumptions!$G$75,0),0) | R9: =IF(AND(12>=E9,OR(F9="",12<=F9)),(D9*(1+assumptions!$G$76)^0/12*(1+assumptions!$G$70+assumptions!$G$71+IF(12>=assumptions!$G$73,assumptions!$G$72,0))+assumptions!$G$74/12)+IF(12=E9,D9*assumptions!$G$75,0),0) | S9: =IF(AND(13>=E9,OR(F9="",13<=F9)),(D9*(1+assumptions!$G$76)^1/12*(1+assumptions!$G$70+assumptions!$G$71+IF(13>=assumptions!$G$73,assumptions!$G$72,0))+assumptions!$G$74/12)+IF(13=E9,D9*assumptions!$G$75,0),0) | T9: =IF(AND(14>=E9,OR(F9="",14<=F9)),(D9*(1+assumptions!$G$76)^1/12*(1+assumptions!$G$70+assumptions!$G$71+IF(14>=assumptions!$G$73,assumptions!$G$72,0))+assumptions!$G$74/12)+IF(14=E9,D9*assumptions!$G$75,0),0) | U9: =IF(AND(15>=E9,OR(F9="",15<=F9)),(D9*(1+assumptions!$G$76)^1/12*(1+assumptions!$G$70+assumptions!$G$71+IF(15>=assumptions!$G$73,assumptions!$G$72,0))+assumptions!$G$74/12)+IF(15=E9,D9*assumptions!$G$75,0),0) | V9: =IF(AND(16>=E9,OR(F9="",16<=F9)),(D9*(1+assumptions!$G$76)^1/12*(1+assumptions!$G$70+assumptions!$G$71+IF(16>=assumptions!$G$73,assumptions!$G$72,0))+assumptions!$G$74/12)+IF(16=E9,D9*assumptions!$G$75,0),0) | W9: =IF(AND(17>=E9,OR(F9="",17<=F9)),(D9*(1+assumptions!$G$76)^1/12*(1+assumptions!$G$70+assumptions!$G$71+IF(17>=assumptions!$G$73,assumptions!$G$72,0))+assumptions!$G$74/12)+IF(17=E9,D9*assumptions!$G$75,0),0) | X9: =IF(AND(18>=E9,OR(F9="",18<=F9)),(D9*(1+assumptions!$G$76)^1/12*(1+assumptions!$G$70+assumptions!$G$71+IF(18>=assumptions!$G$73,assumptions!$G$72,0))+assumptions!$G$74/12)+IF(18=E9,D9*assumptions!$G$75,0),0) | Y9: =IF(AND(19>=E9,OR(F9="",19<=F9)),(D9*(1+assumptions!$G$76)^1/12*(1+assumptions!$G$70+assumptions!$G$71+IF(19>=assumptions!$G$73,assumptions!$G$72,0))+assumptions!$G$74/12)+IF(19=E9,D9*assumptions!$G$75,0),0) | Z9: =IF(AND(20>=E9,OR(F9="",20<=F9)),(D9*(1+assumptions!$G$76)^1/12*(1+assumptions!$G$70+assumptions!$G$71+IF(20>=assumptions!$G$73,assumptions!$G$72,0))+assumptions!$G$74/12)+IF(20=E9,D9*assumptions!$G$75,0),0) | AA9: =IF(AND(21>=E9,OR(F9="",21<=F9)),(D9*(1+assumptions!$G$76)^1/12*(1+assumptions!$G$70+assumptions!$G$71+IF(21>=assumptions!$G$73,assumptions!$G$72,0))+assumptions!$G$74/12)+IF(21=E9,D9*assumptions!$G$75,0),0) | AB9: =IF(AND(22>=E9,OR(F9="",22<=F9)),(D9*(1+assumptions!$G$76)^1/12*(1+assumptions!$G$70+assumptions!$G$71+IF(22>=assumptions!$G$73,assumptions!$G$72,0))+assumptions!$G$74/12)+IF(22=E9,D9*assumptions!$G$75,0),0) | AC9: =IF(AND(23>=E9,OR(F9="",23<=F9)),(D9*(1+assumptions!$G$76)^1/12*(1+assumptions!$G$70+assumptions!$G$71+IF(23>=assumptions!$G$73,assumptions!$G$72,0))+assumptions!$G$74/12)+IF(23=E9,D9*assumptions!$G$75,0),0) | AD9: =IF(AND(24>=E9,OR(F9="",24<=F9)),(D9*(1+assumptions!$G$76)^1/12*(1+assumptions!$G$70+assumptions!$G$71+IF(24>=assumptions!$G$73,assumptions!$G$72,0))+assumptions!$G$74/12)+IF(24=E9,D9*assumptions!$G$75,0),0) | AE9: =IF(AND(25>=E9,OR(F9="",25<=F9)),(D9*(1+assumptions!$G$76)^2/12*(1+assumptions!$G$70+assumptions!$G$71+IF(25>=assumptions!$G$73,assumptions!$G$72,0))+assumptions!$G$74/12)+IF(25=E9,D9*assumptions!$G$75,0),0) | AF9: =IF(AND(26>=E9,OR(F9="",26<=F9)),(D9*(1+assumptions!$G$76)^2/12*(1+assumptions!$G$70+assumptions!$G$71+IF(26>=assumptions!$G$73,assumptions!$G$72,0))+assumptions!$G$74/12)+IF(26=E9,D9*assumptions!$G$75,0),0) | AG9: =IF(AND(27>=E9,OR(F9="",27<=F9)),(D9*(1+assumptions!$G$76)^2/12*(1+assumptions!$G$70+assumptions!$G$71+IF(27>=assumptions!$G$73,assumptions!$G$72,0))+assumptions!$G$74/12)+IF(27=E9,D9*assumptions!$G$75,0),0) | AH9: =IF(AND(28>=E9,OR(F9="",28<=F9)),(D9*(1+assumptions!$G$76)^2/12*(1+assumptions!$G$70+assumptions!$G$71+IF(28>=assumptions!$G$73,assumptions!$G$72,0))+assumptions!$G$74/12)+IF(28=E9,D9*assumptions!$G$75,0),0) | AI9: =IF(AND(29>=E9,OR(F9="",29<=F9)),(D9*(1+assumptions!$G$76)^2/12*(1+assumptions!$G$70+assumptions!$G$71+IF(29>=assumptions!$G$73,assumptions!$G$72,0))+assumptions!$G$74/12)+IF(29=E9,D9*assumptions!$G$75,0),0) | AJ9: =IF(AND(30>=E9,OR(F9="",30<=F9)),(D9*(1+assumptions!$G$76)^2/12*(1+assumptions!$G$70+assumptions!$G$71+IF(30>=assumptions!$G$73,assumptions!$G$72,0))+assumptions!$G$74/12)+IF(30=E9,D9*assumptions!$G$75,0),0) | AK9: =IF(AND(31>=E9,OR(F9="",31<=F9)),(D9*(1+assumptions!$G$76)^2/12*(1+assumptions!$G$70+assumptions!$G$71+IF(31>=assumptions!$G$73,assumptions!$G$72,0))+assumptions!$G$74/12)+IF(31=E9,D9*assumptions!$G$75,0),0) | AL9: =IF(AND(32>=E9,OR(F9="",32<=F9)),(D9*(1+assumptions!$G$76)^2/12*(1+assumptions!$G$70+assumptions!$G$71+IF(32>=assumptions!$G$73,assumptions!$G$72,0))+assumptions!$G$74/12)+IF(32=E9,D9*assumptions!$G$75,0),0) | AM9: =IF(AND(33>=E9,OR(F9="",33<=F9)),(D9*(1+assumptions!$G$76)^2/12*(1+assumptions!$G$70+assumptions!$G$71+IF(33>=assumptions!$G$73,assumptions!$G$72,0))+assumptions!$G$74/12)+IF(33=E9,D9*assumptions!$G$75,0),0) | AN9: =IF(AND(34>=E9,OR(F9="",34<=F9)),(D9*(1+assumptions!$G$76)^2/12*(1+assumptions!$G$70+assumptions!$G$71+IF(34>=assumptions!$G$73,assumptions!$G$72,0))+assumptions!$G$74/12)+IF(34=E9,D9*assumptions!$G$75,0),0) | AO9: =IF(AND(35>=E9,OR(F9="",35<=F9)),(D9*(1+assumptions!$G$76)^2/12*(1+assumptions!$G$70+assumptions!$G$71+IF(35>=assumptions!$G$73,assumptions!$G$72,0))+assumptions!$G$74/12)+IF(35=E9,D9*assumptions!$G$75,0),0) | AP9: =IF(AND(36>=E9,OR(F9="",36<=F9)),(D9*(1+assumptions!$G$76)^2/12*(1+assumptions!$G$70+assumptions!$G$71+IF(36>=assumptions!$G$73,assumptions!$G$72,0))+assumptions!$G$74/12)+IF(36=E9,D9*assumptions!$G$75,0),0) | AQ9: =IF(AND(37>=E9,OR(F9="",37<=F9)),(D9*(1+assumptions!$G$76)^3/12*(1+assumptions!$G$70+assumptions!$G$71+IF(37>=assumptions!$G$73,assumptions!$G$72,0))+assumptions!$G$74/12)+IF(37=E9,D9*assumptions!$G$75,0),0) | AR9: =IF(AND(38>=E9,OR(F9="",38<=F9)),(D9*(1+assumptions!$G$76)^3/12*(1+assumptions!$G$70+assumptions!$G$71+IF(38>=assumptions!$G$73,assumptions!$G$72,0))+assumptions!$G$74/12)+IF(38=E9,D9*assumptions!$G$75,0),0) | AS9: =IF(AND(39>=E9,OR(F9="",39<=F9)),(D9*(1+assumptions!$G$76)^3/12*(1+assumptions!$G$70+assumptions!$G$71+IF(39>=assumptions!$G$73,assumptions!$G$72,0))+assumptions!$G$74/12)+IF(39=E9,D9*assumptions!$G$75,0),0) | AT9: =IF(AND(40>=E9,OR(F9="",40<=F9)),(D9*(1+assumptions!$G$76)^3/12*(1+assumptions!$G$70+assumptions!$G$71+IF(40>=assumptions!$G$73,assumptions!$G$72,0))+assumptions!$G$74/12)+IF(40=E9,D9*assumptions!$G$75,0),0) | AU9: =IF(AND(41>=E9,OR(F9="",41<=F9)),(D9*(1+assumptions!$G$76)^3/12*(1+assumptions!$G$70+assumptions!$G$71+IF(41>=assumptions!$G$73,assumptions!$G$72,0))+assumptions!$G$74/12)+IF(41=E9,D9*assumptions!$G$75,0),0) | AV9: =IF(AND(42>=E9,OR(F9="",42<=F9)),(D9*(1+assumptions!$G$76)^3/12*(1+assumptions!$G$70+assumptions!$G$71+IF(42>=assumptions!$G$73,assumptions!$G$72,0))+assumptions!$G$74/12)+IF(42=E9,D9*assumptions!$G$75,0),0) | AW9: =IF(AND(43>=E9,OR(F9="",43<=F9)),(D9*(1+assumptions!$G$76)^3/12*(1+assumptions!$G$70+assumptions!$G$71+IF(43>=assumptions!$G$73,assumptions!$G$72,0))+assumptions!$G$74/12)+IF(43=E9,D9*assumptions!$G$75,0),0) | AX9: =IF(AND(44>=E9,OR(F9="",44<=F9)),(D9*(1+assumptions!$G$76)^3/12*(1+assumptions!$G$70+assumptions!$G$71+IF(44>=assumptions!$G$73,assumptions!$G$72,0))+assumptions!$G$74/12)+IF(44=E9,D9*assumptions!$G$75,0),0) | AY9: =IF(AND(45>=E9,OR(F9="",45<=F9)),(D9*(1+assumptions!$G$76)^3/12*(1+assumptions!$G$70+assumptions!$G$71+IF(45>=assumptions!$G$73,assumptions!$G$72,0))+assumptions!$G$74/12)+IF(45=E9,D9*assumptions!$G$75,0),0) | AZ9: =IF(AND(46>=E9,OR(F9="",46<=F9)),(D9*(1+assumptions!$G$76)^3/12*(1+assumptions!$G$70+assumptions!$G$71+IF(46>=assumptions!$G$73,assumptions!$G$72,0))+assumptions!$G$74/12)+IF(46=E9,D9*assumptions!$G$75,0),0) | BA9: =IF(AND(47>=E9,OR(F9="",47<=F9)),(D9*(1+assumptions!$G$76)^3/12*(1+assumptions!$G$70+assumptions!$G$71+IF(47>=assumptions!$G$73,assumptions!$G$72,0))+assumptions!$G$74/12)+IF(47=E9,D9*assumptions!$G$75,0),0) | BB9: =IF(AND(48>=E9,OR(F9="",48<=F9)),(D9*(1+assumptions!$G$76)^3/12*(1+assumptions!$G$70+assumptions!$G$71+IF(48>=assumptions!$G$73,assumptions!$G$72,0))+assumptions!$G$74/12)+IF(48=E9,D9*assumptions!$G$75,0),0) | BC9: =IF(AND(49>=E9,OR(F9="",49<=F9)),(D9*(1+assumptions!$G$76)^4/12*(1+assumptions!$G$70+assumptions!$G$71+IF(49>=assumptions!$G$73,assumptions!$G$72,0))+assumptions!$G$74/12)+IF(49=E9,D9*assumptions!$G$75,0),0) | BD9: =IF(AND(50>=E9,OR(F9="",50<=F9)),(D9*(1+assumptions!$G$76)^4/12*(1+assumptions!$G$70+assumptions!$G$71+IF(50>=assumptions!$G$73,assumptions!$G$72,0))+assumptions!$G$74/12)+IF(50=E9,D9*assumptions!$G$75,0),0) | BE9: =IF(AND(51>=E9,OR(F9="",51<=F9)),(D9*(1+assumptions!$G$76)^4/12*(1+assumptions!$G$70+assumptions!$G$71+IF(51>=assumptions!$G$73,assumptions!$G$72,0))+assumptions!$G$74/12)+IF(51=E9,D9*assumptions!$G$75,0),0) | BF9: =IF(AND(52>=E9,OR(F9="",52<=F9)),(D9*(1+assumptions!$G$76)^4/12*(1+assumptions!$G$70+assumptions!$G$71+IF(52>=assumptions!$G$73,assumptions!$G$72,0))+assumptions!$G$74/12)+IF(52=E9,D9*assumptions!$G$75,0),0) | BG9: =IF(AND(53>=E9,OR(F9="",53<=F9)),(D9*(1+assumptions!$G$76)^4/12*(1+assumptions!$G$70+assumptions!$G$71+IF(53>=assumptions!$G$73,assumptions!$G$72,0))+assumptions!$G$74/12)+IF(53=E9,D9*assumptions!$G$75,0),0) | BH9: =IF(AND(54>=E9,OR(F9="",54<=F9)),(D9*(1+assumptions!$G$76)^4/12*(1+assumptions!$G$70+assumptions!$G$71+IF(54>=assumptions!$G$73,assumptions!$G$72,0))+assumptions!$G$74/12)+IF(54=E9,D9*assumptions!$G$75,0),0) | BI9: =IF(AND(55>=E9,OR(F9="",55<=F9)),(D9*(1+assumptions!$G$76)^4/12*(1+assumptions!$G$70+assumptions!$G$71+IF(55>=assumptions!$G$73,assumptions!$G$72,0))+assumptions!$G$74/12)+IF(55=E9,D9*assumptions!$G$75,0),0) | BJ9: =IF(AND(56>=E9,OR(F9="",56<=F9)),(D9*(1+assumptions!$G$76)^4/12*(1+assumptions!$G$70+assumptions!$G$71+IF(56>=assumptions!$G$73,assumptions!$G$72,0))+assumptions!$G$74/12)+IF(56=E9,D9*assumptions!$G$75,0),0) | BK9: =IF(AND(57>=E9,OR(F9="",57<=F9)),(D9*(1+assumptions!$G$76)^4/12*(1+assumptions!$G$70+assumptions!$G$71+IF(57>=assumptions!$G$73,assumptions!$G$72,0))+assumptions!$G$74/12)+IF(57=E9,D9*assumptions!$G$75,0),0) | BL9: =IF(AND(58>=E9,OR(F9="",58<=F9)),(D9*(1+assumptions!$G$76)^4/12*(1+assumptions!$G$70+assumptions!$G$71+IF(58>=assumptions!$G$73,assumptions!$G$72,0))+assumptions!$G$74/12)+IF(58=E9,D9*assumptions!$G$75,0),0) | BM9: =IF(AND(59>=E9,OR(F9="",59<=F9)),(D9*(1+assumptions!$G$76)^4/12*(1+assumptions!$G$70+assumptions!$G$71+IF(59>=assumptions!$G$73,assumptions!$G$72,0))+assumptions!$G$74/12)+IF(59=E9,D9*assumptions!$G$75,0),0) | BN9: =IF(AND(60>=E9,OR(F9="",60<=F9)),(D9*(1+assumptions!$G$76)^4/12*(1+assumptions!$G$70+assumptions!$G$71+IF(60>=assumptions!$G$73,assumptions!$G$72,0))+assumptions!$G$74/12)+IF(60=E9,D9*assumptions!$G$75,0),0)
A10: 7 | B10: Senior mobile engineer (RN) | C10: eng | D10: 95000 | E10: 4 | G10: =IF(AND(1>=E10,OR(F10="",1<=F10)),(D10*(1+assumptions!$G$76)^0/12*(1+assumptions!$G$70+assumptions!$G$71+IF(1>=assumptions!$G$73,assumptions!$G$72,0))+assumptions!$G$74/12)+IF(1=E10,D10*assumptions!$G$75,0),0) | H10: =IF(AND(2>=E10,OR(F10="",2<=F10)),(D10*(1+assumptions!$G$76)^0/12*(1+assumptions!$G$70+assumptions!$G$71+IF(2>=assumptions!$G$73,assumptions!$G$72,0))+assumptions!$G$74/12)+IF(2=E10,D10*assumptions!$G$75,0),0) | I10: =IF(AND(3>=E10,OR(F10="",3<=F10)),(D10*(1+assumptions!$G$76)^0/12*(1+assumptions!$G$70+assumptions!$G$71+IF(3>=assumptions!$G$73,assumptions!$G$72,0))+assumptions!$G$74/12)+IF(3=E10,D10*assumptions!$G$75,0),0) | J10: =IF(AND(4>=E10,OR(F10="",4<=F10)),(D10*(1+assumptions!$G$76)^0/12*(1+assumptions!$G$70+assumptions!$G$71+IF(4>=assumptions!$G$73,assumptions!$G$72,0))+assumptions!$G$74/12)+IF(4=E10,D10*assumptions!$G$75,0),0) | K10: =IF(AND(5>=E10,OR(F10="",5<=F10)),(D10*(1+assumptions!$G$76)^0/12*(1+assumptions!$G$70+assumptions!$G$71+IF(5>=assumptions!$G$73,assumptions!$G$72,0))+assumptions!$G$74/12)+IF(5=E10,D10*assumptions!$G$75,0),0) | L10: =IF(AND(6>=E10,OR(F10="",6<=F10)),(D10*(1+assumptions!$G$76)^0/12*(1+assumptions!$G$70+assumptions!$G$71+IF(6>=assumptions!$G$73,assumptions!$G$72,0))+assumptions!$G$74/12)+IF(6=E10,D10*assumptions!$G$75,0),0) | M10: =IF(AND(7>=E10,OR(F10="",7<=F10)),(D10*(1+assumptions!$G$76)^0/12*(1+assumptions!$G$70+assumptions!$G$71+IF(7>=assumptions!$G$73,assumptions!$G$72,0))+assumptions!$G$74/12)+IF(7=E10,D10*assumptions!$G$75,0),0) | N10: =IF(AND(8>=E10,OR(F10="",8<=F10)),(D10*(1+assumptions!$G$76)^0/12*(1+assumptions!$G$70+assumptions!$G$71+IF(8>=assumptions!$G$73,assumptions!$G$72,0))+assumptions!$G$74/12)+IF(8=E10,D10*assumptions!$G$75,0),0) | O10: =IF(AND(9>=E10,OR(F10="",9<=F10)),(D10*(1+assumptions!$G$76)^0/12*(1+assumptions!$G$70+assumptions!$G$71+IF(9>=assumptions!$G$73,assumptions!$G$72,0))+assumptions!$G$74/12)+IF(9=E10,D10*assumptions!$G$75,0),0) | P10: =IF(AND(10>=E10,OR(F10="",10<=F10)),(D10*(1+assumptions!$G$76)^0/12*(1+assumptions!$G$70+assumptions!$G$71+IF(10>=assumptions!$G$73,assumptions!$G$72,0))+assumptions!$G$74/12)+IF(10=E10,D10*assumptions!$G$75,0),0) | Q10: =IF(AND(11>=E10,OR(F10="",11<=F10)),(D10*(1+assumptions!$G$76)^0/12*(1+assumptions!$G$70+assumptions!$G$71+IF(11>=assumptions!$G$73,assumptions!$G$72,0))+assumptions!$G$74/12)+IF(11=E10,D10*assumptions!$G$75,0),0) | R10: =IF(AND(12>=E10,OR(F10="",12<=F10)),(D10*(1+assumptions!$G$76)^0/12*(1+assumptions!$G$70+assumptions!$G$71+IF(12>=assumptions!$G$73,assumptions!$G$72,0))+assumptions!$G$74/12)+IF(12=E10,D10*assumptions!$G$75,0),0) | S10: =IF(AND(13>=E10,OR(F10="",13<=F10)),(D10*(1+assumptions!$G$76)^1/12*(1+assumptions!$G$70+assumptions!$G$71+IF(13>=assumptions!$G$73,assumptions!$G$72,0))+assumptions!$G$74/12)+IF(13=E10,D10*assumptions!$G$75,0),0) | T10: =IF(AND(14>=E10,OR(F10="",14<=F10)),(D10*(1+assumptions!$G$76)^1/12*(1+assumptions!$G$70+assumptions!$G$71+IF(14>=assumptions!$G$73,assumptions!$G$72,0))+assumptions!$G$74/12)+IF(14=E10,D10*assumptions!$G$75,0),0) | U10: =IF(AND(15>=E10,OR(F10="",15<=F10)),(D10*(1+assumptions!$G$76)^1/12*(1+assumptions!$G$70+assumptions!$G$71+IF(15>=assumptions!$G$73,assumptions!$G$72,0))+assumptions!$G$74/12)+IF(15=E10,D10*assumptions!$G$75,0),0) | V10: =IF(AND(16>=E10,OR(F10="",16<=F10)),(D10*(1+assumptions!$G$76)^1/12*(1+assumptions!$G$70+assumptions!$G$71+IF(16>=assumptions!$G$73,assumptions!$G$72,0))+assumptions!$G$74/12)+IF(16=E10,D10*assumptions!$G$75,0),0) | W10: =IF(AND(17>=E10,OR(F10="",17<=F10)),(D10*(1+assumptions!$G$76)^1/12*(1+assumptions!$G$70+assumptions!$G$71+IF(17>=assumptions!$G$73,assumptions!$G$72,0))+assumptions!$G$74/12)+IF(17=E10,D10*assumptions!$G$75,0),0) | X10: =IF(AND(18>=E10,OR(F10="",18<=F10)),(D10*(1+assumptions!$G$76)^1/12*(1+assumptions!$G$70+assumptions!$G$71+IF(18>=assumptions!$G$73,assumptions!$G$72,0))+assumptions!$G$74/12)+IF(18=E10,D10*assumptions!$G$75,0),0) | Y10: =IF(AND(19>=E10,OR(F10="",19<=F10)),(D10*(1+assumptions!$G$76)^1/12*(1+assumptions!$G$70+assumptions!$G$71+IF(19>=assumptions!$G$73,assumptions!$G$72,0))+assumptions!$G$74/12)+IF(19=E10,D10*assumptions!$G$75,0),0) | Z10: =IF(AND(20>=E10,OR(F10="",20<=F10)),(D10*(1+assumptions!$G$76)^1/12*(1+assumptions!$G$70+assumptions!$G$71+IF(20>=assumptions!$G$73,assumptions!$G$72,0))+assumptions!$G$74/12)+IF(20=E10,D10*assumptions!$G$75,0),0) | AA10: =IF(AND(21>=E10,OR(F10="",21<=F10)),(D10*(1+assumptions!$G$76)^1/12*(1+assumptions!$G$70+assumptions!$G$71+IF(21>=assumptions!$G$73,assumptions!$G$72,0))+assumptions!$G$74/12)+IF(21=E10,D10*assumptions!$G$75,0),0) | AB10: =IF(AND(22>=E10,OR(F10="",22<=F10)),(D10*(1+assumptions!$G$76)^1/12*(1+assumptions!$G$70+assumptions!$G$71+IF(22>=assumptions!$G$73,assumptions!$G$72,0))+assumptions!$G$74/12)+IF(22=E10,D10*assumptions!$G$75,0),0) | AC10: =IF(AND(23>=E10,OR(F10="",23<=F10)),(D10*(1+assumptions!$G$76)^1/12*(1+assumptions!$G$70+assumptions!$G$71+IF(23>=assumptions!$G$73,assumptions!$G$72,0))+assumptions!$G$74/12)+IF(23=E10,D10*assumptions!$G$75,0),0) | AD10: =IF(AND(24>=E10,OR(F10="",24<=F10)),(D10*(1+assumptions!$G$76)^1/12*(1+assumptions!$G$70+assumptions!$G$71+IF(24>=assumptions!$G$73,assumptions!$G$72,0))+assumptions!$G$74/12)+IF(24=E10,D10*assumptions!$G$75,0),0) | AE10: =IF(AND(25>=E10,OR(F10="",25<=F10)),(D10*(1+assumptions!$G$76)^2/12*(1+assumptions!$G$70+assumptions!$G$71+IF(25>=assumptions!$G$73,assumptions!$G$72,0))+assumptions!$G$74/12)+IF(25=E10,D10*assumptions!$G$75,0),0) | AF10: =IF(AND(26>=E10,OR(F10="",26<=F10)),(D10*(1+assumptions!$G$76)^2/12*(1+assumptions!$G$70+assumptions!$G$71+IF(26>=assumptions!$G$73,assumptions!$G$72,0))+assumptions!$G$74/12)+IF(26=E10,D10*assumptions!$G$75,0),0) | AG10: =IF(AND(27>=E10,OR(F10="",27<=F10)),(D10*(1+assumptions!$G$76)^2/12*(1+assumptions!$G$70+assumptions!$G$71+IF(27>=assumptions!$G$73,assumptions!$G$72,0))+assumptions!$G$74/12)+IF(27=E10,D10*assumptions!$G$75,0),0) | AH10: =IF(AND(28>=E10,OR(F10="",28<=F10)),(D10*(1+assumptions!$G$76)^2/12*(1+assumptions!$G$70+assumptions!$G$71+IF(28>=assumptions!$G$73,assumptions!$G$72,0))+assumptions!$G$74/12)+IF(28=E10,D10*assumptions!$G$75,0),0) | AI10: =IF(AND(29>=E10,OR(F10="",29<=F10)),(D10*(1+assumptions!$G$76)^2/12*(1+assumptions!$G$70+assumptions!$G$71+IF(29>=assumptions!$G$73,assumptions!$G$72,0))+assumptions!$G$74/12)+IF(29=E10,D10*assumptions!$G$75,0),0) | AJ10: =IF(AND(30>=E10,OR(F10="",30<=F10)),(D10*(1+assumptions!$G$76)^2/12*(1+assumptions!$G$70+assumptions!$G$71+IF(30>=assumptions!$G$73,assumptions!$G$72,0))+assumptions!$G$74/12)+IF(30=E10,D10*assumptions!$G$75,0),0) | AK10: =IF(AND(31>=E10,OR(F10="",31<=F10)),(D10*(1+assumptions!$G$76)^2/12*(1+assumptions!$G$70+assumptions!$G$71+IF(31>=assumptions!$G$73,assumptions!$G$72,0))+assumptions!$G$74/12)+IF(31=E10,D10*assumptions!$G$75,0),0) | AL10: =IF(AND(32>=E10,OR(F10="",32<=F10)),(D10*(1+assumptions!$G$76)^2/12*(1+assumptions!$G$70+assumptions!$G$71+IF(32>=assumptions!$G$73,assumptions!$G$72,0))+assumptions!$G$74/12)+IF(32=E10,D10*assumptions!$G$75,0),0) | AM10: =IF(AND(33>=E10,OR(F10="",33<=F10)),(D10*(1+assumptions!$G$76)^2/12*(1+assumptions!$G$70+assumptions!$G$71+IF(33>=assumptions!$G$73,assumptions!$G$72,0))+assumptions!$G$74/12)+IF(33=E10,D10*assumptions!$G$75,0),0) | AN10: =IF(AND(34>=E10,OR(F10="",34<=F10)),(D10*(1+assumptions!$G$76)^2/12*(1+assumptions!$G$70+assumptions!$G$71+IF(34>=assumptions!$G$73,assumptions!$G$72,0))+assumptions!$G$74/12)+IF(34=E10,D10*assumptions!$G$75,0),0) | AO10: =IF(AND(35>=E10,OR(F10="",35<=F10)),(D10*(1+assumptions!$G$76)^2/12*(1+assumptions!$G$70+assumptions!$G$71+IF(35>=assumptions!$G$73,assumptions!$G$72,0))+assumptions!$G$74/12)+IF(35=E10,D10*assumptions!$G$75,0),0) | AP10: =IF(AND(36>=E10,OR(F10="",36<=F10)),(D10*(1+assumptions!$G$76)^2/12*(1+assumptions!$G$70+assumptions!$G$71+IF(36>=assumptions!$G$73,assumptions!$G$72,0))+assumptions!$G$74/12)+IF(36=E10,D10*assumptions!$G$75,0),0) | AQ10: =IF(AND(37>=E10,OR(F10="",37<=F10)),(D10*(1+assumptions!$G$76)^3/12*(1+assumptions!$G$70+assumptions!$G$71+IF(37>=assumptions!$G$73,assumptions!$G$72,0))+assumptions!$G$74/12)+IF(37=E10,D10*assumptions!$G$75,0),0) | AR10: =IF(AND(38>=E10,OR(F10="",38<=F10)),(D10*(1+assumptions!$G$76)^3/12*(1+assumptions!$G$70+assumptions!$G$71+IF(38>=assumptions!$G$73,assumptions!$G$72,0))+assumptions!$G$74/12)+IF(38=E10,D10*assumptions!$G$75,0),0) | AS10: =IF(AND(39>=E10,OR(F10="",39<=F10)),(D10*(1+assumptions!$G$76)^3/12*(1+assumptions!$G$70+assumptions!$G$71+IF(39>=assumptions!$G$73,assumptions!$G$72,0))+assumptions!$G$74/12)+IF(39=E10,D10*assumptions!$G$75,0),0) | AT10: =IF(AND(40>=E10,OR(F10="",40<=F10)),(D10*(1+assumptions!$G$76)^3/12*(1+assumptions!$G$70+assumptions!$G$71+IF(40>=assumptions!$G$73,assumptions!$G$72,0))+assumptions!$G$74/12)+IF(40=E10,D10*assumptions!$G$75,0),0) | AU10: =IF(AND(41>=E10,OR(F10="",41<=F10)),(D10*(1+assumptions!$G$76)^3/12*(1+assumptions!$G$70+assumptions!$G$71+IF(41>=assumptions!$G$73,assumptions!$G$72,0))+assumptions!$G$74/12)+IF(41=E10,D10*assumptions!$G$75,0),0) | AV10: =IF(AND(42>=E10,OR(F10="",42<=F10)),(D10*(1+assumptions!$G$76)^3/12*(1+assumptions!$G$70+assumptions!$G$71+IF(42>=assumptions!$G$73,assumptions!$G$72,0))+assumptions!$G$74/12)+IF(42=E10,D10*assumptions!$G$75,0),0) | AW10: =IF(AND(43>=E10,OR(F10="",43<=F10)),(D10*(1+assumptions!$G$76)^3/12*(1+assumptions!$G$70+assumptions!$G$71+IF(43>=assumptions!$G$73,assumptions!$G$72,0))+assumptions!$G$74/12)+IF(43=E10,D10*assumptions!$G$75,0),0) | AX10: =IF(AND(44>=E10,OR(F10="",44<=F10)),(D10*(1+assumptions!$G$76)^3/12*(1+assumptions!$G$70+assumptions!$G$71+IF(44>=assumptions!$G$73,assumptions!$G$72,0))+assumptions!$G$74/12)+IF(44=E10,D10*assumptions!$G$75,0),0) | AY10: =IF(AND(45>=E10,OR(F10="",45<=F10)),(D10*(1+assumptions!$G$76)^3/12*(1+assumptions!$G$70+assumptions!$G$71+IF(45>=assumptions!$G$73,assumptions!$G$72,0))+assumptions!$G$74/12)+IF(45=E10,D10*assumptions!$G$75,0),0) | AZ10: =IF(AND(46>=E10,OR(F10="",46<=F10)),(D10*(1+assumptions!$G$76)^3/12*(1+assumptions!$G$70+assumptions!$G$71+IF(46>=assumptions!$G$73,assumptions!$G$72,0))+assumptions!$G$74/12)+IF(46=E10,D10*assumptions!$G$75,0),0) | BA10: =IF(AND(47>=E10,OR(F10="",47<=F10)),(D10*(1+assumptions!$G$76)^3/12*(1+assumptions!$G$70+assumptions!$G$71+IF(47>=assumptions!$G$73,assumptions!$G$72,0))+assumptions!$G$74/12)+IF(47=E10,D10*assumptions!$G$75,0),0) | BB10: =IF(AND(48>=E10,OR(F10="",48<=F10)),(D10*(1+assumptions!$G$76)^3/12*(1+assumptions!$G$70+assumptions!$G$71+IF(48>=assumptions!$G$73,assumptions!$G$72,0))+assumptions!$G$74/12)+IF(48=E10,D10*assumptions!$G$75,0),0) | BC10: =IF(AND(49>=E10,OR(F10="",49<=F10)),(D10*(1+assumptions!$G$76)^4/12*(1+assumptions!$G$70+assumptions!$G$71+IF(49>=assumptions!$G$73,assumptions!$G$72,0))+assumptions!$G$74/12)+IF(49=E10,D10*assumptions!$G$75,0),0) | BD10: =IF(AND(50>=E10,OR(F10="",50<=F10)),(D10*(1+assumptions!$G$76)^4/12*(1+assumptions!$G$70+assumptions!$G$71+IF(50>=assumptions!$G$73,assumptions!$G$72,0))+assumptions!$G$74/12)+IF(50=E10,D10*assumptions!$G$75,0),0) | BE10: =IF(AND(51>=E10,OR(F10="",51<=F10)),(D10*(1+assumptions!$G$76)^4/12*(1+assumptions!$G$70+assumptions!$G$71+IF(51>=assumptions!$G$73,assumptions!$G$72,0))+assumptions!$G$74/12)+IF(51=E10,D10*assumptions!$G$75,0),0) | BF10: =IF(AND(52>=E10,OR(F10="",52<=F10)),(D10*(1+assumptions!$G$76)^4/12*(1+assumptions!$G$70+assumptions!$G$71+IF(52>=assumptions!$G$73,assumptions!$G$72,0))+assumptions!$G$74/12)+IF(52=E10,D10*assumptions!$G$75,0),0) | BG10: =IF(AND(53>=E10,OR(F10="",53<=F10)),(D10*(1+assumptions!$G$76)^4/12*(1+assumptions!$G$70+assumptions!$G$71+IF(53>=assumptions!$G$73,assumptions!$G$72,0))+assumptions!$G$74/12)+IF(53=E10,D10*assumptions!$G$75,0),0) | BH10: =IF(AND(54>=E10,OR(F10="",54<=F10)),(D10*(1+assumptions!$G$76)^4/12*(1+assumptions!$G$70+assumptions!$G$71+IF(54>=assumptions!$G$73,assumptions!$G$72,0))+assumptions!$G$74/12)+IF(54=E10,D10*assumptions!$G$75,0),0) | BI10: =IF(AND(55>=E10,OR(F10="",55<=F10)),(D10*(1+assumptions!$G$76)^4/12*(1+assumptions!$G$70+assumptions!$G$71+IF(55>=assumptions!$G$73,assumptions!$G$72,0))+assumptions!$G$74/12)+IF(55=E10,D10*assumptions!$G$75,0),0) | BJ10: =IF(AND(56>=E10,OR(F10="",56<=F10)),(D10*(1+assumptions!$G$76)^4/12*(1+assumptions!$G$70+assumptions!$G$71+IF(56>=assumptions!$G$73,assumptions!$G$72,0))+assumptions!$G$74/12)+IF(56=E10,D10*assumptions!$G$75,0),0) | BK10: =IF(AND(57>=E10,OR(F10="",57<=F10)),(D10*(1+assumptions!$G$76)^4/12*(1+assumptions!$G$70+assumptions!$G$71+IF(57>=assumptions!$G$73,assumptions!$G$72,0))+assumptions!$G$74/12)+IF(57=E10,D10*assumptions!$G$75,0),0) | BL10: =IF(AND(58>=E10,OR(F10="",58<=F10)),(D10*(1+assumptions!$G$76)^4/12*(1+assumptions!$G$70+assumptions!$G$71+IF(58>=assumptions!$G$73,assumptions!$G$72,0))+assumptions!$G$74/12)+IF(58=E10,D10*assumptions!$G$75,0),0) | BM10: =IF(AND(59>=E10,OR(F10="",59<=F10)),(D10*(1+assumptions!$G$76)^4/12*(1+assumptions!$G$70+assumptions!$G$71+IF(59>=assumptions!$G$73,assumptions!$G$72,0))+assumptions!$G$74/12)+IF(59=E10,D10*assumptions!$G$75,0),0) | BN10: =IF(AND(60>=E10,OR(F10="",60<=F10)),(D10*(1+assumptions!$G$76)^4/12*(1+assumptions!$G$70+assumptions!$G$71+IF(60>=assumptions!$G$73,assumptions!$G$72,0))+assumptions!$G$74/12)+IF(60=E10,D10*assumptions!$G$75,0),0)
A11: 8 | B11: Creator partnerships manager | C11: growth | D11: 55000 | E11: 4 | G11: =IF(AND(1>=E11,OR(F11="",1<=F11)),(D11*(1+assumptions!$G$76)^0/12*(1+assumptions!$G$70+assumptions!$G$71+IF(1>=assumptions!$G$73,assumptions!$G$72,0))+assumptions!$G$74/12)+IF(1=E11,D11*assumptions!$G$75,0),0) | H11: =IF(AND(2>=E11,OR(F11="",2<=F11)),(D11*(1+assumptions!$G$76)^0/12*(1+assumptions!$G$70+assumptions!$G$71+IF(2>=assumptions!$G$73,assumptions!$G$72,0))+assumptions!$G$74/12)+IF(2=E11,D11*assumptions!$G$75,0),0) | I11: =IF(AND(3>=E11,OR(F11="",3<=F11)),(D11*(1+assumptions!$G$76)^0/12*(1+assumptions!$G$70+assumptions!$G$71+IF(3>=assumptions!$G$73,assumptions!$G$72,0))+assumptions!$G$74/12)+IF(3=E11,D11*assumptions!$G$75,0),0) | J11: =IF(AND(4>=E11,OR(F11="",4<=F11)),(D11*(1+assumptions!$G$76)^0/12*(1+assumptions!$G$70+assumptions!$G$71+IF(4>=assumptions!$G$73,assumptions!$G$72,0))+assumptions!$G$74/12)+IF(4=E11,D11*assumptions!$G$75,0),0) | K11: =IF(AND(5>=E11,OR(F11="",5<=F11)),(D11*(1+assumptions!$G$76)^0/12*(1+assumptions!$G$70+assumptions!$G$71+IF(5>=assumptions!$G$73,assumptions!$G$72,0))+assumptions!$G$74/12)+IF(5=E11,D11*assumptions!$G$75,0),0) | L11: =IF(AND(6>=E11,OR(F11="",6<=F11)),(D11*(1+assumptions!$G$76)^0/12*(1+assumptions!$G$70+assumptions!$G$71+IF(6>=assumptions!$G$73,assumptions!$G$72,0))+assumptions!$G$74/12)+IF(6=E11,D11*assumptions!$G$75,0),0) | M11: =IF(AND(7>=E11,OR(F11="",7<=F11)),(D11*(1+assumptions!$G$76)^0/12*(1+assumptions!$G$70+assumptions!$G$71+IF(7>=assumptions!$G$73,assumptions!$G$72,0))+assumptions!$G$74/12)+IF(7=E11,D11*assumptions!$G$75,0),0) | N11: =IF(AND(8>=E11,OR(F11="",8<=F11)),(D11*(1+assumptions!$G$76)^0/12*(1+assumptions!$G$70+assumptions!$G$71+IF(8>=assumptions!$G$73,assumptions!$G$72,0))+assumptions!$G$74/12)+IF(8=E11,D11*assumptions!$G$75,0),0) | O11: =IF(AND(9>=E11,OR(F11="",9<=F11)),(D11*(1+assumptions!$G$76)^0/12*(1+assumptions!$G$70+assumptions!$G$71+IF(9>=assumptions!$G$73,assumptions!$G$72,0))+assumptions!$G$74/12)+IF(9=E11,D11*assumptions!$G$75,0),0) | P11: =IF(AND(10>=E11,OR(F11="",10<=F11)),(D11*(1+assumptions!$G$76)^0/12*(1+assumptions!$G$70+assumptions!$G$71+IF(10>=assumptions!$G$73,assumptions!$G$72,0))+assumptions!$G$74/12)+IF(10=E11,D11*assumptions!$G$75,0),0) | Q11: =IF(AND(11>=E11,OR(F11="",11<=F11)),(D11*(1+assumptions!$G$76)^0/12*(1+assumptions!$G$70+assumptions!$G$71+IF(11>=assumptions!$G$73,assumptions!$G$72,0))+assumptions!$G$74/12)+IF(11=E11,D11*assumptions!$G$75,0),0) | R11: =IF(AND(12>=E11,OR(F11="",12<=F11)),(D11*(1+assumptions!$G$76)^0/12*(1+assumptions!$G$70+assumptions!$G$71+IF(12>=assumptions!$G$73,assumptions!$G$72,0))+assumptions!$G$74/12)+IF(12=E11,D11*assumptions!$G$75,0),0) | S11: =IF(AND(13>=E11,OR(F11="",13<=F11)),(D11*(1+assumptions!$G$76)^1/12*(1+assumptions!$G$70+assumptions!$G$71+IF(13>=assumptions!$G$73,assumptions!$G$72,0))+assumptions!$G$74/12)+IF(13=E11,D11*assumptions!$G$75,0),0) | T11: =IF(AND(14>=E11,OR(F11="",14<=F11)),(D11*(1+assumptions!$G$76)^1/12*(1+assumptions!$G$70+assumptions!$G$71+IF(14>=assumptions!$G$73,assumptions!$G$72,0))+assumptions!$G$74/12)+IF(14=E11,D11*assumptions!$G$75,0),0) | U11: =IF(AND(15>=E11,OR(F11="",15<=F11)),(D11*(1+assumptions!$G$76)^1/12*(1+assumptions!$G$70+assumptions!$G$71+IF(15>=assumptions!$G$73,assumptions!$G$72,0))+assumptions!$G$74/12)+IF(15=E11,D11*assumptions!$G$75,0),0) | V11: =IF(AND(16>=E11,OR(F11="",16<=F11)),(D11*(1+assumptions!$G$76)^1/12*(1+assumptions!$G$70+assumptions!$G$71+IF(16>=assumptions!$G$73,assumptions!$G$72,0))+assumptions!$G$74/12)+IF(16=E11,D11*assumptions!$G$75,0),0) | W11: =IF(AND(17>=E11,OR(F11="",17<=F11)),(D11*(1+assumptions!$G$76)^1/12*(1+assumptions!$G$70+assumptions!$G$71+IF(17>=assumptions!$G$73,assumptions!$G$72,0))+assumptions!$G$74/12)+IF(17=E11,D11*assumptions!$G$75,0),0) | X11: =IF(AND(18>=E11,OR(F11="",18<=F11)),(D11*(1+assumptions!$G$76)^1/12*(1+assumptions!$G$70+assumptions!$G$71+IF(18>=assumptions!$G$73,assumptions!$G$72,0))+assumptions!$G$74/12)+IF(18=E11,D11*assumptions!$G$75,0),0) | Y11: =IF(AND(19>=E11,OR(F11="",19<=F11)),(D11*(1+assumptions!$G$76)^1/12*(1+assumptions!$G$70+assumptions!$G$71+IF(19>=assumptions!$G$73,assumptions!$G$72,0))+assumptions!$G$74/12)+IF(19=E11,D11*assumptions!$G$75,0),0) | Z11: =IF(AND(20>=E11,OR(F11="",20<=F11)),(D11*(1+assumptions!$G$76)^1/12*(1+assumptions!$G$70+assumptions!$G$71+IF(20>=assumptions!$G$73,assumptions!$G$72,0))+assumptions!$G$74/12)+IF(20=E11,D11*assumptions!$G$75,0),0) | AA11: =IF(AND(21>=E11,OR(F11="",21<=F11)),(D11*(1+assumptions!$G$76)^1/12*(1+assumptions!$G$70+assumptions!$G$71+IF(21>=assumptions!$G$73,assumptions!$G$72,0))+assumptions!$G$74/12)+IF(21=E11,D11*assumptions!$G$75,0),0) | AB11: =IF(AND(22>=E11,OR(F11="",22<=F11)),(D11*(1+assumptions!$G$76)^1/12*(1+assumptions!$G$70+assumptions!$G$71+IF(22>=assumptions!$G$73,assumptions!$G$72,0))+assumptions!$G$74/12)+IF(22=E11,D11*assumptions!$G$75,0),0) | AC11: =IF(AND(23>=E11,OR(F11="",23<=F11)),(D11*(1+assumptions!$G$76)^1/12*(1+assumptions!$G$70+assumptions!$G$71+IF(23>=assumptions!$G$73,assumptions!$G$72,0))+assumptions!$G$74/12)+IF(23=E11,D11*assumptions!$G$75,0),0) | AD11: =IF(AND(24>=E11,OR(F11="",24<=F11)),(D11*(1+assumptions!$G$76)^1/12*(1+assumptions!$G$70+assumptions!$G$71+IF(24>=assumptions!$G$73,assumptions!$G$72,0))+assumptions!$G$74/12)+IF(24=E11,D11*assumptions!$G$75,0),0) | AE11: =IF(AND(25>=E11,OR(F11="",25<=F11)),(D11*(1+assumptions!$G$76)^2/12*(1+assumptions!$G$70+assumptions!$G$71+IF(25>=assumptions!$G$73,assumptions!$G$72,0))+assumptions!$G$74/12)+IF(25=E11,D11*assumptions!$G$75,0),0) | AF11: =IF(AND(26>=E11,OR(F11="",26<=F11)),(D11*(1+assumptions!$G$76)^2/12*(1+assumptions!$G$70+assumptions!$G$71+IF(26>=assumptions!$G$73,assumptions!$G$72,0))+assumptions!$G$74/12)+IF(26=E11,D11*assumptions!$G$75,0),0) | AG11: =IF(AND(27>=E11,OR(F11="",27<=F11)),(D11*(1+assumptions!$G$76)^2/12*(1+assumptions!$G$70+assumptions!$G$71+IF(27>=assumptions!$G$73,assumptions!$G$72,0))+assumptions!$G$74/12)+IF(27=E11,D11*assumptions!$G$75,0),0) | AH11: =IF(AND(28>=E11,OR(F11="",28<=F11)),(D11*(1+assumptions!$G$76)^2/12*(1+assumptions!$G$70+assumptions!$G$71+IF(28>=assumptions!$G$73,assumptions!$G$72,0))+assumptions!$G$74/12)+IF(28=E11,D11*assumptions!$G$75,0),0) | AI11: =IF(AND(29>=E11,OR(F11="",29<=F11)),(D11*(1+assumptions!$G$76)^2/12*(1+assumptions!$G$70+assumptions!$G$71+IF(29>=assumptions!$G$73,assumptions!$G$72,0))+assumptions!$G$74/12)+IF(29=E11,D11*assumptions!$G$75,0),0) | AJ11: =IF(AND(30>=E11,OR(F11="",30<=F11)),(D11*(1+assumptions!$G$76)^2/12*(1+assumptions!$G$70+assumptions!$G$71+IF(30>=assumptions!$G$73,assumptions!$G$72,0))+assumptions!$G$74/12)+IF(30=E11,D11*assumptions!$G$75,0),0) | AK11: =IF(AND(31>=E11,OR(F11="",31<=F11)),(D11*(1+assumptions!$G$76)^2/12*(1+assumptions!$G$70+assumptions!$G$71+IF(31>=assumptions!$G$73,assumptions!$G$72,0))+assumptions!$G$74/12)+IF(31=E11,D11*assumptions!$G$75,0),0) | AL11: =IF(AND(32>=E11,OR(F11="",32<=F11)),(D11*(1+assumptions!$G$76)^2/12*(1+assumptions!$G$70+assumptions!$G$71+IF(32>=assumptions!$G$73,assumptions!$G$72,0))+assumptions!$G$74/12)+IF(32=E11,D11*assumptions!$G$75,0),0) | AM11: =IF(AND(33>=E11,OR(F11="",33<=F11)),(D11*(1+assumptions!$G$76)^2/12*(1+assumptions!$G$70+assumptions!$G$71+IF(33>=assumptions!$G$73,assumptions!$G$72,0))+assumptions!$G$74/12)+IF(33=E11,D11*assumptions!$G$75,0),0) | AN11: =IF(AND(34>=E11,OR(F11="",34<=F11)),(D11*(1+assumptions!$G$76)^2/12*(1+assumptions!$G$70+assumptions!$G$71+IF(34>=assumptions!$G$73,assumptions!$G$72,0))+assumptions!$G$74/12)+IF(34=E11,D11*assumptions!$G$75,0),0) | AO11: =IF(AND(35>=E11,OR(F11="",35<=F11)),(D11*(1+assumptions!$G$76)^2/12*(1+assumptions!$G$70+assumptions!$G$71+IF(35>=assumptions!$G$73,assumptions!$G$72,0))+assumptions!$G$74/12)+IF(35=E11,D11*assumptions!$G$75,0),0) | AP11: =IF(AND(36>=E11,OR(F11="",36<=F11)),(D11*(1+assumptions!$G$76)^2/12*(1+assumptions!$G$70+assumptions!$G$71+IF(36>=assumptions!$G$73,assumptions!$G$72,0))+assumptions!$G$74/12)+IF(36=E11,D11*assumptions!$G$75,0),0) | AQ11: =IF(AND(37>=E11,OR(F11="",37<=F11)),(D11*(1+assumptions!$G$76)^3/12*(1+assumptions!$G$70+assumptions!$G$71+IF(37>=assumptions!$G$73,assumptions!$G$72,0))+assumptions!$G$74/12)+IF(37=E11,D11*assumptions!$G$75,0),0) | AR11: =IF(AND(38>=E11,OR(F11="",38<=F11)),(D11*(1+assumptions!$G$76)^3/12*(1+assumptions!$G$70+assumptions!$G$71+IF(38>=assumptions!$G$73,assumptions!$G$72,0))+assumptions!$G$74/12)+IF(38=E11,D11*assumptions!$G$75,0),0) | AS11: =IF(AND(39>=E11,OR(F11="",39<=F11)),(D11*(1+assumptions!$G$76)^3/12*(1+assumptions!$G$70+assumptions!$G$71+IF(39>=assumptions!$G$73,assumptions!$G$72,0))+assumptions!$G$74/12)+IF(39=E11,D11*assumptions!$G$75,0),0) | AT11: =IF(AND(40>=E11,OR(F11="",40<=F11)),(D11*(1+assumptions!$G$76)^3/12*(1+assumptions!$G$70+assumptions!$G$71+IF(40>=assumptions!$G$73,assumptions!$G$72,0))+assumptions!$G$74/12)+IF(40=E11,D11*assumptions!$G$75,0),0) | AU11: =IF(AND(41>=E11,OR(F11="",41<=F11)),(D11*(1+assumptions!$G$76)^3/12*(1+assumptions!$G$70+assumptions!$G$71+IF(41>=assumptions!$G$73,assumptions!$G$72,0))+assumptions!$G$74/12)+IF(41=E11,D11*assumptions!$G$75,0),0) | AV11: =IF(AND(42>=E11,OR(F11="",42<=F11)),(D11*(1+assumptions!$G$76)^3/12*(1+assumptions!$G$70+assumptions!$G$71+IF(42>=assumptions!$G$73,assumptions!$G$72,0))+assumptions!$G$74/12)+IF(42=E11,D11*assumptions!$G$75,0),0) | AW11: =IF(AND(43>=E11,OR(F11="",43<=F11)),(D11*(1+assumptions!$G$76)^3/12*(1+assumptions!$G$70+assumptions!$G$71+IF(43>=assumptions!$G$73,assumptions!$G$72,0))+assumptions!$G$74/12)+IF(43=E11,D11*assumptions!$G$75,0),0) | AX11: =IF(AND(44>=E11,OR(F11="",44<=F11)),(D11*(1+assumptions!$G$76)^3/12*(1+assumptions!$G$70+assumptions!$G$71+IF(44>=assumptions!$G$73,assumptions!$G$72,0))+assumptions!$G$74/12)+IF(44=E11,D11*assumptions!$G$75,0),0) | AY11: =IF(AND(45>=E11,OR(F11="",45<=F11)),(D11*(1+assumptions!$G$76)^3/12*(1+assumptions!$G$70+assumptions!$G$71+IF(45>=assumptions!$G$73,assumptions!$G$72,0))+assumptions!$G$74/12)+IF(45=E11,D11*assumptions!$G$75,0),0) | AZ11: =IF(AND(46>=E11,OR(F11="",46<=F11)),(D11*(1+assumptions!$G$76)^3/12*(1+assumptions!$G$70+assumptions!$G$71+IF(46>=assumptions!$G$73,assumptions!$G$72,0))+assumptions!$G$74/12)+IF(46=E11,D11*assumptions!$G$75,0),0) | BA11: =IF(AND(47>=E11,OR(F11="",47<=F11)),(D11*(1+assumptions!$G$76)^3/12*(1+assumptions!$G$70+assumptions!$G$71+IF(47>=assumptions!$G$73,assumptions!$G$72,0))+assumptions!$G$74/12)+IF(47=E11,D11*assumptions!$G$75,0),0) | BB11: =IF(AND(48>=E11,OR(F11="",48<=F11)),(D11*(1+assumptions!$G$76)^3/12*(1+assumptions!$G$70+assumptions!$G$71+IF(48>=assumptions!$G$73,assumptions!$G$72,0))+assumptions!$G$74/12)+IF(48=E11,D11*assumptions!$G$75,0),0) | BC11: =IF(AND(49>=E11,OR(F11="",49<=F11)),(D11*(1+assumptions!$G$76)^4/12*(1+assumptions!$G$70+assumptions!$G$71+IF(49>=assumptions!$G$73,assumptions!$G$72,0))+assumptions!$G$74/12)+IF(49=E11,D11*assumptions!$G$75,0),0) | BD11: =IF(AND(50>=E11,OR(F11="",50<=F11)),(D11*(1+assumptions!$G$76)^4/12*(1+assumptions!$G$70+assumptions!$G$71+IF(50>=assumptions!$G$73,assumptions!$G$72,0))+assumptions!$G$74/12)+IF(50=E11,D11*assumptions!$G$75,0),0) | BE11: =IF(AND(51>=E11,OR(F11="",51<=F11)),(D11*(1+assumptions!$G$76)^4/12*(1+assumptions!$G$70+assumptions!$G$71+IF(51>=assumptions!$G$73,assumptions!$G$72,0))+assumptions!$G$74/12)+IF(51=E11,D11*assumptions!$G$75,0),0) | BF11: =IF(AND(52>=E11,OR(F11="",52<=F11)),(D11*(1+assumptions!$G$76)^4/12*(1+assumptions!$G$70+assumptions!$G$71+IF(52>=assumptions!$G$73,assumptions!$G$72,0))+assumptions!$G$74/12)+IF(52=E11,D11*assumptions!$G$75,0),0) | BG11: =IF(AND(53>=E11,OR(F11="",53<=F11)),(D11*(1+assumptions!$G$76)^4/12*(1+assumptions!$G$70+assumptions!$G$71+IF(53>=assumptions!$G$73,assumptions!$G$72,0))+assumptions!$G$74/12)+IF(53=E11,D11*assumptions!$G$75,0),0) | BH11: =IF(AND(54>=E11,OR(F11="",54<=F11)),(D11*(1+assumptions!$G$76)^4/12*(1+assumptions!$G$70+assumptions!$G$71+IF(54>=assumptions!$G$73,assumptions!$G$72,0))+assumptions!$G$74/12)+IF(54=E11,D11*assumptions!$G$75,0),0) | BI11: =IF(AND(55>=E11,OR(F11="",55<=F11)),(D11*(1+assumptions!$G$76)^4/12*(1+assumptions!$G$70+assumptions!$G$71+IF(55>=assumptions!$G$73,assumptions!$G$72,0))+assumptions!$G$74/12)+IF(55=E11,D11*assumptions!$G$75,0),0) | BJ11: =IF(AND(56>=E11,OR(F11="",56<=F11)),(D11*(1+assumptions!$G$76)^4/12*(1+assumptions!$G$70+assumptions!$G$71+IF(56>=assumptions!$G$73,assumptions!$G$72,0))+assumptions!$G$74/12)+IF(56=E11,D11*assumptions!$G$75,0),0) | BK11: =IF(AND(57>=E11,OR(F11="",57<=F11)),(D11*(1+assumptions!$G$76)^4/12*(1+assumptions!$G$70+assumptions!$G$71+IF(57>=assumptions!$G$73,assumptions!$G$72,0))+assumptions!$G$74/12)+IF(57=E11,D11*assumptions!$G$75,0),0) | BL11: =IF(AND(58>=E11,OR(F11="",58<=F11)),(D11*(1+assumptions!$G$76)^4/12*(1+assumptions!$G$70+assumptions!$G$71+IF(58>=assumptions!$G$73,assumptions!$G$72,0))+assumptions!$G$74/12)+IF(58=E11,D11*assumptions!$G$75,0),0) | BM11: =IF(AND(59>=E11,OR(F11="",59<=F11)),(D11*(1+assumptions!$G$76)^4/12*(1+assumptions!$G$70+assumptions!$G$71+IF(59>=assumptions!$G$73,assumptions!$G$72,0))+assumptions!$G$74/12)+IF(59=E11,D11*assumptions!$G$75,0),0) | BN11: =IF(AND(60>=E11,OR(F11="",60<=F11)),(D11*(1+assumptions!$G$76)^4/12*(1+assumptions!$G$70+assumptions!$G$71+IF(60>=assumptions!$G$73,assumptions!$G$72,0))+assumptions!$G$74/12)+IF(60=E11,D11*assumptions!$G$75,0),0)
A12: 9 | B12: Head of Operator Supply | C12: supply | D12: 80000 | E12: 6 | G12: =IF(AND(1>=E12,OR(F12="",1<=F12)),(D12*(1+assumptions!$G$76)^0/12*(1+assumptions!$G$70+assumptions!$G$71+IF(1>=assumptions!$G$73,assumptions!$G$72,0))+assumptions!$G$74/12)+IF(1=E12,D12*assumptions!$G$75,0),0) | H12: =IF(AND(2>=E12,OR(F12="",2<=F12)),(D12*(1+assumptions!$G$76)^0/12*(1+assumptions!$G$70+assumptions!$G$71+IF(2>=assumptions!$G$73,assumptions!$G$72,0))+assumptions!$G$74/12)+IF(2=E12,D12*assumptions!$G$75,0),0) | I12: =IF(AND(3>=E12,OR(F12="",3<=F12)),(D12*(1+assumptions!$G$76)^0/12*(1+assumptions!$G$70+assumptions!$G$71+IF(3>=assumptions!$G$73,assumptions!$G$72,0))+assumptions!$G$74/12)+IF(3=E12,D12*assumptions!$G$75,0),0) | J12: =IF(AND(4>=E12,OR(F12="",4<=F12)),(D12*(1+assumptions!$G$76)^0/12*(1+assumptions!$G$70+assumptions!$G$71+IF(4>=assumptions!$G$73,assumptions!$G$72,0))+assumptions!$G$74/12)+IF(4=E12,D12*assumptions!$G$75,0),0) | K12: =IF(AND(5>=E12,OR(F12="",5<=F12)),(D12*(1+assumptions!$G$76)^0/12*(1+assumptions!$G$70+assumptions!$G$71+IF(5>=assumptions!$G$73,assumptions!$G$72,0))+assumptions!$G$74/12)+IF(5=E12,D12*assumptions!$G$75,0),0) | L12: =IF(AND(6>=E12,OR(F12="",6<=F12)),(D12*(1+assumptions!$G$76)^0/12*(1+assumptions!$G$70+assumptions!$G$71+IF(6>=assumptions!$G$73,assumptions!$G$72,0))+assumptions!$G$74/12)+IF(6=E12,D12*assumptions!$G$75,0),0) | M12: =IF(AND(7>=E12,OR(F12="",7<=F12)),(D12*(1+assumptions!$G$76)^0/12*(1+assumptions!$G$70+assumptions!$G$71+IF(7>=assumptions!$G$73,assumptions!$G$72,0))+assumptions!$G$74/12)+IF(7=E12,D12*assumptions!$G$75,0),0) | N12: =IF(AND(8>=E12,OR(F12="",8<=F12)),(D12*(1+assumptions!$G$76)^0/12*(1+assumptions!$G$70+assumptions!$G$71+IF(8>=assumptions!$G$73,assumptions!$G$72,0))+assumptions!$G$74/12)+IF(8=E12,D12*assumptions!$G$75,0),0) | O12: =IF(AND(9>=E12,OR(F12="",9<=F12)),(D12*(1+assumptions!$G$76)^0/12*(1+assumptions!$G$70+assumptions!$G$71+IF(9>=assumptions!$G$73,assumptions!$G$72,0))+assumptions!$G$74/12)+IF(9=E12,D12*assumptions!$G$75,0),0) | P12: =IF(AND(10>=E12,OR(F12="",10<=F12)),(D12*(1+assumptions!$G$76)^0/12*(1+assumptions!$G$70+assumptions!$G$71+IF(10>=assumptions!$G$73,assumptions!$G$72,0))+assumptions!$G$74/12)+IF(10=E12,D12*assumptions!$G$75,0),0) | Q12: =IF(AND(11>=E12,OR(F12="",11<=F12)),(D12*(1+assumptions!$G$76)^0/12*(1+assumptions!$G$70+assumptions!$G$71+IF(11>=assumptions!$G$73,assumptions!$G$72,0))+assumptions!$G$74/12)+IF(11=E12,D12*assumptions!$G$75,0),0) | R12: =IF(AND(12>=E12,OR(F12="",12<=F12)),(D12*(1+assumptions!$G$76)^0/12*(1+assumptions!$G$70+assumptions!$G$71+IF(12>=assumptions!$G$73,assumptions!$G$72,0))+assumptions!$G$74/12)+IF(12=E12,D12*assumptions!$G$75,0),0) | S12: =IF(AND(13>=E12,OR(F12="",13<=F12)),(D12*(1+assumptions!$G$76)^1/12*(1+assumptions!$G$70+assumptions!$G$71+IF(13>=assumptions!$G$73,assumptions!$G$72,0))+assumptions!$G$74/12)+IF(13=E12,D12*assumptions!$G$75,0),0) | T12: =IF(AND(14>=E12,OR(F12="",14<=F12)),(D12*(1+assumptions!$G$76)^1/12*(1+assumptions!$G$70+assumptions!$G$71+IF(14>=assumptions!$G$73,assumptions!$G$72,0))+assumptions!$G$74/12)+IF(14=E12,D12*assumptions!$G$75,0),0) | U12: =IF(AND(15>=E12,OR(F12="",15<=F12)),(D12*(1+assumptions!$G$76)^1/12*(1+assumptions!$G$70+assumptions!$G$71+IF(15>=assumptions!$G$73,assumptions!$G$72,0))+assumptions!$G$74/12)+IF(15=E12,D12*assumptions!$G$75,0),0) | V12: =IF(AND(16>=E12,OR(F12="",16<=F12)),(D12*(1+assumptions!$G$76)^1/12*(1+assumptions!$G$70+assumptions!$G$71+IF(16>=assumptions!$G$73,assumptions!$G$72,0))+assumptions!$G$74/12)+IF(16=E12,D12*assumptions!$G$75,0),0) | W12: =IF(AND(17>=E12,OR(F12="",17<=F12)),(D12*(1+assumptions!$G$76)^1/12*(1+assumptions!$G$70+assumptions!$G$71+IF(17>=assumptions!$G$73,assumptions!$G$72,0))+assumptions!$G$74/12)+IF(17=E12,D12*assumptions!$G$75,0),0) | X12: =IF(AND(18>=E12,OR(F12="",18<=F12)),(D12*(1+assumptions!$G$76)^1/12*(1+assumptions!$G$70+assumptions!$G$71+IF(18>=assumptions!$G$73,assumptions!$G$72,0))+assumptions!$G$74/12)+IF(18=E12,D12*assumptions!$G$75,0),0) | Y12: =IF(AND(19>=E12,OR(F12="",19<=F12)),(D12*(1+assumptions!$G$76)^1/12*(1+assumptions!$G$70+assumptions!$G$71+IF(19>=assumptions!$G$73,assumptions!$G$72,0))+assumptions!$G$74/12)+IF(19=E12,D12*assumptions!$G$75,0),0) | Z12: =IF(AND(20>=E12,OR(F12="",20<=F12)),(D12*(1+assumptions!$G$76)^1/12*(1+assumptions!$G$70+assumptions!$G$71+IF(20>=assumptions!$G$73,assumptions!$G$72,0))+assumptions!$G$74/12)+IF(20=E12,D12*assumptions!$G$75,0),0) | AA12: =IF(AND(21>=E12,OR(F12="",21<=F12)),(D12*(1+assumptions!$G$76)^1/12*(1+assumptions!$G$70+assumptions!$G$71+IF(21>=assumptions!$G$73,assumptions!$G$72,0))+assumptions!$G$74/12)+IF(21=E12,D12*assumptions!$G$75,0),0) | AB12: =IF(AND(22>=E12,OR(F12="",22<=F12)),(D12*(1+assumptions!$G$76)^1/12*(1+assumptions!$G$70+assumptions!$G$71+IF(22>=assumptions!$G$73,assumptions!$G$72,0))+assumptions!$G$74/12)+IF(22=E12,D12*assumptions!$G$75,0),0) | AC12: =IF(AND(23>=E12,OR(F12="",23<=F12)),(D12*(1+assumptions!$G$76)^1/12*(1+assumptions!$G$70+assumptions!$G$71+IF(23>=assumptions!$G$73,assumptions!$G$72,0))+assumptions!$G$74/12)+IF(23=E12,D12*assumptions!$G$75,0),0) | AD12: =IF(AND(24>=E12,OR(F12="",24<=F12)),(D12*(1+assumptions!$G$76)^1/12*(1+assumptions!$G$70+assumptions!$G$71+IF(24>=assumptions!$G$73,assumptions!$G$72,0))+assumptions!$G$74/12)+IF(24=E12,D12*assumptions!$G$75,0),0) | AE12: =IF(AND(25>=E12,OR(F12="",25<=F12)),(D12*(1+assumptions!$G$76)^2/12*(1+assumptions!$G$70+assumptions!$G$71+IF(25>=assumptions!$G$73,assumptions!$G$72,0))+assumptions!$G$74/12)+IF(25=E12,D12*assumptions!$G$75,0),0) | AF12: =IF(AND(26>=E12,OR(F12="",26<=F12)),(D12*(1+assumptions!$G$76)^2/12*(1+assumptions!$G$70+assumptions!$G$71+IF(26>=assumptions!$G$73,assumptions!$G$72,0))+assumptions!$G$74/12)+IF(26=E12,D12*assumptions!$G$75,0),0) | AG12: =IF(AND(27>=E12,OR(F12="",27<=F12)),(D12*(1+assumptions!$G$76)^2/12*(1+assumptions!$G$70+assumptions!$G$71+IF(27>=assumptions!$G$73,assumptions!$G$72,0))+assumptions!$G$74/12)+IF(27=E12,D12*assumptions!$G$75,0),0) | AH12: =IF(AND(28>=E12,OR(F12="",28<=F12)),(D12*(1+assumptions!$G$76)^2/12*(1+assumptions!$G$70+assumptions!$G$71+IF(28>=assumptions!$G$73,assumptions!$G$72,0))+assumptions!$G$74/12)+IF(28=E12,D12*assumptions!$G$75,0),0) | AI12: =IF(AND(29>=E12,OR(F12="",29<=F12)),(D12*(1+assumptions!$G$76)^2/12*(1+assumptions!$G$70+assumptions!$G$71+IF(29>=assumptions!$G$73,assumptions!$G$72,0))+assumptions!$G$74/12)+IF(29=E12,D12*assumptions!$G$75,0),0) | AJ12: =IF(AND(30>=E12,OR(F12="",30<=F12)),(D12*(1+assumptions!$G$76)^2/12*(1+assumptions!$G$70+assumptions!$G$71+IF(30>=assumptions!$G$73,assumptions!$G$72,0))+assumptions!$G$74/12)+IF(30=E12,D12*assumptions!$G$75,0),0) | AK12: =IF(AND(31>=E12,OR(F12="",31<=F12)),(D12*(1+assumptions!$G$76)^2/12*(1+assumptions!$G$70+assumptions!$G$71+IF(31>=assumptions!$G$73,assumptions!$G$72,0))+assumptions!$G$74/12)+IF(31=E12,D12*assumptions!$G$75,0),0) | AL12: =IF(AND(32>=E12,OR(F12="",32<=F12)),(D12*(1+assumptions!$G$76)^2/12*(1+assumptions!$G$70+assumptions!$G$71+IF(32>=assumptions!$G$73,assumptions!$G$72,0))+assumptions!$G$74/12)+IF(32=E12,D12*assumptions!$G$75,0),0) | AM12: =IF(AND(33>=E12,OR(F12="",33<=F12)),(D12*(1+assumptions!$G$76)^2/12*(1+assumptions!$G$70+assumptions!$G$71+IF(33>=assumptions!$G$73,assumptions!$G$72,0))+assumptions!$G$74/12)+IF(33=E12,D12*assumptions!$G$75,0),0) | AN12: =IF(AND(34>=E12,OR(F12="",34<=F12)),(D12*(1+assumptions!$G$76)^2/12*(1+assumptions!$G$70+assumptions!$G$71+IF(34>=assumptions!$G$73,assumptions!$G$72,0))+assumptions!$G$74/12)+IF(34=E12,D12*assumptions!$G$75,0),0) | AO12: =IF(AND(35>=E12,OR(F12="",35<=F12)),(D12*(1+assumptions!$G$76)^2/12*(1+assumptions!$G$70+assumptions!$G$71+IF(35>=assumptions!$G$73,assumptions!$G$72,0))+assumptions!$G$74/12)+IF(35=E12,D12*assumptions!$G$75,0),0) | AP12: =IF(AND(36>=E12,OR(F12="",36<=F12)),(D12*(1+assumptions!$G$76)^2/12*(1+assumptions!$G$70+assumptions!$G$71+IF(36>=assumptions!$G$73,assumptions!$G$72,0))+assumptions!$G$74/12)+IF(36=E12,D12*assumptions!$G$75,0),0) | AQ12: =IF(AND(37>=E12,OR(F12="",37<=F12)),(D12*(1+assumptions!$G$76)^3/12*(1+assumptions!$G$70+assumptions!$G$71+IF(37>=assumptions!$G$73,assumptions!$G$72,0))+assumptions!$G$74/12)+IF(37=E12,D12*assumptions!$G$75,0),0) | AR12: =IF(AND(38>=E12,OR(F12="",38<=F12)),(D12*(1+assumptions!$G$76)^3/12*(1+assumptions!$G$70+assumptions!$G$71+IF(38>=assumptions!$G$73,assumptions!$G$72,0))+assumptions!$G$74/12)+IF(38=E12,D12*assumptions!$G$75,0),0) | AS12: =IF(AND(39>=E12,OR(F12="",39<=F12)),(D12*(1+assumptions!$G$76)^3/12*(1+assumptions!$G$70+assumptions!$G$71+IF(39>=assumptions!$G$73,assumptions!$G$72,0))+assumptions!$G$74/12)+IF(39=E12,D12*assumptions!$G$75,0),0) | AT12: =IF(AND(40>=E12,OR(F12="",40<=F12)),(D12*(1+assumptions!$G$76)^3/12*(1+assumptions!$G$70+assumptions!$G$71+IF(40>=assumptions!$G$73,assumptions!$G$72,0))+assumptions!$G$74/12)+IF(40=E12,D12*assumptions!$G$75,0),0) | AU12: =IF(AND(41>=E12,OR(F12="",41<=F12)),(D12*(1+assumptions!$G$76)^3/12*(1+assumptions!$G$70+assumptions!$G$71+IF(41>=assumptions!$G$73,assumptions!$G$72,0))+assumptions!$G$74/12)+IF(41=E12,D12*assumptions!$G$75,0),0) | AV12: =IF(AND(42>=E12,OR(F12="",42<=F12)),(D12*(1+assumptions!$G$76)^3/12*(1+assumptions!$G$70+assumptions!$G$71+IF(42>=assumptions!$G$73,assumptions!$G$72,0))+assumptions!$G$74/12)+IF(42=E12,D12*assumptions!$G$75,0),0) | AW12: =IF(AND(43>=E12,OR(F12="",43<=F12)),(D12*(1+assumptions!$G$76)^3/12*(1+assumptions!$G$70+assumptions!$G$71+IF(43>=assumptions!$G$73,assumptions!$G$72,0))+assumptions!$G$74/12)+IF(43=E12,D12*assumptions!$G$75,0),0) | AX12: =IF(AND(44>=E12,OR(F12="",44<=F12)),(D12*(1+assumptions!$G$76)^3/12*(1+assumptions!$G$70+assumptions!$G$71+IF(44>=assumptions!$G$73,assumptions!$G$72,0))+assumptions!$G$74/12)+IF(44=E12,D12*assumptions!$G$75,0),0) | AY12: =IF(AND(45>=E12,OR(F12="",45<=F12)),(D12*(1+assumptions!$G$76)^3/12*(1+assumptions!$G$70+assumptions!$G$71+IF(45>=assumptions!$G$73,assumptions!$G$72,0))+assumptions!$G$74/12)+IF(45=E12,D12*assumptions!$G$75,0),0) | AZ12: =IF(AND(46>=E12,OR(F12="",46<=F12)),(D12*(1+assumptions!$G$76)^3/12*(1+assumptions!$G$70+assumptions!$G$71+IF(46>=assumptions!$G$73,assumptions!$G$72,0))+assumptions!$G$74/12)+IF(46=E12,D12*assumptions!$G$75,0),0) | BA12: =IF(AND(47>=E12,OR(F12="",47<=F12)),(D12*(1+assumptions!$G$76)^3/12*(1+assumptions!$G$70+assumptions!$G$71+IF(47>=assumptions!$G$73,assumptions!$G$72,0))+assumptions!$G$74/12)+IF(47=E12,D12*assumptions!$G$75,0),0) | BB12: =IF(AND(48>=E12,OR(F12="",48<=F12)),(D12*(1+assumptions!$G$76)^3/12*(1+assumptions!$G$70+assumptions!$G$71+IF(48>=assumptions!$G$73,assumptions!$G$72,0))+assumptions!$G$74/12)+IF(48=E12,D12*assumptions!$G$75,0),0) | BC12: =IF(AND(49>=E12,OR(F12="",49<=F12)),(D12*(1+assumptions!$G$76)^4/12*(1+assumptions!$G$70+assumptions!$G$71+IF(49>=assumptions!$G$73,assumptions!$G$72,0))+assumptions!$G$74/12)+IF(49=E12,D12*assumptions!$G$75,0),0) | BD12: =IF(AND(50>=E12,OR(F12="",50<=F12)),(D12*(1+assumptions!$G$76)^4/12*(1+assumptions!$G$70+assumptions!$G$71+IF(50>=assumptions!$G$73,assumptions!$G$72,0))+assumptions!$G$74/12)+IF(50=E12,D12*assumptions!$G$75,0),0) | BE12: =IF(AND(51>=E12,OR(F12="",51<=F12)),(D12*(1+assumptions!$G$76)^4/12*(1+assumptions!$G$70+assumptions!$G$71+IF(51>=assumptions!$G$73,assumptions!$G$72,0))+assumptions!$G$74/12)+IF(51=E12,D12*assumptions!$G$75,0),0) | BF12: =IF(AND(52>=E12,OR(F12="",52<=F12)),(D12*(1+assumptions!$G$76)^4/12*(1+assumptions!$G$70+assumptions!$G$71+IF(52>=assumptions!$G$73,assumptions!$G$72,0))+assumptions!$G$74/12)+IF(52=E12,D12*assumptions!$G$75,0),0) | BG12: =IF(AND(53>=E12,OR(F12="",53<=F12)),(D12*(1+assumptions!$G$76)^4/12*(1+assumptions!$G$70+assumptions!$G$71+IF(53>=assumptions!$G$73,assumptions!$G$72,0))+assumptions!$G$74/12)+IF(53=E12,D12*assumptions!$G$75,0),0) | BH12: =IF(AND(54>=E12,OR(F12="",54<=F12)),(D12*(1+assumptions!$G$76)^4/12*(1+assumptions!$G$70+assumptions!$G$71+IF(54>=assumptions!$G$73,assumptions!$G$72,0))+assumptions!$G$74/12)+IF(54=E12,D12*assumptions!$G$75,0),0) | BI12: =IF(AND(55>=E12,OR(F12="",55<=F12)),(D12*(1+assumptions!$G$76)^4/12*(1+assumptions!$G$70+assumptions!$G$71+IF(55>=assumptions!$G$73,assumptions!$G$72,0))+assumptions!$G$74/12)+IF(55=E12,D12*assumptions!$G$75,0),0) | BJ12: =IF(AND(56>=E12,OR(F12="",56<=F12)),(D12*(1+assumptions!$G$76)^4/12*(1+assumptions!$G$70+assumptions!$G$71+IF(56>=assumptions!$G$73,assumptions!$G$72,0))+assumptions!$G$74/12)+IF(56=E12,D12*assumptions!$G$75,0),0) | BK12: =IF(AND(57>=E12,OR(F12="",57<=F12)),(D12*(1+assumptions!$G$76)^4/12*(1+assumptions!$G$70+assumptions!$G$71+IF(57>=assumptions!$G$73,assumptions!$G$72,0))+assumptions!$G$74/12)+IF(57=E12,D12*assumptions!$G$75,0),0) | BL12: =IF(AND(58>=E12,OR(F12="",58<=F12)),(D12*(1+assumptions!$G$76)^4/12*(1+assumptions!$G$70+assumptions!$G$71+IF(58>=assumptions!$G$73,assumptions!$G$72,0))+assumptions!$G$74/12)+IF(58=E12,D12*assumptions!$G$75,0),0) | BM12: =IF(AND(59>=E12,OR(F12="",59<=F12)),(D12*(1+assumptions!$G$76)^4/12*(1+assumptions!$G$70+assumptions!$G$71+IF(59>=assumptions!$G$73,assumptions!$G$72,0))+assumptions!$G$74/12)+IF(59=E12,D12*assumptions!$G$75,0),0) | BN12: =IF(AND(60>=E12,OR(F12="",60<=F12)),(D12*(1+assumptions!$G$76)^4/12*(1+assumptions!$G$70+assumptions!$G$71+IF(60>=assumptions!$G$73,assumptions!$G$72,0))+assumptions!$G$74/12)+IF(60=E12,D12*assumptions!$G$75,0),0)
A13: 10 | B13: Data / ML engineer | C13: eng | D13: 90000 | E13: 6 | G13: =IF(AND(1>=E13,OR(F13="",1<=F13)),(D13*(1+assumptions!$G$76)^0/12*(1+assumptions!$G$70+assumptions!$G$71+IF(1>=assumptions!$G$73,assumptions!$G$72,0))+assumptions!$G$74/12)+IF(1=E13,D13*assumptions!$G$75,0),0) | H13: =IF(AND(2>=E13,OR(F13="",2<=F13)),(D13*(1+assumptions!$G$76)^0/12*(1+assumptions!$G$70+assumptions!$G$71+IF(2>=assumptions!$G$73,assumptions!$G$72,0))+assumptions!$G$74/12)+IF(2=E13,D13*assumptions!$G$75,0),0) | I13: =IF(AND(3>=E13,OR(F13="",3<=F13)),(D13*(1+assumptions!$G$76)^0/12*(1+assumptions!$G$70+assumptions!$G$71+IF(3>=assumptions!$G$73,assumptions!$G$72,0))+assumptions!$G$74/12)+IF(3=E13,D13*assumptions!$G$75,0),0) | J13: =IF(AND(4>=E13,OR(F13="",4<=F13)),(D13*(1+assumptions!$G$76)^0/12*(1+assumptions!$G$70+assumptions!$G$71+IF(4>=assumptions!$G$73,assumptions!$G$72,0))+assumptions!$G$74/12)+IF(4=E13,D13*assumptions!$G$75,0),0) | K13: =IF(AND(5>=E13,OR(F13="",5<=F13)),(D13*(1+assumptions!$G$76)^0/12*(1+assumptions!$G$70+assumptions!$G$71+IF(5>=assumptions!$G$73,assumptions!$G$72,0))+assumptions!$G$74/12)+IF(5=E13,D13*assumptions!$G$75,0),0) | L13: =IF(AND(6>=E13,OR(F13="",6<=F13)),(D13*(1+assumptions!$G$76)^0/12*(1+assumptions!$G$70+assumptions!$G$71+IF(6>=assumptions!$G$73,assumptions!$G$72,0))+assumptions!$G$74/12)+IF(6=E13,D13*assumptions!$G$75,0),0) | M13: =IF(AND(7>=E13,OR(F13="",7<=F13)),(D13*(1+assumptions!$G$76)^0/12*(1+assumptions!$G$70+assumptions!$G$71+IF(7>=assumptions!$G$73,assumptions!$G$72,0))+assumptions!$G$74/12)+IF(7=E13,D13*assumptions!$G$75,0),0) | N13: =IF(AND(8>=E13,OR(F13="",8<=F13)),(D13*(1+assumptions!$G$76)^0/12*(1+assumptions!$G$70+assumptions!$G$71+IF(8>=assumptions!$G$73,assumptions!$G$72,0))+assumptions!$G$74/12)+IF(8=E13,D13*assumptions!$G$75,0),0) | O13: =IF(AND(9>=E13,OR(F13="",9<=F13)),(D13*(1+assumptions!$G$76)^0/12*(1+assumptions!$G$70+assumptions!$G$71+IF(9>=assumptions!$G$73,assumptions!$G$72,0))+assumptions!$G$74/12)+IF(9=E13,D13*assumptions!$G$75,0),0) | P13: =IF(AND(10>=E13,OR(F13="",10<=F13)),(D13*(1+assumptions!$G$76)^0/12*(1+assumptions!$G$70+assumptions!$G$71+IF(10>=assumptions!$G$73,assumptions!$G$72,0))+assumptions!$G$74/12)+IF(10=E13,D13*assumptions!$G$75,0),0) | Q13: =IF(AND(11>=E13,OR(F13="",11<=F13)),(D13*(1+assumptions!$G$76)^0/12*(1+assumptions!$G$70+assumptions!$G$71+IF(11>=assumptions!$G$73,assumptions!$G$72,0))+assumptions!$G$74/12)+IF(11=E13,D13*assumptions!$G$75,0),0) | R13: =IF(AND(12>=E13,OR(F13="",12<=F13)),(D13*(1+assumptions!$G$76)^0/12*(1+assumptions!$G$70+assumptions!$G$71+IF(12>=assumptions!$G$73,assumptions!$G$72,0))+assumptions!$G$74/12)+IF(12=E13,D13*assumptions!$G$75,0),0) | S13: =IF(AND(13>=E13,OR(F13="",13<=F13)),(D13*(1+assumptions!$G$76)^1/12*(1+assumptions!$G$70+assumptions!$G$71+IF(13>=assumptions!$G$73,assumptions!$G$72,0))+assumptions!$G$74/12)+IF(13=E13,D13*assumptions!$G$75,0),0) | T13: =IF(AND(14>=E13,OR(F13="",14<=F13)),(D13*(1+assumptions!$G$76)^1/12*(1+assumptions!$G$70+assumptions!$G$71+IF(14>=assumptions!$G$73,assumptions!$G$72,0))+assumptions!$G$74/12)+IF(14=E13,D13*assumptions!$G$75,0),0) | U13: =IF(AND(15>=E13,OR(F13="",15<=F13)),(D13*(1+assumptions!$G$76)^1/12*(1+assumptions!$G$70+assumptions!$G$71+IF(15>=assumptions!$G$73,assumptions!$G$72,0))+assumptions!$G$74/12)+IF(15=E13,D13*assumptions!$G$75,0),0) | V13: =IF(AND(16>=E13,OR(F13="",16<=F13)),(D13*(1+assumptions!$G$76)^1/12*(1+assumptions!$G$70+assumptions!$G$71+IF(16>=assumptions!$G$73,assumptions!$G$72,0))+assumptions!$G$74/12)+IF(16=E13,D13*assumptions!$G$75,0),0) | W13: =IF(AND(17>=E13,OR(F13="",17<=F13)),(D13*(1+assumptions!$G$76)^1/12*(1+assumptions!$G$70+assumptions!$G$71+IF(17>=assumptions!$G$73,assumptions!$G$72,0))+assumptions!$G$74/12)+IF(17=E13,D13*assumptions!$G$75,0),0) | X13: =IF(AND(18>=E13,OR(F13="",18<=F13)),(D13*(1+assumptions!$G$76)^1/12*(1+assumptions!$G$70+assumptions!$G$71+IF(18>=assumptions!$G$73,assumptions!$G$72,0))+assumptions!$G$74/12)+IF(18=E13,D13*assumptions!$G$75,0),0) | Y13: =IF(AND(19>=E13,OR(F13="",19<=F13)),(D13*(1+assumptions!$G$76)^1/12*(1+assumptions!$G$70+assumptions!$G$71+IF(19>=assumptions!$G$73,assumptions!$G$72,0))+assumptions!$G$74/12)+IF(19=E13,D13*assumptions!$G$75,0),0) | Z13: =IF(AND(20>=E13,OR(F13="",20<=F13)),(D13*(1+assumptions!$G$76)^1/12*(1+assumptions!$G$70+assumptions!$G$71+IF(20>=assumptions!$G$73,assumptions!$G$72,0))+assumptions!$G$74/12)+IF(20=E13,D13*assumptions!$G$75,0),0) | AA13: =IF(AND(21>=E13,OR(F13="",21<=F13)),(D13*(1+assumptions!$G$76)^1/12*(1+assumptions!$G$70+assumptions!$G$71+IF(21>=assumptions!$G$73,assumptions!$G$72,0))+assumptions!$G$74/12)+IF(21=E13,D13*assumptions!$G$75,0),0) | AB13: =IF(AND(22>=E13,OR(F13="",22<=F13)),(D13*(1+assumptions!$G$76)^1/12*(1+assumptions!$G$70+assumptions!$G$71+IF(22>=assumptions!$G$73,assumptions!$G$72,0))+assumptions!$G$74/12)+IF(22=E13,D13*assumptions!$G$75,0),0) | AC13: =IF(AND(23>=E13,OR(F13="",23<=F13)),(D13*(1+assumptions!$G$76)^1/12*(1+assumptions!$G$70+assumptions!$G$71+IF(23>=assumptions!$G$73,assumptions!$G$72,0))+assumptions!$G$74/12)+IF(23=E13,D13*assumptions!$G$75,0),0) | AD13: =IF(AND(24>=E13,OR(F13="",24<=F13)),(D13*(1+assumptions!$G$76)^1/12*(1+assumptions!$G$70+assumptions!$G$71+IF(24>=assumptions!$G$73,assumptions!$G$72,0))+assumptions!$G$74/12)+IF(24=E13,D13*assumptions!$G$75,0),0) | AE13: =IF(AND(25>=E13,OR(F13="",25<=F13)),(D13*(1+assumptions!$G$76)^2/12*(1+assumptions!$G$70+assumptions!$G$71+IF(25>=assumptions!$G$73,assumptions!$G$72,0))+assumptions!$G$74/12)+IF(25=E13,D13*assumptions!$G$75,0),0) | AF13: =IF(AND(26>=E13,OR(F13="",26<=F13)),(D13*(1+assumptions!$G$76)^2/12*(1+assumptions!$G$70+assumptions!$G$71+IF(26>=assumptions!$G$73,assumptions!$G$72,0))+assumptions!$G$74/12)+IF(26=E13,D13*assumptions!$G$75,0),0) | AG13: =IF(AND(27>=E13,OR(F13="",27<=F13)),(D13*(1+assumptions!$G$76)^2/12*(1+assumptions!$G$70+assumptions!$G$71+IF(27>=assumptions!$G$73,assumptions!$G$72,0))+assumptions!$G$74/12)+IF(27=E13,D13*assumptions!$G$75,0),0) | AH13: =IF(AND(28>=E13,OR(F13="",28<=F13)),(D13*(1+assumptions!$G$76)^2/12*(1+assumptions!$G$70+assumptions!$G$71+IF(28>=assumptions!$G$73,assumptions!$G$72,0))+assumptions!$G$74/12)+IF(28=E13,D13*assumptions!$G$75,0),0) | AI13: =IF(AND(29>=E13,OR(F13="",29<=F13)),(D13*(1+assumptions!$G$76)^2/12*(1+assumptions!$G$70+assumptions!$G$71+IF(29>=assumptions!$G$73,assumptions!$G$72,0))+assumptions!$G$74/12)+IF(29=E13,D13*assumptions!$G$75,0),0) | AJ13: =IF(AND(30>=E13,OR(F13="",30<=F13)),(D13*(1+assumptions!$G$76)^2/12*(1+assumptions!$G$70+assumptions!$G$71+IF(30>=assumptions!$G$73,assumptions!$G$72,0))+assumptions!$G$74/12)+IF(30=E13,D13*assumptions!$G$75,0),0) | AK13: =IF(AND(31>=E13,OR(F13="",31<=F13)),(D13*(1+assumptions!$G$76)^2/12*(1+assumptions!$G$70+assumptions!$G$71+IF(31>=assumptions!$G$73,assumptions!$G$72,0))+assumptions!$G$74/12)+IF(31=E13,D13*assumptions!$G$75,0),0) | AL13: =IF(AND(32>=E13,OR(F13="",32<=F13)),(D13*(1+assumptions!$G$76)^2/12*(1+assumptions!$G$70+assumptions!$G$71+IF(32>=assumptions!$G$73,assumptions!$G$72,0))+assumptions!$G$74/12)+IF(32=E13,D13*assumptions!$G$75,0),0) | AM13: =IF(AND(33>=E13,OR(F13="",33<=F13)),(D13*(1+assumptions!$G$76)^2/12*(1+assumptions!$G$70+assumptions!$G$71+IF(33>=assumptions!$G$73,assumptions!$G$72,0))+assumptions!$G$74/12)+IF(33=E13,D13*assumptions!$G$75,0),0) | AN13: =IF(AND(34>=E13,OR(F13="",34<=F13)),(D13*(1+assumptions!$G$76)^2/12*(1+assumptions!$G$70+assumptions!$G$71+IF(34>=assumptions!$G$73,assumptions!$G$72,0))+assumptions!$G$74/12)+IF(34=E13,D13*assumptions!$G$75,0),0) | AO13: =IF(AND(35>=E13,OR(F13="",35<=F13)),(D13*(1+assumptions!$G$76)^2/12*(1+assumptions!$G$70+assumptions!$G$71+IF(35>=assumptions!$G$73,assumptions!$G$72,0))+assumptions!$G$74/12)+IF(35=E13,D13*assumptions!$G$75,0),0) | AP13: =IF(AND(36>=E13,OR(F13="",36<=F13)),(D13*(1+assumptions!$G$76)^2/12*(1+assumptions!$G$70+assumptions!$G$71+IF(36>=assumptions!$G$73,assumptions!$G$72,0))+assumptions!$G$74/12)+IF(36=E13,D13*assumptions!$G$75,0),0) | AQ13: =IF(AND(37>=E13,OR(F13="",37<=F13)),(D13*(1+assumptions!$G$76)^3/12*(1+assumptions!$G$70+assumptions!$G$71+IF(37>=assumptions!$G$73,assumptions!$G$72,0))+assumptions!$G$74/12)+IF(37=E13,D13*assumptions!$G$75,0),0) | AR13: =IF(AND(38>=E13,OR(F13="",38<=F13)),(D13*(1+assumptions!$G$76)^3/12*(1+assumptions!$G$70+assumptions!$G$71+IF(38>=assumptions!$G$73,assumptions!$G$72,0))+assumptions!$G$74/12)+IF(38=E13,D13*assumptions!$G$75,0),0) | AS13: =IF(AND(39>=E13,OR(F13="",39<=F13)),(D13*(1+assumptions!$G$76)^3/12*(1+assumptions!$G$70+assumptions!$G$71+IF(39>=assumptions!$G$73,assumptions!$G$72,0))+assumptions!$G$74/12)+IF(39=E13,D13*assumptions!$G$75,0),0) | AT13: =IF(AND(40>=E13,OR(F13="",40<=F13)),(D13*(1+assumptions!$G$76)^3/12*(1+assumptions!$G$70+assumptions!$G$71+IF(40>=assumptions!$G$73,assumptions!$G$72,0))+assumptions!$G$74/12)+IF(40=E13,D13*assumptions!$G$75,0),0) | AU13: =IF(AND(41>=E13,OR(F13="",41<=F13)),(D13*(1+assumptions!$G$76)^3/12*(1+assumptions!$G$70+assumptions!$G$71+IF(41>=assumptions!$G$73,assumptions!$G$72,0))+assumptions!$G$74/12)+IF(41=E13,D13*assumptions!$G$75,0),0) | AV13: =IF(AND(42>=E13,OR(F13="",42<=F13)),(D13*(1+assumptions!$G$76)^3/12*(1+assumptions!$G$70+assumptions!$G$71+IF(42>=assumptions!$G$73,assumptions!$G$72,0))+assumptions!$G$74/12)+IF(42=E13,D13*assumptions!$G$75,0),0) | AW13: =IF(AND(43>=E13,OR(F13="",43<=F13)),(D13*(1+assumptions!$G$76)^3/12*(1+assumptions!$G$70+assumptions!$G$71+IF(43>=assumptions!$G$73,assumptions!$G$72,0))+assumptions!$G$74/12)+IF(43=E13,D13*assumptions!$G$75,0),0) | AX13: =IF(AND(44>=E13,OR(F13="",44<=F13)),(D13*(1+assumptions!$G$76)^3/12*(1+assumptions!$G$70+assumptions!$G$71+IF(44>=assumptions!$G$73,assumptions!$G$72,0))+assumptions!$G$74/12)+IF(44=E13,D13*assumptions!$G$75,0),0) | AY13: =IF(AND(45>=E13,OR(F13="",45<=F13)),(D13*(1+assumptions!$G$76)^3/12*(1+assumptions!$G$70+assumptions!$G$71+IF(45>=assumptions!$G$73,assumptions!$G$72,0))+assumptions!$G$74/12)+IF(45=E13,D13*assumptions!$G$75,0),0) | AZ13: =IF(AND(46>=E13,OR(F13="",46<=F13)),(D13*(1+assumptions!$G$76)^3/12*(1+assumptions!$G$70+assumptions!$G$71+IF(46>=assumptions!$G$73,assumptions!$G$72,0))+assumptions!$G$74/12)+IF(46=E13,D13*assumptions!$G$75,0),0) | BA13: =IF(AND(47>=E13,OR(F13="",47<=F13)),(D13*(1+assumptions!$G$76)^3/12*(1+assumptions!$G$70+assumptions!$G$71+IF(47>=assumptions!$G$73,assumptions!$G$72,0))+assumptions!$G$74/12)+IF(47=E13,D13*assumptions!$G$75,0),0) | BB13: =IF(AND(48>=E13,OR(F13="",48<=F13)),(D13*(1+assumptions!$G$76)^3/12*(1+assumptions!$G$70+assumptions!$G$71+IF(48>=assumptions!$G$73,assumptions!$G$72,0))+assumptions!$G$74/12)+IF(48=E13,D13*assumptions!$G$75,0),0) | BC13: =IF(AND(49>=E13,OR(F13="",49<=F13)),(D13*(1+assumptions!$G$76)^4/12*(1+assumptions!$G$70+assumptions!$G$71+IF(49>=assumptions!$G$73,assumptions!$G$72,0))+assumptions!$G$74/12)+IF(49=E13,D13*assumptions!$G$75,0),0) | BD13: =IF(AND(50>=E13,OR(F13="",50<=F13)),(D13*(1+assumptions!$G$76)^4/12*(1+assumptions!$G$70+assumptions!$G$71+IF(50>=assumptions!$G$73,assumptions!$G$72,0))+assumptions!$G$74/12)+IF(50=E13,D13*assumptions!$G$75,0),0) | BE13: =IF(AND(51>=E13,OR(F13="",51<=F13)),(D13*(1+assumptions!$G$76)^4/12*(1+assumptions!$G$70+assumptions!$G$71+IF(51>=assumptions!$G$73,assumptions!$G$72,0))+assumptions!$G$74/12)+IF(51=E13,D13*assumptions!$G$75,0),0) | BF13: =IF(AND(52>=E13,OR(F13="",52<=F13)),(D13*(1+assumptions!$G$76)^4/12*(1+assumptions!$G$70+assumptions!$G$71+IF(52>=assumptions!$G$73,assumptions!$G$72,0))+assumptions!$G$74/12)+IF(52=E13,D13*assumptions!$G$75,0),0) | BG13: =IF(AND(53>=E13,OR(F13="",53<=F13)),(D13*(1+assumptions!$G$76)^4/12*(1+assumptions!$G$70+assumptions!$G$71+IF(53>=assumptions!$G$73,assumptions!$G$72,0))+assumptions!$G$74/12)+IF(53=E13,D13*assumptions!$G$75,0),0) | BH13: =IF(AND(54>=E13,OR(F13="",54<=F13)),(D13*(1+assumptions!$G$76)^4/12*(1+assumptions!$G$70+assumptions!$G$71+IF(54>=assumptions!$G$73,assumptions!$G$72,0))+assumptions!$G$74/12)+IF(54=E13,D13*assumptions!$G$75,0),0) | BI13: =IF(AND(55>=E13,OR(F13="",55<=F13)),(D13*(1+assumptions!$G$76)^4/12*(1+assumptions!$G$70+assumptions!$G$71+IF(55>=assumptions!$G$73,assumptions!$G$72,0))+assumptions!$G$74/12)+IF(55=E13,D13*assumptions!$G$75,0),0) | BJ13: =IF(AND(56>=E13,OR(F13="",56<=F13)),(D13*(1+assumptions!$G$76)^4/12*(1+assumptions!$G$70+assumptions!$G$71+IF(56>=assumptions!$G$73,assumptions!$G$72,0))+assumptions!$G$74/12)+IF(56=E13,D13*assumptions!$G$75,0),0) | BK13: =IF(AND(57>=E13,OR(F13="",57<=F13)),(D13*(1+assumptions!$G$76)^4/12*(1+assumptions!$G$70+assumptions!$G$71+IF(57>=assumptions!$G$73,assumptions!$G$72,0))+assumptions!$G$74/12)+IF(57=E13,D13*assumptions!$G$75,0),0) | BL13: =IF(AND(58>=E13,OR(F13="",58<=F13)),(D13*(1+assumptions!$G$76)^4/12*(1+assumptions!$G$70+assumptions!$G$71+IF(58>=assumptions!$G$73,assumptions!$G$72,0))+assumptions!$G$74/12)+IF(58=E13,D13*assumptions!$G$75,0),0) | BM13: =IF(AND(59>=E13,OR(F13="",59<=F13)),(D13*(1+assumptions!$G$76)^4/12*(1+assumptions!$G$70+assumptions!$G$71+IF(59>=assumptions!$G$73,assumptions!$G$72,0))+assumptions!$G$74/12)+IF(59=E13,D13*assumptions!$G$75,0),0) | BN13: =IF(AND(60>=E13,OR(F13="",60<=F13)),(D13*(1+assumptions!$G$76)^4/12*(1+assumptions!$G$70+assumptions!$G$71+IF(60>=assumptions!$G$73,assumptions!$G$72,0))+assumptions!$G$74/12)+IF(60=E13,D13*assumptions!$G$75,0),0)
A14: 11 | B14: Backend engineer | C14: eng | D14: 80000 | E14: 9 | G14: =IF(AND(1>=E14,OR(F14="",1<=F14)),(D14*(1+assumptions!$G$76)^0/12*(1+assumptions!$G$70+assumptions!$G$71+IF(1>=assumptions!$G$73,assumptions!$G$72,0))+assumptions!$G$74/12)+IF(1=E14,D14*assumptions!$G$75,0),0) | H14: =IF(AND(2>=E14,OR(F14="",2<=F14)),(D14*(1+assumptions!$G$76)^0/12*(1+assumptions!$G$70+assumptions!$G$71+IF(2>=assumptions!$G$73,assumptions!$G$72,0))+assumptions!$G$74/12)+IF(2=E14,D14*assumptions!$G$75,0),0) | I14: =IF(AND(3>=E14,OR(F14="",3<=F14)),(D14*(1+assumptions!$G$76)^0/12*(1+assumptions!$G$70+assumptions!$G$71+IF(3>=assumptions!$G$73,assumptions!$G$72,0))+assumptions!$G$74/12)+IF(3=E14,D14*assumptions!$G$75,0),0) | J14: =IF(AND(4>=E14,OR(F14="",4<=F14)),(D14*(1+assumptions!$G$76)^0/12*(1+assumptions!$G$70+assumptions!$G$71+IF(4>=assumptions!$G$73,assumptions!$G$72,0))+assumptions!$G$74/12)+IF(4=E14,D14*assumptions!$G$75,0),0) | K14: =IF(AND(5>=E14,OR(F14="",5<=F14)),(D14*(1+assumptions!$G$76)^0/12*(1+assumptions!$G$70+assumptions!$G$71+IF(5>=assumptions!$G$73,assumptions!$G$72,0))+assumptions!$G$74/12)+IF(5=E14,D14*assumptions!$G$75,0),0) | L14: =IF(AND(6>=E14,OR(F14="",6<=F14)),(D14*(1+assumptions!$G$76)^0/12*(1+assumptions!$G$70+assumptions!$G$71+IF(6>=assumptions!$G$73,assumptions!$G$72,0))+assumptions!$G$74/12)+IF(6=E14,D14*assumptions!$G$75,0),0) | M14: =IF(AND(7>=E14,OR(F14="",7<=F14)),(D14*(1+assumptions!$G$76)^0/12*(1+assumptions!$G$70+assumptions!$G$71+IF(7>=assumptions!$G$73,assumptions!$G$72,0))+assumptions!$G$74/12)+IF(7=E14,D14*assumptions!$G$75,0),0) | N14: =IF(AND(8>=E14,OR(F14="",8<=F14)),(D14*(1+assumptions!$G$76)^0/12*(1+assumptions!$G$70+assumptions!$G$71+IF(8>=assumptions!$G$73,assumptions!$G$72,0))+assumptions!$G$74/12)+IF(8=E14,D14*assumptions!$G$75,0),0) | O14: =IF(AND(9>=E14,OR(F14="",9<=F14)),(D14*(1+assumptions!$G$76)^0/12*(1+assumptions!$G$70+assumptions!$G$71+IF(9>=assumptions!$G$73,assumptions!$G$72,0))+assumptions!$G$74/12)+IF(9=E14,D14*assumptions!$G$75,0),0) | P14: =IF(AND(10>=E14,OR(F14="",10<=F14)),(D14*(1+assumptions!$G$76)^0/12*(1+assumptions!$G$70+assumptions!$G$71+IF(10>=assumptions!$G$73,assumptions!$G$72,0))+assumptions!$G$74/12)+IF(10=E14,D14*assumptions!$G$75,0),0) | Q14: =IF(AND(11>=E14,OR(F14="",11<=F14)),(D14*(1+assumptions!$G$76)^0/12*(1+assumptions!$G$70+assumptions!$G$71+IF(11>=assumptions!$G$73,assumptions!$G$72,0))+assumptions!$G$74/12)+IF(11=E14,D14*assumptions!$G$75,0),0) | R14: =IF(AND(12>=E14,OR(F14="",12<=F14)),(D14*(1+assumptions!$G$76)^0/12*(1+assumptions!$G$70+assumptions!$G$71+IF(12>=assumptions!$G$73,assumptions!$G$72,0))+assumptions!$G$74/12)+IF(12=E14,D14*assumptions!$G$75,0),0) | S14: =IF(AND(13>=E14,OR(F14="",13<=F14)),(D14*(1+assumptions!$G$76)^1/12*(1+assumptions!$G$70+assumptions!$G$71+IF(13>=assumptions!$G$73,assumptions!$G$72,0))+assumptions!$G$74/12)+IF(13=E14,D14*assumptions!$G$75,0),0) | T14: =IF(AND(14>=E14,OR(F14="",14<=F14)),(D14*(1+assumptions!$G$76)^1/12*(1+assumptions!$G$70+assumptions!$G$71+IF(14>=assumptions!$G$73,assumptions!$G$72,0))+assumptions!$G$74/12)+IF(14=E14,D14*assumptions!$G$75,0),0) | U14: =IF(AND(15>=E14,OR(F14="",15<=F14)),(D14*(1+assumptions!$G$76)^1/12*(1+assumptions!$G$70+assumptions!$G$71+IF(15>=assumptions!$G$73,assumptions!$G$72,0))+assumptions!$G$74/12)+IF(15=E14,D14*assumptions!$G$75,0),0) | V14: =IF(AND(16>=E14,OR(F14="",16<=F14)),(D14*(1+assumptions!$G$76)^1/12*(1+assumptions!$G$70+assumptions!$G$71+IF(16>=assumptions!$G$73,assumptions!$G$72,0))+assumptions!$G$74/12)+IF(16=E14,D14*assumptions!$G$75,0),0) | W14: =IF(AND(17>=E14,OR(F14="",17<=F14)),(D14*(1+assumptions!$G$76)^1/12*(1+assumptions!$G$70+assumptions!$G$71+IF(17>=assumptions!$G$73,assumptions!$G$72,0))+assumptions!$G$74/12)+IF(17=E14,D14*assumptions!$G$75,0),0) | X14: =IF(AND(18>=E14,OR(F14="",18<=F14)),(D14*(1+assumptions!$G$76)^1/12*(1+assumptions!$G$70+assumptions!$G$71+IF(18>=assumptions!$G$73,assumptions!$G$72,0))+assumptions!$G$74/12)+IF(18=E14,D14*assumptions!$G$75,0),0) | Y14: =IF(AND(19>=E14,OR(F14="",19<=F14)),(D14*(1+assumptions!$G$76)^1/12*(1+assumptions!$G$70+assumptions!$G$71+IF(19>=assumptions!$G$73,assumptions!$G$72,0))+assumptions!$G$74/12)+IF(19=E14,D14*assumptions!$G$75,0),0) | Z14: =IF(AND(20>=E14,OR(F14="",20<=F14)),(D14*(1+assumptions!$G$76)^1/12*(1+assumptions!$G$70+assumptions!$G$71+IF(20>=assumptions!$G$73,assumptions!$G$72,0))+assumptions!$G$74/12)+IF(20=E14,D14*assumptions!$G$75,0),0) | AA14: =IF(AND(21>=E14,OR(F14="",21<=F14)),(D14*(1+assumptions!$G$76)^1/12*(1+assumptions!$G$70+assumptions!$G$71+IF(21>=assumptions!$G$73,assumptions!$G$72,0))+assumptions!$G$74/12)+IF(21=E14,D14*assumptions!$G$75,0),0) | AB14: =IF(AND(22>=E14,OR(F14="",22<=F14)),(D14*(1+assumptions!$G$76)^1/12*(1+assumptions!$G$70+assumptions!$G$71+IF(22>=assumptions!$G$73,assumptions!$G$72,0))+assumptions!$G$74/12)+IF(22=E14,D14*assumptions!$G$75,0),0) | AC14: =IF(AND(23>=E14,OR(F14="",23<=F14)),(D14*(1+assumptions!$G$76)^1/12*(1+assumptions!$G$70+assumptions!$G$71+IF(23>=assumptions!$G$73,assumptions!$G$72,0))+assumptions!$G$74/12)+IF(23=E14,D14*assumptions!$G$75,0),0) | AD14: =IF(AND(24>=E14,OR(F14="",24<=F14)),(D14*(1+assumptions!$G$76)^1/12*(1+assumptions!$G$70+assumptions!$G$71+IF(24>=assumptions!$G$73,assumptions!$G$72,0))+assumptions!$G$74/12)+IF(24=E14,D14*assumptions!$G$75,0),0) | AE14: =IF(AND(25>=E14,OR(F14="",25<=F14)),(D14*(1+assumptions!$G$76)^2/12*(1+assumptions!$G$70+assumptions!$G$71+IF(25>=assumptions!$G$73,assumptions!$G$72,0))+assumptions!$G$74/12)+IF(25=E14,D14*assumptions!$G$75,0),0) | AF14: =IF(AND(26>=E14,OR(F14="",26<=F14)),(D14*(1+assumptions!$G$76)^2/12*(1+assumptions!$G$70+assumptions!$G$71+IF(26>=assumptions!$G$73,assumptions!$G$72,0))+assumptions!$G$74/12)+IF(26=E14,D14*assumptions!$G$75,0),0) | AG14: =IF(AND(27>=E14,OR(F14="",27<=F14)),(D14*(1+assumptions!$G$76)^2/12*(1+assumptions!$G$70+assumptions!$G$71+IF(27>=assumptions!$G$73,assumptions!$G$72,0))+assumptions!$G$74/12)+IF(27=E14,D14*assumptions!$G$75,0),0) | AH14: =IF(AND(28>=E14,OR(F14="",28<=F14)),(D14*(1+assumptions!$G$76)^2/12*(1+assumptions!$G$70+assumptions!$G$71+IF(28>=assumptions!$G$73,assumptions!$G$72,0))+assumptions!$G$74/12)+IF(28=E14,D14*assumptions!$G$75,0),0) | AI14: =IF(AND(29>=E14,OR(F14="",29<=F14)),(D14*(1+assumptions!$G$76)^2/12*(1+assumptions!$G$70+assumptions!$G$71+IF(29>=assumptions!$G$73,assumptions!$G$72,0))+assumptions!$G$74/12)+IF(29=E14,D14*assumptions!$G$75,0),0) | AJ14: =IF(AND(30>=E14,OR(F14="",30<=F14)),(D14*(1+assumptions!$G$76)^2/12*(1+assumptions!$G$70+assumptions!$G$71+IF(30>=assumptions!$G$73,assumptions!$G$72,0))+assumptions!$G$74/12)+IF(30=E14,D14*assumptions!$G$75,0),0) | AK14: =IF(AND(31>=E14,OR(F14="",31<=F14)),(D14*(1+assumptions!$G$76)^2/12*(1+assumptions!$G$70+assumptions!$G$71+IF(31>=assumptions!$G$73,assumptions!$G$72,0))+assumptions!$G$74/12)+IF(31=E14,D14*assumptions!$G$75,0),0) | AL14: =IF(AND(32>=E14,OR(F14="",32<=F14)),(D14*(1+assumptions!$G$76)^2/12*(1+assumptions!$G$70+assumptions!$G$71+IF(32>=assumptions!$G$73,assumptions!$G$72,0))+assumptions!$G$74/12)+IF(32=E14,D14*assumptions!$G$75,0),0) | AM14: =IF(AND(33>=E14,OR(F14="",33<=F14)),(D14*(1+assumptions!$G$76)^2/12*(1+assumptions!$G$70+assumptions!$G$71+IF(33>=assumptions!$G$73,assumptions!$G$72,0))+assumptions!$G$74/12)+IF(33=E14,D14*assumptions!$G$75,0),0) | AN14: =IF(AND(34>=E14,OR(F14="",34<=F14)),(D14*(1+assumptions!$G$76)^2/12*(1+assumptions!$G$70+assumptions!$G$71+IF(34>=assumptions!$G$73,assumptions!$G$72,0))+assumptions!$G$74/12)+IF(34=E14,D14*assumptions!$G$75,0),0) | AO14: =IF(AND(35>=E14,OR(F14="",35<=F14)),(D14*(1+assumptions!$G$76)^2/12*(1+assumptions!$G$70+assumptions!$G$71+IF(35>=assumptions!$G$73,assumptions!$G$72,0))+assumptions!$G$74/12)+IF(35=E14,D14*assumptions!$G$75,0),0) | AP14: =IF(AND(36>=E14,OR(F14="",36<=F14)),(D14*(1+assumptions!$G$76)^2/12*(1+assumptions!$G$70+assumptions!$G$71+IF(36>=assumptions!$G$73,assumptions!$G$72,0))+assumptions!$G$74/12)+IF(36=E14,D14*assumptions!$G$75,0),0) | AQ14: =IF(AND(37>=E14,OR(F14="",37<=F14)),(D14*(1+assumptions!$G$76)^3/12*(1+assumptions!$G$70+assumptions!$G$71+IF(37>=assumptions!$G$73,assumptions!$G$72,0))+assumptions!$G$74/12)+IF(37=E14,D14*assumptions!$G$75,0),0) | AR14: =IF(AND(38>=E14,OR(F14="",38<=F14)),(D14*(1+assumptions!$G$76)^3/12*(1+assumptions!$G$70+assumptions!$G$71+IF(38>=assumptions!$G$73,assumptions!$G$72,0))+assumptions!$G$74/12)+IF(38=E14,D14*assumptions!$G$75,0),0) | AS14: =IF(AND(39>=E14,OR(F14="",39<=F14)),(D14*(1+assumptions!$G$76)^3/12*(1+assumptions!$G$70+assumptions!$G$71+IF(39>=assumptions!$G$73,assumptions!$G$72,0))+assumptions!$G$74/12)+IF(39=E14,D14*assumptions!$G$75,0),0) | AT14: =IF(AND(40>=E14,OR(F14="",40<=F14)),(D14*(1+assumptions!$G$76)^3/12*(1+assumptions!$G$70+assumptions!$G$71+IF(40>=assumptions!$G$73,assumptions!$G$72,0))+assumptions!$G$74/12)+IF(40=E14,D14*assumptions!$G$75,0),0) | AU14: =IF(AND(41>=E14,OR(F14="",41<=F14)),(D14*(1+assumptions!$G$76)^3/12*(1+assumptions!$G$70+assumptions!$G$71+IF(41>=assumptions!$G$73,assumptions!$G$72,0))+assumptions!$G$74/12)+IF(41=E14,D14*assumptions!$G$75,0),0) | AV14: =IF(AND(42>=E14,OR(F14="",42<=F14)),(D14*(1+assumptions!$G$76)^3/12*(1+assumptions!$G$70+assumptions!$G$71+IF(42>=assumptions!$G$73,assumptions!$G$72,0))+assumptions!$G$74/12)+IF(42=E14,D14*assumptions!$G$75,0),0) | AW14: =IF(AND(43>=E14,OR(F14="",43<=F14)),(D14*(1+assumptions!$G$76)^3/12*(1+assumptions!$G$70+assumptions!$G$71+IF(43>=assumptions!$G$73,assumptions!$G$72,0))+assumptions!$G$74/12)+IF(43=E14,D14*assumptions!$G$75,0),0) | AX14: =IF(AND(44>=E14,OR(F14="",44<=F14)),(D14*(1+assumptions!$G$76)^3/12*(1+assumptions!$G$70+assumptions!$G$71+IF(44>=assumptions!$G$73,assumptions!$G$72,0))+assumptions!$G$74/12)+IF(44=E14,D14*assumptions!$G$75,0),0) | AY14: =IF(AND(45>=E14,OR(F14="",45<=F14)),(D14*(1+assumptions!$G$76)^3/12*(1+assumptions!$G$70+assumptions!$G$71+IF(45>=assumptions!$G$73,assumptions!$G$72,0))+assumptions!$G$74/12)+IF(45=E14,D14*assumptions!$G$75,0),0) | AZ14: =IF(AND(46>=E14,OR(F14="",46<=F14)),(D14*(1+assumptions!$G$76)^3/12*(1+assumptions!$G$70+assumptions!$G$71+IF(46>=assumptions!$G$73,assumptions!$G$72,0))+assumptions!$G$74/12)+IF(46=E14,D14*assumptions!$G$75,0),0) | BA14: =IF(AND(47>=E14,OR(F14="",47<=F14)),(D14*(1+assumptions!$G$76)^3/12*(1+assumptions!$G$70+assumptions!$G$71+IF(47>=assumptions!$G$73,assumptions!$G$72,0))+assumptions!$G$74/12)+IF(47=E14,D14*assumptions!$G$75,0),0) | BB14: =IF(AND(48>=E14,OR(F14="",48<=F14)),(D14*(1+assumptions!$G$76)^3/12*(1+assumptions!$G$70+assumptions!$G$71+IF(48>=assumptions!$G$73,assumptions!$G$72,0))+assumptions!$G$74/12)+IF(48=E14,D14*assumptions!$G$75,0),0) | BC14: =IF(AND(49>=E14,OR(F14="",49<=F14)),(D14*(1+assumptions!$G$76)^4/12*(1+assumptions!$G$70+assumptions!$G$71+IF(49>=assumptions!$G$73,assumptions!$G$72,0))+assumptions!$G$74/12)+IF(49=E14,D14*assumptions!$G$75,0),0) | BD14: =IF(AND(50>=E14,OR(F14="",50<=F14)),(D14*(1+assumptions!$G$76)^4/12*(1+assumptions!$G$70+assumptions!$G$71+IF(50>=assumptions!$G$73,assumptions!$G$72,0))+assumptions!$G$74/12)+IF(50=E14,D14*assumptions!$G$75,0),0) | BE14: =IF(AND(51>=E14,OR(F14="",51<=F14)),(D14*(1+assumptions!$G$76)^4/12*(1+assumptions!$G$70+assumptions!$G$71+IF(51>=assumptions!$G$73,assumptions!$G$72,0))+assumptions!$G$74/12)+IF(51=E14,D14*assumptions!$G$75,0),0) | BF14: =IF(AND(52>=E14,OR(F14="",52<=F14)),(D14*(1+assumptions!$G$76)^4/12*(1+assumptions!$G$70+assumptions!$G$71+IF(52>=assumptions!$G$73,assumptions!$G$72,0))+assumptions!$G$74/12)+IF(52=E14,D14*assumptions!$G$75,0),0) | BG14: =IF(AND(53>=E14,OR(F14="",53<=F14)),(D14*(1+assumptions!$G$76)^4/12*(1+assumptions!$G$70+assumptions!$G$71+IF(53>=assumptions!$G$73,assumptions!$G$72,0))+assumptions!$G$74/12)+IF(53=E14,D14*assumptions!$G$75,0),0) | BH14: =IF(AND(54>=E14,OR(F14="",54<=F14)),(D14*(1+assumptions!$G$76)^4/12*(1+assumptions!$G$70+assumptions!$G$71+IF(54>=assumptions!$G$73,assumptions!$G$72,0))+assumptions!$G$74/12)+IF(54=E14,D14*assumptions!$G$75,0),0) | BI14: =IF(AND(55>=E14,OR(F14="",55<=F14)),(D14*(1+assumptions!$G$76)^4/12*(1+assumptions!$G$70+assumptions!$G$71+IF(55>=assumptions!$G$73,assumptions!$G$72,0))+assumptions!$G$74/12)+IF(55=E14,D14*assumptions!$G$75,0),0) | BJ14: =IF(AND(56>=E14,OR(F14="",56<=F14)),(D14*(1+assumptions!$G$76)^4/12*(1+assumptions!$G$70+assumptions!$G$71+IF(56>=assumptions!$G$73,assumptions!$G$72,0))+assumptions!$G$74/12)+IF(56=E14,D14*assumptions!$G$75,0),0) | BK14: =IF(AND(57>=E14,OR(F14="",57<=F14)),(D14*(1+assumptions!$G$76)^4/12*(1+assumptions!$G$70+assumptions!$G$71+IF(57>=assumptions!$G$73,assumptions!$G$72,0))+assumptions!$G$74/12)+IF(57=E14,D14*assumptions!$G$75,0),0) | BL14: =IF(AND(58>=E14,OR(F14="",58<=F14)),(D14*(1+assumptions!$G$76)^4/12*(1+assumptions!$G$70+assumptions!$G$71+IF(58>=assumptions!$G$73,assumptions!$G$72,0))+assumptions!$G$74/12)+IF(58=E14,D14*assumptions!$G$75,0),0) | BM14: =IF(AND(59>=E14,OR(F14="",59<=F14)),(D14*(1+assumptions!$G$76)^4/12*(1+assumptions!$G$70+assumptions!$G$71+IF(59>=assumptions!$G$73,assumptions!$G$72,0))+assumptions!$G$74/12)+IF(59=E14,D14*assumptions!$G$75,0),0) | BN14: =IF(AND(60>=E14,OR(F14="",60<=F14)),(D14*(1+assumptions!$G$76)^4/12*(1+assumptions!$G$70+assumptions!$G$71+IF(60>=assumptions!$G$73,assumptions!$G$72,0))+assumptions!$G$74/12)+IF(60=E14,D14*assumptions!$G$75,0),0)
A15: 12 | B15: Growth marketer | C15: growth | D15: 60000 | E15: 9 | G15: =IF(AND(1>=E15,OR(F15="",1<=F15)),(D15*(1+assumptions!$G$76)^0/12*(1+assumptions!$G$70+assumptions!$G$71+IF(1>=assumptions!$G$73,assumptions!$G$72,0))+assumptions!$G$74/12)+IF(1=E15,D15*assumptions!$G$75,0),0) | H15: =IF(AND(2>=E15,OR(F15="",2<=F15)),(D15*(1+assumptions!$G$76)^0/12*(1+assumptions!$G$70+assumptions!$G$71+IF(2>=assumptions!$G$73,assumptions!$G$72,0))+assumptions!$G$74/12)+IF(2=E15,D15*assumptions!$G$75,0),0) | I15: =IF(AND(3>=E15,OR(F15="",3<=F15)),(D15*(1+assumptions!$G$76)^0/12*(1+assumptions!$G$70+assumptions!$G$71+IF(3>=assumptions!$G$73,assumptions!$G$72,0))+assumptions!$G$74/12)+IF(3=E15,D15*assumptions!$G$75,0),0) | J15: =IF(AND(4>=E15,OR(F15="",4<=F15)),(D15*(1+assumptions!$G$76)^0/12*(1+assumptions!$G$70+assumptions!$G$71+IF(4>=assumptions!$G$73,assumptions!$G$72,0))+assumptions!$G$74/12)+IF(4=E15,D15*assumptions!$G$75,0),0) | K15: =IF(AND(5>=E15,OR(F15="",5<=F15)),(D15*(1+assumptions!$G$76)^0/12*(1+assumptions!$G$70+assumptions!$G$71+IF(5>=assumptions!$G$73,assumptions!$G$72,0))+assumptions!$G$74/12)+IF(5=E15,D15*assumptions!$G$75,0),0) | L15: =IF(AND(6>=E15,OR(F15="",6<=F15)),(D15*(1+assumptions!$G$76)^0/12*(1+assumptions!$G$70+assumptions!$G$71+IF(6>=assumptions!$G$73,assumptions!$G$72,0))+assumptions!$G$74/12)+IF(6=E15,D15*assumptions!$G$75,0),0) | M15: =IF(AND(7>=E15,OR(F15="",7<=F15)),(D15*(1+assumptions!$G$76)^0/12*(1+assumptions!$G$70+assumptions!$G$71+IF(7>=assumptions!$G$73,assumptions!$G$72,0))+assumptions!$G$74/12)+IF(7=E15,D15*assumptions!$G$75,0),0) | N15: =IF(AND(8>=E15,OR(F15="",8<=F15)),(D15*(1+assumptions!$G$76)^0/12*(1+assumptions!$G$70+assumptions!$G$71+IF(8>=assumptions!$G$73,assumptions!$G$72,0))+assumptions!$G$74/12)+IF(8=E15,D15*assumptions!$G$75,0),0) | O15: =IF(AND(9>=E15,OR(F15="",9<=F15)),(D15*(1+assumptions!$G$76)^0/12*(1+assumptions!$G$70+assumptions!$G$71+IF(9>=assumptions!$G$73,assumptions!$G$72,0))+assumptions!$G$74/12)+IF(9=E15,D15*assumptions!$G$75,0),0) | P15: =IF(AND(10>=E15,OR(F15="",10<=F15)),(D15*(1+assumptions!$G$76)^0/12*(1+assumptions!$G$70+assumptions!$G$71+IF(10>=assumptions!$G$73,assumptions!$G$72,0))+assumptions!$G$74/12)+IF(10=E15,D15*assumptions!$G$75,0),0) | Q15: =IF(AND(11>=E15,OR(F15="",11<=F15)),(D15*(1+assumptions!$G$76)^0/12*(1+assumptions!$G$70+assumptions!$G$71+IF(11>=assumptions!$G$73,assumptions!$G$72,0))+assumptions!$G$74/12)+IF(11=E15,D15*assumptions!$G$75,0),0) | R15: =IF(AND(12>=E15,OR(F15="",12<=F15)),(D15*(1+assumptions!$G$76)^0/12*(1+assumptions!$G$70+assumptions!$G$71+IF(12>=assumptions!$G$73,assumptions!$G$72,0))+assumptions!$G$74/12)+IF(12=E15,D15*assumptions!$G$75,0),0) | S15: =IF(AND(13>=E15,OR(F15="",13<=F15)),(D15*(1+assumptions!$G$76)^1/12*(1+assumptions!$G$70+assumptions!$G$71+IF(13>=assumptions!$G$73,assumptions!$G$72,0))+assumptions!$G$74/12)+IF(13=E15,D15*assumptions!$G$75,0),0) | T15: =IF(AND(14>=E15,OR(F15="",14<=F15)),(D15*(1+assumptions!$G$76)^1/12*(1+assumptions!$G$70+assumptions!$G$71+IF(14>=assumptions!$G$73,assumptions!$G$72,0))+assumptions!$G$74/12)+IF(14=E15,D15*assumptions!$G$75,0),0) | U15: =IF(AND(15>=E15,OR(F15="",15<=F15)),(D15*(1+assumptions!$G$76)^1/12*(1+assumptions!$G$70+assumptions!$G$71+IF(15>=assumptions!$G$73,assumptions!$G$72,0))+assumptions!$G$74/12)+IF(15=E15,D15*assumptions!$G$75,0),0) | V15: =IF(AND(16>=E15,OR(F15="",16<=F15)),(D15*(1+assumptions!$G$76)^1/12*(1+assumptions!$G$70+assumptions!$G$71+IF(16>=assumptions!$G$73,assumptions!$G$72,0))+assumptions!$G$74/12)+IF(16=E15,D15*assumptions!$G$75,0),0) | W15: =IF(AND(17>=E15,OR(F15="",17<=F15)),(D15*(1+assumptions!$G$76)^1/12*(1+assumptions!$G$70+assumptions!$G$71+IF(17>=assumptions!$G$73,assumptions!$G$72,0))+assumptions!$G$74/12)+IF(17=E15,D15*assumptions!$G$75,0),0) | X15: =IF(AND(18>=E15,OR(F15="",18<=F15)),(D15*(1+assumptions!$G$76)^1/12*(1+assumptions!$G$70+assumptions!$G$71+IF(18>=assumptions!$G$73,assumptions!$G$72,0))+assumptions!$G$74/12)+IF(18=E15,D15*assumptions!$G$75,0),0) | Y15: =IF(AND(19>=E15,OR(F15="",19<=F15)),(D15*(1+assumptions!$G$76)^1/12*(1+assumptions!$G$70+assumptions!$G$71+IF(19>=assumptions!$G$73,assumptions!$G$72,0))+assumptions!$G$74/12)+IF(19=E15,D15*assumptions!$G$75,0),0) | Z15: =IF(AND(20>=E15,OR(F15="",20<=F15)),(D15*(1+assumptions!$G$76)^1/12*(1+assumptions!$G$70+assumptions!$G$71+IF(20>=assumptions!$G$73,assumptions!$G$72,0))+assumptions!$G$74/12)+IF(20=E15,D15*assumptions!$G$75,0),0) | AA15: =IF(AND(21>=E15,OR(F15="",21<=F15)),(D15*(1+assumptions!$G$76)^1/12*(1+assumptions!$G$70+assumptions!$G$71+IF(21>=assumptions!$G$73,assumptions!$G$72,0))+assumptions!$G$74/12)+IF(21=E15,D15*assumptions!$G$75,0),0) | AB15: =IF(AND(22>=E15,OR(F15="",22<=F15)),(D15*(1+assumptions!$G$76)^1/12*(1+assumptions!$G$70+assumptions!$G$71+IF(22>=assumptions!$G$73,assumptions!$G$72,0))+assumptions!$G$74/12)+IF(22=E15,D15*assumptions!$G$75,0),0) | AC15: =IF(AND(23>=E15,OR(F15="",23<=F15)),(D15*(1+assumptions!$G$76)^1/12*(1+assumptions!$G$70+assumptions!$G$71+IF(23>=assumptions!$G$73,assumptions!$G$72,0))+assumptions!$G$74/12)+IF(23=E15,D15*assumptions!$G$75,0),0) | AD15: =IF(AND(24>=E15,OR(F15="",24<=F15)),(D15*(1+assumptions!$G$76)^1/12*(1+assumptions!$G$70+assumptions!$G$71+IF(24>=assumptions!$G$73,assumptions!$G$72,0))+assumptions!$G$74/12)+IF(24=E15,D15*assumptions!$G$75,0),0) | AE15: =IF(AND(25>=E15,OR(F15="",25<=F15)),(D15*(1+assumptions!$G$76)^2/12*(1+assumptions!$G$70+assumptions!$G$71+IF(25>=assumptions!$G$73,assumptions!$G$72,0))+assumptions!$G$74/12)+IF(25=E15,D15*assumptions!$G$75,0),0) | AF15: =IF(AND(26>=E15,OR(F15="",26<=F15)),(D15*(1+assumptions!$G$76)^2/12*(1+assumptions!$G$70+assumptions!$G$71+IF(26>=assumptions!$G$73,assumptions!$G$72,0))+assumptions!$G$74/12)+IF(26=E15,D15*assumptions!$G$75,0),0) | AG15: =IF(AND(27>=E15,OR(F15="",27<=F15)),(D15*(1+assumptions!$G$76)^2/12*(1+assumptions!$G$70+assumptions!$G$71+IF(27>=assumptions!$G$73,assumptions!$G$72,0))+assumptions!$G$74/12)+IF(27=E15,D15*assumptions!$G$75,0),0) | AH15: =IF(AND(28>=E15,OR(F15="",28<=F15)),(D15*(1+assumptions!$G$76)^2/12*(1+assumptions!$G$70+assumptions!$G$71+IF(28>=assumptions!$G$73,assumptions!$G$72,0))+assumptions!$G$74/12)+IF(28=E15,D15*assumptions!$G$75,0),0) | AI15: =IF(AND(29>=E15,OR(F15="",29<=F15)),(D15*(1+assumptions!$G$76)^2/12*(1+assumptions!$G$70+assumptions!$G$71+IF(29>=assumptions!$G$73,assumptions!$G$72,0))+assumptions!$G$74/12)+IF(29=E15,D15*assumptions!$G$75,0),0) | AJ15: =IF(AND(30>=E15,OR(F15="",30<=F15)),(D15*(1+assumptions!$G$76)^2/12*(1+assumptions!$G$70+assumptions!$G$71+IF(30>=assumptions!$G$73,assumptions!$G$72,0))+assumptions!$G$74/12)+IF(30=E15,D15*assumptions!$G$75,0),0) | AK15: =IF(AND(31>=E15,OR(F15="",31<=F15)),(D15*(1+assumptions!$G$76)^2/12*(1+assumptions!$G$70+assumptions!$G$71+IF(31>=assumptions!$G$73,assumptions!$G$72,0))+assumptions!$G$74/12)+IF(31=E15,D15*assumptions!$G$75,0),0) | AL15: =IF(AND(32>=E15,OR(F15="",32<=F15)),(D15*(1+assumptions!$G$76)^2/12*(1+assumptions!$G$70+assumptions!$G$71+IF(32>=assumptions!$G$73,assumptions!$G$72,0))+assumptions!$G$74/12)+IF(32=E15,D15*assumptions!$G$75,0),0) | AM15: =IF(AND(33>=E15,OR(F15="",33<=F15)),(D15*(1+assumptions!$G$76)^2/12*(1+assumptions!$G$70+assumptions!$G$71+IF(33>=assumptions!$G$73,assumptions!$G$72,0))+assumptions!$G$74/12)+IF(33=E15,D15*assumptions!$G$75,0),0) | AN15: =IF(AND(34>=E15,OR(F15="",34<=F15)),(D15*(1+assumptions!$G$76)^2/12*(1+assumptions!$G$70+assumptions!$G$71+IF(34>=assumptions!$G$73,assumptions!$G$72,0))+assumptions!$G$74/12)+IF(34=E15,D15*assumptions!$G$75,0),0) | AO15: =IF(AND(35>=E15,OR(F15="",35<=F15)),(D15*(1+assumptions!$G$76)^2/12*(1+assumptions!$G$70+assumptions!$G$71+IF(35>=assumptions!$G$73,assumptions!$G$72,0))+assumptions!$G$74/12)+IF(35=E15,D15*assumptions!$G$75,0),0) | AP15: =IF(AND(36>=E15,OR(F15="",36<=F15)),(D15*(1+assumptions!$G$76)^2/12*(1+assumptions!$G$70+assumptions!$G$71+IF(36>=assumptions!$G$73,assumptions!$G$72,0))+assumptions!$G$74/12)+IF(36=E15,D15*assumptions!$G$75,0),0) | AQ15: =IF(AND(37>=E15,OR(F15="",37<=F15)),(D15*(1+assumptions!$G$76)^3/12*(1+assumptions!$G$70+assumptions!$G$71+IF(37>=assumptions!$G$73,assumptions!$G$72,0))+assumptions!$G$74/12)+IF(37=E15,D15*assumptions!$G$75,0),0) | AR15: =IF(AND(38>=E15,OR(F15="",38<=F15)),(D15*(1+assumptions!$G$76)^3/12*(1+assumptions!$G$70+assumptions!$G$71+IF(38>=assumptions!$G$73,assumptions!$G$72,0))+assumptions!$G$74/12)+IF(38=E15,D15*assumptions!$G$75,0),0) | AS15: =IF(AND(39>=E15,OR(F15="",39<=F15)),(D15*(1+assumptions!$G$76)^3/12*(1+assumptions!$G$70+assumptions!$G$71+IF(39>=assumptions!$G$73,assumptions!$G$72,0))+assumptions!$G$74/12)+IF(39=E15,D15*assumptions!$G$75,0),0) | AT15: =IF(AND(40>=E15,OR(F15="",40<=F15)),(D15*(1+assumptions!$G$76)^3/12*(1+assumptions!$G$70+assumptions!$G$71+IF(40>=assumptions!$G$73,assumptions!$G$72,0))+assumptions!$G$74/12)+IF(40=E15,D15*assumptions!$G$75,0),0) | AU15: =IF(AND(41>=E15,OR(F15="",41<=F15)),(D15*(1+assumptions!$G$76)^3/12*(1+assumptions!$G$70+assumptions!$G$71+IF(41>=assumptions!$G$73,assumptions!$G$72,0))+assumptions!$G$74/12)+IF(41=E15,D15*assumptions!$G$75,0),0) | AV15: =IF(AND(42>=E15,OR(F15="",42<=F15)),(D15*(1+assumptions!$G$76)^3/12*(1+assumptions!$G$70+assumptions!$G$71+IF(42>=assumptions!$G$73,assumptions!$G$72,0))+assumptions!$G$74/12)+IF(42=E15,D15*assumptions!$G$75,0),0) | AW15: =IF(AND(43>=E15,OR(F15="",43<=F15)),(D15*(1+assumptions!$G$76)^3/12*(1+assumptions!$G$70+assumptions!$G$71+IF(43>=assumptions!$G$73,assumptions!$G$72,0))+assumptions!$G$74/12)+IF(43=E15,D15*assumptions!$G$75,0),0) | AX15: =IF(AND(44>=E15,OR(F15="",44<=F15)),(D15*(1+assumptions!$G$76)^3/12*(1+assumptions!$G$70+assumptions!$G$71+IF(44>=assumptions!$G$73,assumptions!$G$72,0))+assumptions!$G$74/12)+IF(44=E15,D15*assumptions!$G$75,0),0) | AY15: =IF(AND(45>=E15,OR(F15="",45<=F15)),(D15*(1+assumptions!$G$76)^3/12*(1+assumptions!$G$70+assumptions!$G$71+IF(45>=assumptions!$G$73,assumptions!$G$72,0))+assumptions!$G$74/12)+IF(45=E15,D15*assumptions!$G$75,0),0) | AZ15: =IF(AND(46>=E15,OR(F15="",46<=F15)),(D15*(1+assumptions!$G$76)^3/12*(1+assumptions!$G$70+assumptions!$G$71+IF(46>=assumptions!$G$73,assumptions!$G$72,0))+assumptions!$G$74/12)+IF(46=E15,D15*assumptions!$G$75,0),0) | BA15: =IF(AND(47>=E15,OR(F15="",47<=F15)),(D15*(1+assumptions!$G$76)^3/12*(1+assumptions!$G$70+assumptions!$G$71+IF(47>=assumptions!$G$73,assumptions!$G$72,0))+assumptions!$G$74/12)+IF(47=E15,D15*assumptions!$G$75,0),0) | BB15: =IF(AND(48>=E15,OR(F15="",48<=F15)),(D15*(1+assumptions!$G$76)^3/12*(1+assumptions!$G$70+assumptions!$G$71+IF(48>=assumptions!$G$73,assumptions!$G$72,0))+assumptions!$G$74/12)+IF(48=E15,D15*assumptions!$G$75,0),0) | BC15: =IF(AND(49>=E15,OR(F15="",49<=F15)),(D15*(1+assumptions!$G$76)^4/12*(1+assumptions!$G$70+assumptions!$G$71+IF(49>=assumptions!$G$73,assumptions!$G$72,0))+assumptions!$G$74/12)+IF(49=E15,D15*assumptions!$G$75,0),0) | BD15: =IF(AND(50>=E15,OR(F15="",50<=F15)),(D15*(1+assumptions!$G$76)^4/12*(1+assumptions!$G$70+assumptions!$G$71+IF(50>=assumptions!$G$73,assumptions!$G$72,0))+assumptions!$G$74/12)+IF(50=E15,D15*assumptions!$G$75,0),0) | BE15: =IF(AND(51>=E15,OR(F15="",51<=F15)),(D15*(1+assumptions!$G$76)^4/12*(1+assumptions!$G$70+assumptions!$G$71+IF(51>=assumptions!$G$73,assumptions!$G$72,0))+assumptions!$G$74/12)+IF(51=E15,D15*assumptions!$G$75,0),0) | BF15: =IF(AND(52>=E15,OR(F15="",52<=F15)),(D15*(1+assumptions!$G$76)^4/12*(1+assumptions!$G$70+assumptions!$G$71+IF(52>=assumptions!$G$73,assumptions!$G$72,0))+assumptions!$G$74/12)+IF(52=E15,D15*assumptions!$G$75,0),0) | BG15: =IF(AND(53>=E15,OR(F15="",53<=F15)),(D15*(1+assumptions!$G$76)^4/12*(1+assumptions!$G$70+assumptions!$G$71+IF(53>=assumptions!$G$73,assumptions!$G$72,0))+assumptions!$G$74/12)+IF(53=E15,D15*assumptions!$G$75,0),0) | BH15: =IF(AND(54>=E15,OR(F15="",54<=F15)),(D15*(1+assumptions!$G$76)^4/12*(1+assumptions!$G$70+assumptions!$G$71+IF(54>=assumptions!$G$73,assumptions!$G$72,0))+assumptions!$G$74/12)+IF(54=E15,D15*assumptions!$G$75,0),0) | BI15: =IF(AND(55>=E15,OR(F15="",55<=F15)),(D15*(1+assumptions!$G$76)^4/12*(1+assumptions!$G$70+assumptions!$G$71+IF(55>=assumptions!$G$73,assumptions!$G$72,0))+assumptions!$G$74/12)+IF(55=E15,D15*assumptions!$G$75,0),0) | BJ15: =IF(AND(56>=E15,OR(F15="",56<=F15)),(D15*(1+assumptions!$G$76)^4/12*(1+assumptions!$G$70+assumptions!$G$71+IF(56>=assumptions!$G$73,assumptions!$G$72,0))+assumptions!$G$74/12)+IF(56=E15,D15*assumptions!$G$75,0),0) | BK15: =IF(AND(57>=E15,OR(F15="",57<=F15)),(D15*(1+assumptions!$G$76)^4/12*(1+assumptions!$G$70+assumptions!$G$71+IF(57>=assumptions!$G$73,assumptions!$G$72,0))+assumptions!$G$74/12)+IF(57=E15,D15*assumptions!$G$75,0),0) | BL15: =IF(AND(58>=E15,OR(F15="",58<=F15)),(D15*(1+assumptions!$G$76)^4/12*(1+assumptions!$G$70+assumptions!$G$71+IF(58>=assumptions!$G$73,assumptions!$G$72,0))+assumptions!$G$74/12)+IF(58=E15,D15*assumptions!$G$75,0),0) | BM15: =IF(AND(59>=E15,OR(F15="",59<=F15)),(D15*(1+assumptions!$G$76)^4/12*(1+assumptions!$G$70+assumptions!$G$71+IF(59>=assumptions!$G$73,assumptions!$G$72,0))+assumptions!$G$74/12)+IF(59=E15,D15*assumptions!$G$75,0),0) | BN15: =IF(AND(60>=E15,OR(F15="",60<=F15)),(D15*(1+assumptions!$G$76)^4/12*(1+assumptions!$G$70+assumptions!$G$71+IF(60>=assumptions!$G$73,assumptions!$G$72,0))+assumptions!$G$74/12)+IF(60=E15,D15*assumptions!$G$75,0),0)
... A42: 39 | B42: Head of International | C42: exec | D42: 110000 | E42: 60 | G42: =IF(AND(1>=E42,OR(F42="",1<=F42)),(D42*(1+assumptions!$G$76)^0/12*(1+assumptions!$G$70+assumptions!$G$71+IF(1>=assumptions!$G$73,assumptions!$G$72,0))+assumptions!$G$74/12)+IF(1=E42,D42*assumptions!$G$75,0),0) | H42: =IF(AND(2>=E42,OR(F42="",2<=F42)),(D42*(1+assumptions!$G$76)^0/12*(1+assumptions!$G$70+assumptions!$G$71+IF(2>=assumptions!$G$73,assumptions!$G$72,0))+assumptions!$G$74/12)+IF(2=E42,D42*assumptions!$G$75,0),0) | I42: =IF(AND(3>=E42,OR(F42="",3<=F42)),(D42*(1+assumptions!$G$76)^0/12*(1+assumptions!$G$70+assumptions!$G$71+IF(3>=assumptions!$G$73,assumptions!$G$72,0))+assumptions!$G$74/12)+IF(3=E42,D42*assumptions!$G$75,0),0) | J42: =IF(AND(4>=E42,OR(F42="",4<=F42)),(D42*(1+assumptions!$G$76)^0/12*(1+assumptions!$G$70+assumptions!$G$71+IF(4>=assumptions!$G$73,assumptions!$G$72,0))+assumptions!$G$74/12)+IF(4=E42,D42*assumptions!$G$75,0),0) | K42: =IF(AND(5>=E42,OR(F42="",5<=F42)),(D42*(1+assumptions!$G$76)^0/12*(1+assumptions!$G$70+assumptions!$G$71+IF(5>=assumptions!$G$73,assumptions!$G$72,0))+assumptions!$G$74/12)+IF(5=E42,D42*assumptions!$G$75,0),0) | L42: =IF(AND(6>=E42,OR(F42="",6<=F42)),(D42*(1+assumptions!$G$76)^0/12*(1+assumptions!$G$70+assumptions!$G$71+IF(6>=assumptions!$G$73,assumptions!$G$72,0))+assumptions!$G$74/12)+IF(6=E42,D42*assumptions!$G$75,0),0) | M42: =IF(AND(7>=E42,OR(F42="",7<=F42)),(D42*(1+assumptions!$G$76)^0/12*(1+assumptions!$G$70+assumptions!$G$71+IF(7>=assumptions!$G$73,assumptions!$G$72,0))+assumptions!$G$74/12)+IF(7=E42,D42*assumptions!$G$75,0),0) | N42: =IF(AND(8>=E42,OR(F42="",8<=F42)),(D42*(1+assumptions!$G$76)^0/12*(1+assumptions!$G$70+assumptions!$G$71+IF(8>=assumptions!$G$73,assumptions!$G$72,0))+assumptions!$G$74/12)+IF(8=E42,D42*assumptions!$G$75,0),0) | O42: =IF(AND(9>=E42,OR(F42="",9<=F42)),(D42*(1+assumptions!$G$76)^0/12*(1+assumptions!$G$70+assumptions!$G$71+IF(9>=assumptions!$G$73,assumptions!$G$72,0))+assumptions!$G$74/12)+IF(9=E42,D42*assumptions!$G$75,0),0) | P42: =IF(AND(10>=E42,OR(F42="",10<=F42)),(D42*(1+assumptions!$G$76)^0/12*(1+assumptions!$G$70+assumptions!$G$71+IF(10>=assumptions!$G$73,assumptions!$G$72,0))+assumptions!$G$74/12)+IF(10=E42,D42*assumptions!$G$75,0),0) | Q42: =IF(AND(11>=E42,OR(F42="",11<=F42)),(D42*(1+assumptions!$G$76)^0/12*(1+assumptions!$G$70+assumptions!$G$71+IF(11>=assumptions!$G$73,assumptions!$G$72,0))+assumptions!$G$74/12)+IF(11=E42,D42*assumptions!$G$75,0),0) | R42: =IF(AND(12>=E42,OR(F42="",12<=F42)),(D42*(1+assumptions!$G$76)^0/12*(1+assumptions!$G$70+assumptions!$G$71+IF(12>=assumptions!$G$73,assumptions!$G$72,0))+assumptions!$G$74/12)+IF(12=E42,D42*assumptions!$G$75,0),0) | S42: =IF(AND(13>=E42,OR(F42="",13<=F42)),(D42*(1+assumptions!$G$76)^1/12*(1+assumptions!$G$70+assumptions!$G$71+IF(13>=assumptions!$G$73,assumptions!$G$72,0))+assumptions!$G$74/12)+IF(13=E42,D42*assumptions!$G$75,0),0) | T42: =IF(AND(14>=E42,OR(F42="",14<=F42)),(D42*(1+assumptions!$G$76)^1/12*(1+assumptions!$G$70+assumptions!$G$71+IF(14>=assumptions!$G$73,assumptions!$G$72,0))+assumptions!$G$74/12)+IF(14=E42,D42*assumptions!$G$75,0),0) | U42: =IF(AND(15>=E42,OR(F42="",15<=F42)),(D42*(1+assumptions!$G$76)^1/12*(1+assumptions!$G$70+assumptions!$G$71+IF(15>=assumptions!$G$73,assumptions!$G$72,0))+assumptions!$G$74/12)+IF(15=E42,D42*assumptions!$G$75,0),0) | V42: =IF(AND(16>=E42,OR(F42="",16<=F42)),(D42*(1+assumptions!$G$76)^1/12*(1+assumptions!$G$70+assumptions!$G$71+IF(16>=assumptions!$G$73,assumptions!$G$72,0))+assumptions!$G$74/12)+IF(16=E42,D42*assumptions!$G$75,0),0) | W42: =IF(AND(17>=E42,OR(F42="",17<=F42)),(D42*(1+assumptions!$G$76)^1/12*(1+assumptions!$G$70+assumptions!$G$71+IF(17>=assumptions!$G$73,assumptions!$G$72,0))+assumptions!$G$74/12)+IF(17=E42,D42*assumptions!$G$75,0),0) | X42: =IF(AND(18>=E42,OR(F42="",18<=F42)),(D42*(1+assumptions!$G$76)^1/12*(1+assumptions!$G$70+assumptions!$G$71+IF(18>=assumptions!$G$73,assumptions!$G$72,0))+assumptions!$G$74/12)+IF(18=E42,D42*assumptions!$G$75,0),0) | Y42: =IF(AND(19>=E42,OR(F42="",19<=F42)),(D42*(1+assumptions!$G$76)^1/12*(1+assumptions!$G$70+assumptions!$G$71+IF(19>=assumptions!$G$73,assumptions!$G$72,0))+assumptions!$G$74/12)+IF(19=E42,D42*assumptions!$G$75,0),0) | Z42: =IF(AND(20>=E42,OR(F42="",20<=F42)),(D42*(1+assumptions!$G$76)^1/12*(1+assumptions!$G$70+assumptions!$G$71+IF(20>=assumptions!$G$73,assumptions!$G$72,0))+assumptions!$G$74/12)+IF(20=E42,D42*assumptions!$G$75,0),0) | AA42: =IF(AND(21>=E42,OR(F42="",21<=F42)),(D42*(1+assumptions!$G$76)^1/12*(1+assumptions!$G$70+assumptions!$G$71+IF(21>=assumptions!$G$73,assumptions!$G$72,0))+assumptions!$G$74/12)+IF(21=E42,D42*assumptions!$G$75,0),0) | AB42: =IF(AND(22>=E42,OR(F42="",22<=F42)),(D42*(1+assumptions!$G$76)^1/12*(1+assumptions!$G$70+assumptions!$G$71+IF(22>=assumptions!$G$73,assumptions!$G$72,0))+assumptions!$G$74/12)+IF(22=E42,D42*assumptions!$G$75,0),0) | AC42: =IF(AND(23>=E42,OR(F42="",23<=F42)),(D42*(1+assumptions!$G$76)^1/12*(1+assumptions!$G$70+assumptions!$G$71+IF(23>=assumptions!$G$73,assumptions!$G$72,0))+assumptions!$G$74/12)+IF(23=E42,D42*assumptions!$G$75,0),0) | AD42: =IF(AND(24>=E42,OR(F42="",24<=F42)),(D42*(1+assumptions!$G$76)^1/12*(1+assumptions!$G$70+assumptions!$G$71+IF(24>=assumptions!$G$73,assumptions!$G$72,0))+assumptions!$G$74/12)+IF(24=E42,D42*assumptions!$G$75,0),0) | AE42: =IF(AND(25>=E42,OR(F42="",25<=F42)),(D42*(1+assumptions!$G$76)^2/12*(1+assumptions!$G$70+assumptions!$G$71+IF(25>=assumptions!$G$73,assumptions!$G$72,0))+assumptions!$G$74/12)+IF(25=E42,D42*assumptions!$G$75,0),0) | AF42: =IF(AND(26>=E42,OR(F42="",26<=F42)),(D42*(1+assumptions!$G$76)^2/12*(1+assumptions!$G$70+assumptions!$G$71+IF(26>=assumptions!$G$73,assumptions!$G$72,0))+assumptions!$G$74/12)+IF(26=E42,D42*assumptions!$G$75,0),0) | AG42: =IF(AND(27>=E42,OR(F42="",27<=F42)),(D42*(1+assumptions!$G$76)^2/12*(1+assumptions!$G$70+assumptions!$G$71+IF(27>=assumptions!$G$73,assumptions!$G$72,0))+assumptions!$G$74/12)+IF(27=E42,D42*assumptions!$G$75,0),0) | AH42: =IF(AND(28>=E42,OR(F42="",28<=F42)),(D42*(1+assumptions!$G$76)^2/12*(1+assumptions!$G$70+assumptions!$G$71+IF(28>=assumptions!$G$73,assumptions!$G$72,0))+assumptions!$G$74/12)+IF(28=E42,D42*assumptions!$G$75,0),0) | AI42: =IF(AND(29>=E42,OR(F42="",29<=F42)),(D42*(1+assumptions!$G$76)^2/12*(1+assumptions!$G$70+assumptions!$G$71+IF(29>=assumptions!$G$73,assumptions!$G$72,0))+assumptions!$G$74/12)+IF(29=E42,D42*assumptions!$G$75,0),0) | AJ42: =IF(AND(30>=E42,OR(F42="",30<=F42)),(D42*(1+assumptions!$G$76)^2/12*(1+assumptions!$G$70+assumptions!$G$71+IF(30>=assumptions!$G$73,assumptions!$G$72,0))+assumptions!$G$74/12)+IF(30=E42,D42*assumptions!$G$75,0),0) | AK42: =IF(AND(31>=E42,OR(F42="",31<=F42)),(D42*(1+assumptions!$G$76)^2/12*(1+assumptions!$G$70+assumptions!$G$71+IF(31>=assumptions!$G$73,assumptions!$G$72,0))+assumptions!$G$74/12)+IF(31=E42,D42*assumptions!$G$75,0),0) | AL42: =IF(AND(32>=E42,OR(F42="",32<=F42)),(D42*(1+assumptions!$G$76)^2/12*(1+assumptions!$G$70+assumptions!$G$71+IF(32>=assumptions!$G$73,assumptions!$G$72,0))+assumptions!$G$74/12)+IF(32=E42,D42*assumptions!$G$75,0),0) | AM42: =IF(AND(33>=E42,OR(F42="",33<=F42)),(D42*(1+assumptions!$G$76)^2/12*(1+assumptions!$G$70+assumptions!$G$71+IF(33>=assumptions!$G$73,assumptions!$G$72,0))+assumptions!$G$74/12)+IF(33=E42,D42*assumptions!$G$75,0),0) | AN42: =IF(AND(34>=E42,OR(F42="",34<=F42)),(D42*(1+assumptions!$G$76)^2/12*(1+assumptions!$G$70+assumptions!$G$71+IF(34>=assumptions!$G$73,assumptions!$G$72,0))+assumptions!$G$74/12)+IF(34=E42,D42*assumptions!$G$75,0),0) | AO42: =IF(AND(35>=E42,OR(F42="",35<=F42)),(D42*(1+assumptions!$G$76)^2/12*(1+assumptions!$G$70+assumptions!$G$71+IF(35>=assumptions!$G$73,assumptions!$G$72,0))+assumptions!$G$74/12)+IF(35=E42,D42*assumptions!$G$75,0),0) | AP42: =IF(AND(36>=E42,OR(F42="",36<=F42)),(D42*(1+assumptions!$G$76)^2/12*(1+assumptions!$G$70+assumptions!$G$71+IF(36>=assumptions!$G$73,assumptions!$G$72,0))+assumptions!$G$74/12)+IF(36=E42,D42*assumptions!$G$75,0),0) | AQ42: =IF(AND(37>=E42,OR(F42="",37<=F42)),(D42*(1+assumptions!$G$76)^3/12*(1+assumptions!$G$70+assumptions!$G$71+IF(37>=assumptions!$G$73,assumptions!$G$72,0))+assumptions!$G$74/12)+IF(37=E42,D42*assumptions!$G$75,0),0) | AR42: =IF(AND(38>=E42,OR(F42="",38<=F42)),(D42*(1+assumptions!$G$76)^3/12*(1+assumptions!$G$70+assumptions!$G$71+IF(38>=assumptions!$G$73,assumptions!$G$72,0))+assumptions!$G$74/12)+IF(38=E42,D42*assumptions!$G$75,0),0) | AS42: =IF(AND(39>=E42,OR(F42="",39<=F42)),(D42*(1+assumptions!$G$76)^3/12*(1+assumptions!$G$70+assumptions!$G$71+IF(39>=assumptions!$G$73,assumptions!$G$72,0))+assumptions!$G$74/12)+IF(39=E42,D42*assumptions!$G$75,0),0) | AT42: =IF(AND(40>=E42,OR(F42="",40<=F42)),(D42*(1+assumptions!$G$76)^3/12*(1+assumptions!$G$70+assumptions!$G$71+IF(40>=assumptions!$G$73,assumptions!$G$72,0))+assumptions!$G$74/12)+IF(40=E42,D42*assumptions!$G$75,0),0) | AU42: =IF(AND(41>=E42,OR(F42="",41<=F42)),(D42*(1+assumptions!$G$76)^3/12*(1+assumptions!$G$70+assumptions!$G$71+IF(41>=assumptions!$G$73,assumptions!$G$72,0))+assumptions!$G$74/12)+IF(41=E42,D42*assumptions!$G$75,0),0) | AV42: =IF(AND(42>=E42,OR(F42="",42<=F42)),(D42*(1+assumptions!$G$76)^3/12*(1+assumptions!$G$70+assumptions!$G$71+IF(42>=assumptions!$G$73,assumptions!$G$72,0))+assumptions!$G$74/12)+IF(42=E42,D42*assumptions!$G$75,0),0) | AW42: =IF(AND(43>=E42,OR(F42="",43<=F42)),(D42*(1+assumptions!$G$76)^3/12*(1+assumptions!$G$70+assumptions!$G$71+IF(43>=assumptions!$G$73,assumptions!$G$72,0))+assumptions!$G$74/12)+IF(43=E42,D42*assumptions!$G$75,0),0) | AX42: =IF(AND(44>=E42,OR(F42="",44<=F42)),(D42*(1+assumptions!$G$76)^3/12*(1+assumptions!$G$70+assumptions!$G$71+IF(44>=assumptions!$G$73,assumptions!$G$72,0))+assumptions!$G$74/12)+IF(44=E42,D42*assumptions!$G$75,0),0) | AY42: =IF(AND(45>=E42,OR(F42="",45<=F42)),(D42*(1+assumptions!$G$76)^3/12*(1+assumptions!$G$70+assumptions!$G$71+IF(45>=assumptions!$G$73,assumptions!$G$72,0))+assumptions!$G$74/12)+IF(45=E42,D42*assumptions!$G$75,0),0) | AZ42: =IF(AND(46>=E42,OR(F42="",46<=F42)),(D42*(1+assumptions!$G$76)^3/12*(1+assumptions!$G$70+assumptions!$G$71+IF(46>=assumptions!$G$73,assumptions!$G$72,0))+assumptions!$G$74/12)+IF(46=E42,D42*assumptions!$G$75,0),0) | BA42: =IF(AND(47>=E42,OR(F42="",47<=F42)),(D42*(1+assumptions!$G$76)^3/12*(1+assumptions!$G$70+assumptions!$G$71+IF(47>=assumptions!$G$73,assumptions!$G$72,0))+assumptions!$G$74/12)+IF(47=E42,D42*assumptions!$G$75,0),0) | BB42: =IF(AND(48>=E42,OR(F42="",48<=F42)),(D42*(1+assumptions!$G$76)^3/12*(1+assumptions!$G$70+assumptions!$G$71+IF(48>=assumptions!$G$73,assumptions!$G$72,0))+assumptions!$G$74/12)+IF(48=E42,D42*assumptions!$G$75,0),0) | BC42: =IF(AND(49>=E42,OR(F42="",49<=F42)),(D42*(1+assumptions!$G$76)^4/12*(1+assumptions!$G$70+assumptions!$G$71+IF(49>=assumptions!$G$73,assumptions!$G$72,0))+assumptions!$G$74/12)+IF(49=E42,D42*assumptions!$G$75,0),0) | BD42: =IF(AND(50>=E42,OR(F42="",50<=F42)),(D42*(1+assumptions!$G$76)^4/12*(1+assumptions!$G$70+assumptions!$G$71+IF(50>=assumptions!$G$73,assumptions!$G$72,0))+assumptions!$G$74/12)+IF(50=E42,D42*assumptions!$G$75,0),0) | BE42: =IF(AND(51>=E42,OR(F42="",51<=F42)),(D42*(1+assumptions!$G$76)^4/12*(1+assumptions!$G$70+assumptions!$G$71+IF(51>=assumptions!$G$73,assumptions!$G$72,0))+assumptions!$G$74/12)+IF(51=E42,D42*assumptions!$G$75,0),0) | BF42: =IF(AND(52>=E42,OR(F42="",52<=F42)),(D42*(1+assumptions!$G$76)^4/12*(1+assumptions!$G$70+assumptions!$G$71+IF(52>=assumptions!$G$73,assumptions!$G$72,0))+assumptions!$G$74/12)+IF(52=E42,D42*assumptions!$G$75,0),0) | BG42: =IF(AND(53>=E42,OR(F42="",53<=F42)),(D42*(1+assumptions!$G$76)^4/12*(1+assumptions!$G$70+assumptions!$G$71+IF(53>=assumptions!$G$73,assumptions!$G$72,0))+assumptions!$G$74/12)+IF(53=E42,D42*assumptions!$G$75,0),0) | BH42: =IF(AND(54>=E42,OR(F42="",54<=F42)),(D42*(1+assumptions!$G$76)^4/12*(1+assumptions!$G$70+assumptions!$G$71+IF(54>=assumptions!$G$73,assumptions!$G$72,0))+assumptions!$G$74/12)+IF(54=E42,D42*assumptions!$G$75,0),0) | BI42: =IF(AND(55>=E42,OR(F42="",55<=F42)),(D42*(1+assumptions!$G$76)^4/12*(1+assumptions!$G$70+assumptions!$G$71+IF(55>=assumptions!$G$73,assumptions!$G$72,0))+assumptions!$G$74/12)+IF(55=E42,D42*assumptions!$G$75,0),0) | BJ42: =IF(AND(56>=E42,OR(F42="",56<=F42)),(D42*(1+assumptions!$G$76)^4/12*(1+assumptions!$G$70+assumptions!$G$71+IF(56>=assumptions!$G$73,assumptions!$G$72,0))+assumptions!$G$74/12)+IF(56=E42,D42*assumptions!$G$75,0),0) | BK42: =IF(AND(57>=E42,OR(F42="",57<=F42)),(D42*(1+assumptions!$G$76)^4/12*(1+assumptions!$G$70+assumptions!$G$71+IF(57>=assumptions!$G$73,assumptions!$G$72,0))+assumptions!$G$74/12)+IF(57=E42,D42*assumptions!$G$75,0),0) | BL42: =IF(AND(58>=E42,OR(F42="",58<=F42)),(D42*(1+assumptions!$G$76)^4/12*(1+assumptions!$G$70+assumptions!$G$71+IF(58>=assumptions!$G$73,assumptions!$G$72,0))+assumptions!$G$74/12)+IF(58=E42,D42*assumptions!$G$75,0),0) | BM42: =IF(AND(59>=E42,OR(F42="",59<=F42)),(D42*(1+assumptions!$G$76)^4/12*(1+assumptions!$G$70+assumptions!$G$71+IF(59>=assumptions!$G$73,assumptions!$G$72,0))+assumptions!$G$74/12)+IF(59=E42,D42*assumptions!$G$75,0),0) | BN42: =IF(AND(60>=E42,OR(F42="",60<=F42)),(D42*(1+assumptions!$G$76)^4/12*(1+assumptions!$G$70+assumptions!$G$71+IF(60>=assumptions!$G$73,assumptions!$G$72,0))+assumptions!$G$74/12)+IF(60=E42,D42*assumptions!$G$75,0),0)
B44: Total loaded payroll | G44: =SUM(G4:G42) | H44: =SUM(H4:H42) | I44: =SUM(I4:I42) | J44: =SUM(J4:J42) | K44: =SUM(K4:K42) | L44: =SUM(L4:L42) | M44: =SUM(M4:M42) | N44: =SUM(N4:N42) | ... BN44: =SUM(BN4:BN42)
